Workbook

Sheet Resumo
A1: Projetos Rouanet 2027 – Revisão Art. 18 e planilhas orçamentárias (IN MinC 29/2026)
A2: Prazo de submissão: 31/10/2026 (IN 29, art. 5º). Valores orçados vêm das abas de cada projeto (fórmulas). Status/nota: revisão técnica dos documentos da pasta do Drive em 14/10/2026.
A4: # | B4: Projeto | C4: Frente | D4: Titular p/ carteira | E4: Tipo | F4: Valor pré-planejado | G4: Valor mínimo | H4: Valor total orçado | I4: Diferença | J4: Valor do projeto (base %) | K4: % Adm. | L4: % Acess./Divulg. | M4: % Captação | N4: Limites % e teto | O4: Produto principal – área / segmento (Anexo IV) | P4: Enquadr. | Q4: Campos SALIC OK | R4: PARCIAL | S4: AUSENTE | T4: Nota (0-10) | U4: Status | V4: Pendências críticas
A5: P01 | B5: Escola de Ofícios do Espetáculo | C5: 01. Cultura | D5: Educare | E5: PJ | F5: 500000 | G5: 100000 | H5: ='P01 Escola de Ofícios do Espetá'!B20 -> 499745 | I5: =H5-F5 -> -255 | J5: ='P01 Escola de Ofícios do Espetá'!B16 -> 393500 | K5: ='P01 Escola de Ofícios do Espetá'!C17 -> 0.08 | L5: ='P01 Escola de Ofícios do Espetá'!C18 -> 0.09 | M5: ='P01 Escola de Ofícios do Espetá'!C19 -> 0.1 | N5: =IF(AND('P01 Escola de Ofícios do Espetá'!E17="OK",'P01 Escola de Ofícios do Espetá'!E18="OK",'P01 Escola de Ofícios do Espetá'!E19="OK",'P01 Escola de Ofícios do Espetá'!E22="OK"),"OK","EXCEDE") -> OK | O5: Curso/Oficina – ciclo formativo de iniciação aos ofícios técnicos e criativos das artes cênicas (9 turmas x 24h, 270 vagas, 3 núcleos) – Artes Cênicas / Empreend Ações Educ-Cult/Capacitação/Treinamento | P5: Art. 18 | Q5: 5 | R5: 13 | S5: 3 | T5: 5 | U5: Ajustes importantes | V5: • Documentação jurídica da Educare (cartão CNPJ com CNAE cultural compatível, contrato social, representante) – sem isso o SALIC não admite. • Portfólio de atuação cultural da Educare (obrigatório para projeto de R$ 500 mil). • Projeto pedagógico formal com currículo da coordenadora pedagógica e plano de execução com carga horária e conteúdo programático por turma (Anexo II 7.2/7.3), incluindo a matriz núcleo x formação. • Cartas de anuência dos 3 núcleos e do local da mostra; definição do grupo teatral parceiro com autorização autoral.
A6: P02 | B6: Mestres e Aprendizes | C6: 01. Cultura | D6: Aver Mídia | E6: PJ | F6: 400000 | G6: 80000 | H6: ='P02 Mestres e Aprendizes'!B20 -> 399996.75 | I6: =H6-F6 -> -3.25 | J6: ='P02 Mestres e Aprendizes'!B16 -> 310075 | K6: ='P02 Mestres e Aprendizes'!C17 -> 0.08 | L6: ='P02 Mestres e Aprendizes'!C18 -> 0.11 | M6: ='P02 Mestres e Aprendizes'!C19 -> 0.1 | N6: =IF(AND('P02 Mestres e Aprendizes'!E17="OK",'P02 Mestres e Aprendizes'!E18="OK",'P02 Mestres e Aprendizes'!E19="OK",'P02 Mestres e Aprendizes'!E22="OK"),"OK","EXCEDE") -> OK | O6: Percursos continuados de transmissão de saberes tradicionais conduzidos por 4 mestres (4 turmas x 48h, 120 aprendizes) – Patrimônio Cultural / Salvaguarda do patrimônio cultural imaterial | P6: Art. 18 | Q6: 7 | R6: 11 | S6: 3 | T6: 4 | U6: Ajustes importantes | V6: • Selecionar e formalizar os 4 mestres (cartas de anuência) e, quando o saber for coletivo, a anuência da comunidade detentora (Anexo II 8.1.3). • Dossiê por saber com relatório de reconhecido valor cultural, identificação e relatório do bem (Anexo II 8.1.1, 8.1.2.1, 8.1.4, 8.1.5) – ou acionar o Plano B (Artes Visuais – Ações Educ-Cult). • Documentação PJ da Aver Mídia com CNAE compatível e portfólio cultural. • Espaços das 4 turmas e da exposição com anuência.
A7: P03 | B7: Cultura Viva nas Vilas | C7: 01. Cultura | D7: IHV | E7: PJ | F7: 200000 | G7: 40000 | H7: ='P03 Cultura Viva nas Vilas'!B20 -> 199953.87 | I7: =H7-F7 -> -46.13 | J7: ='P03 Cultura Viva nas Vilas'!B16 -> 155003 | K7: ='P03 Cultura Viva nas Vilas'!C17 -> 0.07 | L7: ='P03 Cultura Viva nas Vilas'!C18 -> 0.12 | M7: ='P03 Cultura Viva nas Vilas'!C19 -> 0.1 | N7: =IF(AND('P03 Cultura Viva nas Vilas'!E17="OK",'P03 Cultura Viva nas Vilas'!E18="OK",'P03 Cultura Viva nas Vilas'!E19="OK",'P03 Cultura Viva nas Vilas'!E22="OK"),"OK","EXCEDE") -> OK | O7: Oficinas de formação artística em cultura urbana – música e musicalidade, grafite e audiovisual (8 oficinas x 24h, 200 participantes) – Artes Visuais / Empreend Ações Educ-Cult/Capacitação/Treinamento | P7: Art. 18 | Q7: 7 | R7: 10 | S7: 4 | T7: 4 | U7: Ajustes importantes | V7: • Regularidade cadastral do IHV (CNPJ ativo, estatuto, ata, representante, CNAE cultural) e padronização do nome/sigla (IHV x IHGV). • Confirmar a função de Ado Viana no IHV e o histórico do IHV no Pronac (dispensa de portfólio e art. 15) – risco de questionamento de carteira/fracionamento com P05 e P16. • Plano de execução com carga horária e conteúdo programático das 8 oficinas e ficha técnica nominal (curadoria + ≥6 oficineiros). • Cartas de anuência dos 4 espaços (incluindo solução para 12–14 anos no Eldorado) e autorizações para painéis de grafite.
A8: P04 | B8: Cena Mineira em Movimento | C8: 01. Cultura | D8: Mobox | E8: PJ | F8: 900000 | G8: 180000 | H8: ='P04 Cena Mineira em Movimento'!B20 -> 899987.85 | I8: =H8-F8 -> -12.15 | J8: ='P04 Cena Mineira em Movimento'!B16 -> 697665 | K8: ='P04 Cena Mineira em Movimento'!C17 -> 0.09 | L8: ='P04 Cena Mineira em Movimento'!C18 -> 0.1 | M8: ='P04 Cena Mineira em Movimento'!C19 -> 0.1 | N8: =IF(AND('P04 Cena Mineira em Movimento'!E17="OK",'P04 Cena Mineira em Movimento'!E18="OK",'P04 Cena Mineira em Movimento'!E19="OK",'P04 Cena Mineira em Movimento'!E22="OK"),"OK","EXCEDE") -> OK | O8: Circulação de 4 espetáculos mineiros de teatro/dança – 24 apresentações gratuitas em 12 municípios – Artes Cênicas / Apresentação ou Performance de Teatro | P8: Art. 18 | Q8: 5 | R8: 12 | S8: 4 | T8: 5 | U8: Ajustes importantes | V8: • Dados jurídicos da Mobox (razão social, CNPJ, CNAE, representante) e portfólio. • Fechar 24 apresentações/24 oficinas e a matriz espetáculo x município (ou outro número), refletindo metas e planilha. • Pré-selecionar (por convite) os 4 espetáculos ou parte deles com sinopse, ficha técnica, currículos e autorização do autor do texto – sem isso o Anexo II 3.3 fica descoberto. • Anuências das 12 prefeituras/equipamentos com ficha técnica e lotação.
A9: P05 | B9: Sons do Congado | C9: 01. Cultura | D9: Ado Viana | E9: PF | F9: 300000 | G9: 60000 | H9: ='P05 Sons do Congado'!B20 -> 299998.13 | I9: =H9-F9 -> -1.87 | J9: ='P05 Sons do Congado'!B16 -> 236219 | K9: ='P05 Sons do Congado'!C17 -> 0.07 | L9: ='P05 Sons do Congado'!C18 -> 0.1 | M9: ='P05 Sons do Congado'!C19 -> 0.1 | N9: =IF(AND('P05 Sons do Congado'!E17="OK",'P05 Sons do Congado'!E18="OK",'P05 Sons do Congado'!E19="OK",'P05 Sons do Congado'!E22="OK"),"OK","EXCEDE") -> OK | O9: Álbum Sons do Congado como registro sonoro de salvaguarda: gravação de campo com 4 guardas (12 faixas), repertório e limites de registro definidos pelos mestres, devolução às comunidades e difusão gratuita. – Patrimônio Cultural / Salvaguarda do patrimônio cultural imaterial | P9: Art. 18 | Q9: 3 | R9: 12 | S9: 6 | T9: 4 | U9: Ajustes importantes | V9: • Definir e cadastrar o proponente PF (CPF, endereço, portfólio de Ado Viana). Confirmar que a carteira P05 + P16 = R$ 500 mil não será ultrapassada. • Obter as declarações de anuência das guardas/comunidades detentoras e o relatório de reconhecido valor cultural (Anexo II, 8.1.2.1 e 8.1.3). Sem isso o Iphan não admite a proposta. • Fechar a lista nominal de guardas, mestres e municípios e as especificações técnicas (12 faixas, 6 oficinas de 4h, minidoc de 15 min, apresentação). • Ficha técnica com currículos, em especial do articulador comunitário/coordenador com experiência comprovada junto às comunidades (8.1.6) e da direção musical.
A10: P06 | B10: Mural Minas | C10: 01. Cultura | D10: Morsa | E10: PJ | F10: 750000 | G10: 150000 | H10: ='P06 Mural Minas'!B20 -> 749993.42 | I10: =H10-F10 -> -6.58 | J10: ='P06 Mural Minas'!B16 -> 590546 | K10: ='P06 Mural Minas'!C17 -> 0.08 | L10: ='P06 Mural Minas'!C18 -> 0.09 | M10: ='P06 Mural Minas'!C19 -> 0.1 | N10: =IF(AND('P06 Mural Minas'!E17="OK",'P06 Mural Minas'!E18="OK",'P06 Mural Minas'!E19="OK",'P06 Mural Minas'!E22="OK"),"OK","EXCEDE") -> OK | O10: 6 murais de arte urbana (~180 m² no total) criados com as turmas e artistas-educadores, em exposição pública permanente e gratuita em BH, Contagem e Santa Luzia. – Artes Visuais / Exposição Cultural / Artística | P10: Art. 18 | Q10: 8 | R10: 10 | S10: 3 | T10: 5 | U10: Ajustes importantes | V10: • CNAE da Morsa: incluir CNAE secundário cultural compatível com Artes Visuais/ensino de arte (o principal é edição de jornais), senão o SALIC inadmite. • Reescrever o documento (hoje no modelo LEIC) para o SALIC: área Artes Visuais, segmento Exposição Cultural/Artística, Art. 18; retirar a prática de 'pixo' do objeto. • Definir as 6 superfícies com anuência/termo de cessão e corrigir a área (180 m² x 80 m²). Decidir 6 ou 9 murais. • Equipe com currículos e plano pedagógico com carga horária e conteúdo programático (Anexo II, 4.1 e 7.3).
A11: P07 | B11: Concertos nas Praças do Interior (documentos: 'Concertos na Praça') | C11: 01. Cultura | D11: Túlio Gama | E11: PF | F11: 500000 | G11: 100000 | H11: ='P07 Concertos nas Praças do Int'!B20 -> 499955.82 | I11: =H11-F11 -> -44.18 | J11: ='P07 Concertos nas Praças do Int'!B16 -> 393666 | K11: ='P07 Concertos nas Praças do Int'!C17 -> 0.07 | L11: ='P07 Concertos nas Praças do Int'!C18 -> 0.1 | M11: ='P07 Concertos nas Praças do Int'!C19 -> 0.1 | N11: =IF(AND('P07 Concertos nas Praças do Int'!E17="OK",'P07 Concertos nas Praças do Int'!E18="OK",'P07 Concertos nas Praças do Int'!E19="OK",'P07 Concertos nas Praças do Int'!E22="OK"),"OK","EXCEDE") -> OK | O11: Circuito de 8 concertos gratuitos de música instrumental/de concerto com formação de câmara (8 músicos + regente) e aberturas regionais instrumentais/corais. – Música / Apresentação/Gravação de Música Instrumental (alternativa: Apresentação/Gravação de Música Erudita) | P11: Art. 18 | Q11: 7 | R11: 11 | S11: 3 | T11: 5 | U11: Ajustes importantes | V11: • Confirmar Túlio Gama (PF) como proponente, corrigir a pasta 'PRO SP' e conferir a carteira: com P07 a R$ 500 mil, P12 vai para a LEIC e P08 fica com a ProSP. • Definir formação principal (nº de músicos), regente/diretor artístico e grupos regionais, com currículos (Anexo II, 5.1). • Escolher os municípios/praças e obter anuências municipais com a lista do que cada prefeitura cede (energia, segurança, banheiros, gradil). Sem isso, 8 concertos não cabem em R$ 500 mil. • Fechar a planilha com cotações (palco, som, ônibus, hospedagem) e a simulação do ECAD; dividir a estrutura entre fornecedores para respeitar o limite de 20%.
A12: P08 | B12: Sabores de Minas – Circuito de Cultura Alimentar, Memória e Patrimônio de Minas Gerais | C12: 01. Cultura | D12: PRO SP | E12: PJ | F12: 600000 | G12: 120000 | H12: ='P08 Sabores de Minas – Circuito'!B20 -> 599985.45 | I12: =H12-F12 -> -14.55 | J12: ='P08 Sabores de Minas – Circuito'!B16 -> 465105 | K12: ='P08 Sabores de Minas – Circuito'!C17 -> 0.08 | L12: ='P08 Sabores de Minas – Circuito'!C18 -> 0.11 | M12: ='P08 Sabores de Minas – Circuito'!C19 -> 0.1 | N12: =IF(AND('P08 Sabores de Minas – Circuito'!E17="OK",'P08 Sabores de Minas – Circuito'!E18="OK",'P08 Sabores de Minas – Circuito'!E19="OK",'P08 Sabores de Minas – Circuito'!E22="OK"),"OK","EXCEDE") -> OK | O12: Encontros de transmissão de saberes da cultura alimentar tradicional mineira com mestres e detentores (cozinhas de mestres, oficinas, 'Cozinha de Memórias' com escolas e rodas de conversa) em 4 etapas municipais, como ação de salvaguarda. – Patrimônio Cultural / Salvaguarda do patrimônio cultural imaterial | P12: Risco | Q12: 4 | R12: 15 | S12: 2 | T12: 3 | U12: Não submeter como está | V12: • Reestruturar o objeto de 'festival gastronômico' para salvaguarda de saberes e modos de fazer tradicionais (Patrimônio/Salvaguarda, Art. 18). Do contrário, o enquadramento é Art. 26 e há glosa de custos (IN, art. 18). • Confirmar o proponente ProSP (CNPJ, CNAE compatível, representante) e corrigir a pasta 'Túlio Gama'. Como PF de Túlio, o projeto é inviável (teto R$ 500 mil e carteira já usada por P07). • Reunir o Anexo II, item 8: identificação dos saberes/bens, registro ou relatório de reconhecido valor, anuências dos detentores/comunidades e ficha técnica com experiência junto às comunidades. • Regulamentar a feira sem taxa e sem receita para o projeto, ou declarar a receita e aplicar o art. 44.
A13: P09 | B13: Auto de Natal Mineiro | C13: 02. Natal | D13: Armind | E13: A confirmar | F13: 700000 | G13: 140000 | H13: ='P09 Auto de Natal Mineiro'!B20 -> 699999.84 | I13: =H13-F13 -> -0.16 | J13: ='P09 Auto de Natal Mineiro'!B16 -> 564516 | K13: ='P09 Auto de Natal Mineiro'!C17 -> 0.07 | L13: ='P09 Auto de Natal Mineiro'!C18 -> 0.07 | M13: ='P09 Auto de Natal Mineiro'!C19 -> 0.1 | N13: =IF(AND('P09 Auto de Natal Mineiro'!E17="OK",'P09 Auto de Natal Mineiro'!E18="OK",'P09 Auto de Natal Mineiro'!E19="OK",'P09 Auto de Natal Mineiro'!E22="OK"),"OK","EXCEDE") -> EXCEDE | O13: Espetáculo teatral-musical Auto de Natal Mineiro – criação e circulação (10 apresentações gratuitas) – Artes Cênicas / Teatro Musical (c/ dramaturgia, danças e canções) – alternativa equivalente: Apresentação ou Performance de Teatro | P13: Art. 18 | Q13: 7 | R13: 11 | S13: 3 | T13: 5 | U13: Ajustes importantes | V13: • Resolver a sobreposição com o P10 (mesmo proponente Arminde e mesmo objeto 'Auto de Natal' em nov–dez/2027) antes de submeter. Sem isso há risco de indeferimento por fracionamento ou duplicidade e de custos de criação contados duas vezes. • Natureza jurídica e dossiê da Arminde (PF, MEI ou PJ; CNPJ e CNAE; portfólio obrigatório por ser > R$ 200 mil). Se for PF, o projeto tem de baixar para ≤ R$ 500 mil. • Ficha técnica com currículos, autor do texto com contrato ou anuência (Anexo II 3.1 e 3.3) e sinopse. • Fechar os 8 municípios e as praças com manifestação das prefeituras, mais o calendário real.
A14: P10 | B14: Natal nas Cidades Mineiras | C14: 02. Natal | D14: Gustavo Ribeiro | E14: A confirmar | F14: 500000 | G14: 100000 | H14: ='P10 Natal nas Cidades Mineiras'!B20 -> 499996.16 | I14: =H14-F14 -> -3.84 | J14: ='P10 Natal nas Cidades Mineiras'!B16 -> 390622 | K14: ='P10 Natal nas Cidades Mineiras'!C17 -> 0.08 | L14: ='P10 Natal nas Cidades Mineiras'!C18 -> 0.1 | M14: ='P10 Natal nas Cidades Mineiras'!C19 -> 0.1 | N14: =IF(AND('P10 Natal nas Cidades Mineiras'!E17="OK",'P10 Natal nas Cidades Mineiras'!E18="OK",'P10 Natal nas Cidades Mineiras'!E19="OK",'P10 Natal nas Cidades Mineiras'!E22="OK"),"OK","EXCEDE") -> OK | O14: Espetáculo Auto de Natal – 5 apresentações gratuitas em praças (criação/adaptação e circulação) – Artes Cênicas / Apresentação ou Performance de Teatro | P14: Art. 18 | Q14: 7 | R14: 11 | S14: 3 | T14: 3 | U14: Não submeter como está | V14: • Resolver a duplicidade com o P09: mesmo proponente (Arminde) e mesmo objeto (Auto de Natal gratuito em praças de MG em nov–dez/2027). Do jeito que está, o projeto não deve ser submetido à Rouanet em paralelo ao P09. • Definir o titular (Arminde PJ ou Gustavo Ribeiro PF) e reunir CNPJ, CNAE, contrato social e portfólio. A planilha e os documentos divergem. • Anuências das 5 prefeituras e autorizações de patrimônio nas cidades históricas, com praças definidas. • Ficha técnica e sinopse do Auto, com anuência do autor.
A15: P11 | B15: Festa Junina 2027 – Saberes e Tradições do Forró | C15: 03. Festas Populares | D15: Mobox | E15: PJ | F15: 800000 | G15: 160000 | H15: ='P11 Festa Junina 2027 – Saberes'!B20 -> 799988.75 | I15: =H15-F15 -> -11.25 | J15: ='P11 Festa Junina 2027 – Saberes'!B16 -> 639991 | K15: ='P11 Festa Junina 2027 – Saberes'!C17 -> 0.06 | L15: ='P11 Festa Junina 2027 – Saberes'!C18 -> 0.09 | M15: ='P11 Festa Junina 2027 – Saberes'!C19 -> 0.1 | N15: =IF(AND('P11 Festa Junina 2027 – Saberes'!E17="OK",'P11 Festa Junina 2027 – Saberes'!E18="OK",'P11 Festa Junina 2027 – Saberes'!E19="OK",'P11 Festa Junina 2027 – Saberes'!E22="OK"),"OK","EXCEDE") -> OK | O15: Festival/Festa: circuito Festa Junina – Saberes e Tradições do Forró (4 municípios, 8 dias). Pelo art. 46, parágrafo único, o enquadramento é dado pelo secundário de maior valor: as 16 apresentações das Matrizes Tradicionais do Forró – Patrimônio Cultural / Salvaguarda do patrimônio cultural imaterial (produto Festival, Bienal, Festa ou Feira) | P15: Art. 18 | Q15: 8 | R15: 11 | S15: 2 | T15: 6 | U15: Ajustes importantes | V15: • Anuência da comunidade detentora das Matrizes Tradicionais do Forró (grupos e coletivos forrozeiros de MG), relatório do bem e comprovante do registro Iphan (Anexo II 8.1.1–8.1.5 e 8.8). Sem isso o enquadramento em Patrimônio não se sustenta. • Fixar no SALIC o segmento das apresentações (Salvaguarda do PCI, ou Música Regional) e retirar o 'sertanejo raiz', para que o secundário de maior valor garanta o Art. 18. • Confirmar municípios, espaços e datas com cartas das prefeituras, incluindo o apoio assumido na planilha: energia da rede, sanitários do local e policiamento. • Cadastro, CNAE e portfólio da Mobox.
A16: P12 | B16: Bloco do Nerd / Carnaval (Bloco Nerd) | C16: 03. Festas Populares | D16: Túlio Gama | E16: PF | F16: 250000 | G16: 50000 | H16: ='P12 Bloco do Nerd Carnaval (Bl'!B20 -> 249999.5 | I16: =H16-F16 -> -0.5 | J16: ='P12 Bloco do Nerd Carnaval (Bl'!B16 -> 196850 | K16: ='P12 Bloco do Nerd Carnaval (Bl'!C17 -> 0.06 | L16: ='P12 Bloco do Nerd Carnaval (Bl'!C18 -> 0.11 | M16: ='P12 Bloco do Nerd Carnaval (Bl'!C19 -> 0.1 | N16: =IF(AND('P12 Bloco do Nerd Carnaval (Bl'!E17="OK",'P12 Bloco do Nerd Carnaval (Bl'!E18="OK",'P12 Bloco do Nerd Carnaval (Bl'!E19="OK",'P12 Bloco do Nerd Carnaval (Bl'!E22="OK"),"OK","EXCEDE") -> OK | O16: Desfile festivo – cortejo carnavalesco Bloco Nerd (com ensaios abertos e lançamento) – Artes Cênicas / Desfiles festivos de caráter musical e cênico | P16: Art. 18 | Q16: 7 | R16: 12 | S16: 2 | T16: 3 | U16: Não submeter como está | V16: • Escolher qual projeto do Túlio vai à Rouanet. P07 + P12 como PF somam R$ 750 mil e violam a carteira de R$ 500 mil (art. 10, I). Conferir também o vínculo de Túlio com a Morsa (art. 15) e com o P08. • Titular formal: PF Túlio ou Morsa, sendo que o CNAE da Morsa ('edição de jornais') é incompatível. Reunir o portfólio documentado (obrigatório acima de R$ 200 mil). • Edição: o Carnaval 2027 é inviável na Rouanet. Reescrever para o Carnaval 2028, o que permite submeter na janela de 2027. • Direitos: nome 'Bloco Nerd' (conflito com outro bloco), licenças de arranjo dos temas, personagens NXP e eliminação do playback.
A17: P13 | B17: Skate e Arte Urbana (Circuito Skate & Rua) | C17: Esporte com cultura | D17: ESIP | E17: PJ | F17: 350000 | G17: 70000 | H17: ='P13 Skate e Arte Urbana (Circui'!B20 -> 349997.76 | I17: =H17-F17 -> -2.24 | J17: ='P13 Skate e Arte Urbana (Circui'!B16 -> 277776 | K17: ='P13 Skate e Arte Urbana (Circui'!C17 -> 0.06 | L17: ='P13 Skate e Arte Urbana (Circui'!C18 -> 0.1 | M17: ='P13 Skate e Arte Urbana (Circui'!C19 -> 0.1 | N17: =IF(AND('P13 Skate e Arte Urbana (Circui'!E17="OK",'P13 Skate e Arte Urbana (Circui'!E18="OK",'P13 Skate e Arte Urbana (Circui'!E19="OK",'P13 Skate e Arte Urbana (Circui'!E22="OK"),"OK","EXCEDE") -> OK | O17: Oficinas de arte urbana (grafite) com criação coletiva de 4 murais permanentes em pistas públicas de skate da RMBH – Artes Visuais / Empreend Ações Educ-Cult/Capacitação/Treinamento | P17: Art. 18 | Q17: 1 | R17: 16 | S17: 4 | T17: 3 | U17: Ajustes importantes | V17: • Reescrever o projeto inteiro com objeto cultural. O texto atual (LIE, com 'predominância esportiva') é inadmissível no SALIC e teria quase todo o orçamento glosado pelo art. 18 da IN. • ESIP: comprovar CNPJ com CNAE cultural compatível com Artes Visuais/Cênicas, estatuto, ata e portfólio de atuação CULTURAL (valor > R$ 200 mil). Sem isso, a proposta não é admitida. • Anuências das 4 pistas, incluindo autorização expressa para pintura mural permanente (superfície, tema, conservação), e cartas de coletivos locais de hip-hop/grafite. • Ficha técnica nominada (curadoria de arte urbana, muralistas, arte-educadores de grafite e breaking, DJ/MC, grupo de breaking) com currículos, e projeto pedagógico com carga horária e conteúdo (Anexo II 7.2/7.3).
A18: P14 | B18: Capoeira: Roda de Minas | C18: Esporte com cultura | D18: ESIP | E18: PJ | F18: 300000 | G18: 60000 | H18: ='P14 Capoeira Roda de Minas'!B20 -> 299993.75 | I18: =H18-F18 -> -6.25 | J18: ='P14 Capoeira Roda de Minas'!B16 -> 239995 | K18: ='P14 Capoeira Roda de Minas'!C17 -> 0.06 | L18: ='P14 Capoeira Roda de Minas'!C18 -> 0.09 | M18: ='P14 Capoeira Roda de Minas'!C19 -> 0.1 | N18: =IF(AND('P14 Capoeira Roda de Minas'!E17="OK",'P14 Capoeira Roda de Minas'!E18="OK",'P14 Capoeira Roda de Minas'!E19="OK",'P14 Capoeira Roda de Minas'!E22="OK"),"OK","EXCEDE") -> OK | O18: Núcleos de formação em capoeira: 4 núcleos, 100 participantes, 16 encontros de 2 h com mestres (fundamentos, musicalidade, história, oralidade) – Artes Cênicas / Apresentação de Dança ou Ação Educativa: Capoeira | P18: Art. 18 | Q18: 6 | R18: 11 | S18: 4 | T18: 5 | U18: Ajustes importantes | V18: • ESIP: CNPJ com CNAE cultural compatível com Artes Cênicas, estatuto com finalidade cultural, ata, certidões e portfólio cultural (valor > R$ 200 mil). O próprio documento classifica isso como pendência CRÍTICA nº 1. • Definir os 2 territórios restantes e os 4 espaços, com cartas de anuência e condições de acessibilidade. Confirmar ou retirar o núcleo quilombola (só citar com anuência formal). • Nominar os mestres dos núcleos e os convidados do Encontro, com currículos e cartas de aceite. Elaborar o projeto pedagógico dos 16 encontros (Anexo II, item 7). • Retirar a narrativa esportiva da versão SALIC e resolver a relação com a lei estadual do esporte (duplicidade de fontes; plano do cliente é LEIC-MG).
A19: P15 | B19: Riso que Cura | C19: Saúde | D19: Aver Mídia | E19: PJ | F19: 450000 | G19: 90000 | H19: ='P15 Riso que Cura'!B20 -> 449675 | I19: =H19-F19 -> -325 | J19: ='P15 Riso que Cura'!B16 -> 359740 | K19: ='P15 Riso que Cura'!C17 -> 0.06 | L19: ='P15 Riso que Cura'!C18 -> 0.09 | M19: ='P15 Riso que Cura'!C19 -> 0.1 | N19: =IF(AND('P15 Riso que Cura'!E17="OK",'P15 Riso que Cura'!E18="OK",'P15 Riso que Cura'!E19="OK",'P15 Riso que Cura'!E22="OK"),"OK","EXCEDE") -> OK | O19: Circulação de performances/intervenções de palhaçaria em hospitais (144 visitas em duplas, 6 hospitais) – Artes Cênicas / Performance de Circo, Clown e Ilusionismo | P19: Art. 18 | Q19: 7 | R19: 10 | S19: 4 | T19: 6 | U19: Ajustes importantes | V19: • Dados jurídicos da Aver Mídia (CNPJ, atos, representante) e CNAE compatível com artes cênicas – risco de inabilitação se o CNAE for só de mídia/publicidade. • Portfólio cultural comprovável da Aver Mídia (obrigatório para valor > R$ 200 mil). • Cartas de interesse/anuência dos 6 hospitais (nome, setor, contato) – sem elas o território e o plano de distribuição são fictícios. • Validação da escala: 144 visitas só cabem em R$ 450 mil com cachê de R$ 400/turno, coordenação acumulada e captação ~9% (ver planilha); confirmar com artistas antes de congelar.
A20: P16 | B20: Música nos Hospitais | C20: Saúde | D20: Ado Viana | E20: PF | F20: 200000 | G20: 40000 | H20: ='P16 Música nos Hospitais'!B20 -> 199888 | I20: =H20-F20 -> -112 | J20: ='P16 Música nos Hospitais'!B16 -> 153760 | K20: ='P16 Música nos Hospitais'!C17 -> 0.08 | L20: ='P16 Música nos Hospitais'!C18 -> 0.12 | M20: ='P16 Música nos Hospitais'!C19 -> 0.1 | N20: =IF(AND('P16 Música nos Hospitais'!E17="OK",'P16 Música nos Hospitais'!E18="OK",'P16 Música nos Hospitais'!E19="OK",'P16 Música nos Hospitais'!E22="OK"),"OK","EXCEDE") -> OK | O20: Apresentações de música instrumental/regional mineira (trio acústico) em instituições de saúde – 30 apresentações – Música / Apresentação/Gravação de Música Instrumental (alternativa: Música Regional) | P20: Risco | Q20: 6 | R20: 10 | S20: 5 | T20: 5 | U20: Ajustes importantes | V20: • Decisão curatorial (formação instrumental/regional) – sem ela o produto principal tende a Art. 26 (música popular cantada). • Carteira PF no limite: P05 (R$ 300 mil) + P16 (R$ 200 mil) = R$ 500 mil e 2 projetos; confirmar que não há outro projeto ativo e vínculos com PJ (art. 15). • Anuências das 6 instituições (nenhuma indicada). • Documentos do proponente PF e equipe nominal (currículos de músicos e educador) + projeto pedagógico das oficinas.
A21: P17 | B21: Corpo em Cena | C21: Saúde | D21: Amanda Lourenço | E21: A confirmar | F21: 200000 | G21: 40000 | H21: ='P17 Corpo em Cena'!B20 -> 199986.9 | I21: =H21-F21 -> -13.1 | J21: ='P17 Corpo em Cena'!B16 -> 157470 | K21: ='P17 Corpo em Cena'!C17 -> 0.08 | L21: ='P17 Corpo em Cena'!C18 -> 0.09 | M21: ='P17 Corpo em Cena'!C19 -> 0.1 | N21: =IF(AND('P17 Corpo em Cena'!E17="OK",'P17 Corpo em Cena'!E18="OK",'P17 Corpo em Cena'!E19="OK",'P17 Corpo em Cena'!E22="OK"),"OK","EXCEDE") -> OK | O21: Oficinas de dança, expressão corporal e artes visuais com criação coletiva (3 núcleos, 48 encontros, 96 h) – Artes Cênicas / Empreendimento de Ações Educativo-Culturais/Capacitação/Treinamento (dança) | P21: Art. 18 | Q21: 8 | R21: 10 | S21: 3 | T21: 6 | U21: Ajustes importantes | V21: • Definir o proponente formal (PF Amanda Lourenço ou PJ com CNAE cultural) – sem ele não há inscrição. • Escolher o 3º município e obter anuências dos 3 espaços de oficinas e do local da apresentação principal em BH. • Ficha técnica nominal e projeto pedagógico formal (carga horária e conteúdo – Anexo II). • Datas civis do cronograma e decisão IFC x Rouanet sem dupla captação.
A22: P18 | B22: Arte e Envelhecimento Ativo | C22: Saúde | D22: Educare | E22: PJ | F22: 250000 | G22: 50000 | H22: ='P18 Arte e Envelhecimento Ativo'!B20 -> 249958.14 | I22: =H22-F22 -> -41.86 | J22: ='P18 Arte e Envelhecimento Ativo'!B16 -> 193766 | K22: ='P18 Arte e Envelhecimento Ativo'!C17 -> 0.08 | L22: ='P18 Arte e Envelhecimento Ativo'!C18 -> 0.11 | M22: ='P18 Arte e Envelhecimento Ativo'!C19 -> 0.1 | N22: =IF(AND('P18 Arte e Envelhecimento Ativo'!E17="OK",'P18 Arte e Envelhecimento Ativo'!E18="OK",'P18 Arte e Envelhecimento Ativo'!E19="OK",'P18 Arte e Envelhecimento Ativo'!E22="OK"),"OK","EXCEDE") -> OK | O22: Oficinas continuadas de dança adaptada para pessoas idosas (72 encontros) com direção artístico-pedagógica – Artes Cênicas / Empreendimento de Ações Educativo-Culturais/Capacitação/Treinamento (dança) | P22: Art. 18 | Q22: 9 | R22: 8 | S22: 4 | T22: 7 | U22: Ajustes importantes | V22: • Confirmar a Educare como proponente (CNPJ, CNAE cultural compatível, portfólio – obrigatório acima de R$ 200 mil). • Anuência das 6 instituições (centros de convivência/ILPIs) com calendário de 24 semanas. • Ficha técnica nominal (direção, regente, arte-educador de dança, formador) e projeto pedagógico formal. • Datas civis e decisão sobre fonte complementar (IFC) sem dupla captação.
A23: P19 | B23: Acelera Minas – formação de kart | C23: Esporte com cultura | D23: Rafael Tose | E23: A confirmar | F23: 450000 | G23: 90000 | H23: ='P19 Acelera Minas – formação de'!B20 -> 449999.72 | I23: =H23-F23 -> -0.28 | J23: ='P19 Acelera Minas – formação de'!B16 -> 362903 | K23: ='P19 Acelera Minas – formação de'!C17 -> 0.06 | L23: ='P19 Acelera Minas – formação de'!C18 -> 0.08 | M23: ='P19 Acelera Minas – formação de'!C19 -> 0.1 | N23: =IF(AND('P19 Acelera Minas – formação de'!E17="OK",'P19 Acelera Minas – formação de'!E18="OK",'P19 Acelera Minas – formação de'!E19="OK",'P19 Acelera Minas – formação de'!E22="OK"),"OK","EXCEDE") -> OK | O23: [REFORMULAÇÃO – referência] Laboratório de formação audiovisual para 80 adolescentes (4 turmas de 20, 80 h cada) de Juatuba e Santa Luzia – Audiovisual / Ações de capacitação e treinamento de pessoal | P23: Risco | Q23: 0 | R23: 17 | S23: 4 | T23: 1 | U23: Não submeter como está | V23: • NÃO SUBMETER À ROUANET: o objeto (escola de kart) é esportivo, sem segmento no Anexo IV, e o orçamento seria integralmente glosado (IN art. 18). A planilha esportiva original não é aceitável. • Encaminhar para a Lei de Incentivo ao Esporte (Lei 11.438/2006) ou para a Lei Estadual de Incentivo ao Esporte de MG (Lei 20.824/2013), com uma OSC esportiva como proponente. • Valor incompatível: o documento pede R$ 2.434.400, a planilha do cliente prevê R$ 450 mil. Redimensionar em qualquer mecanismo. • Proponente indefinido ('[Nome da OSC]' x Rafael Tose). Se Rafael Tose for PF, só cabe um entre P19 e P21 na Rouanet (carteira de R$ 500 mil). Priorizar o P21 (cinema), que é cultural.
A24: P20 | B24: Jovens do Fut – formação em Juatuba | C24: Esporte com cultura | D24: A definir | E24: A confirmar | F24: 500000 | G24: 90000 | H24: ='P20 Jovens do Fut – formação em'!B20 -> 499996.98 | I24: =H24-F24 -> -3.02 | J24: ='P20 Jovens do Fut – formação em'!B16 -> 396823 | K24: ='P20 Jovens do Fut – formação em'!C17 -> 0.06 | L24: ='P20 Jovens do Fut – formação em'!C18 -> 0.1 | M24: ='P20 Jovens do Fut – formação em'!C19 -> 0.1 | N24: =IF(AND('P20 Jovens do Fut – formação em'!E17="OK",'P20 Jovens do Fut – formação em'!E18="OK",'P20 Jovens do Fut – formação em'!E19="OK",'P20 Jovens do Fut – formação em'!E22="OK"),"OK","EXCEDE") -> OK | O24: [REFORMULAÇÃO] Escola de Audiovisual e Narração do Futebol: 6 turmas de 20 jovens (audiovisual/fotografia e narração/podcast), 60 h cada – Audiovisual / Ações de capacitação e treinamento de pessoal | P24: Art. 18 | Q24: 0 | R24: 16 | S24: 5 | T24: 2 | U24: Não submeter como está | V24: • O documento atual (escola de futebol, formato LIE) NÃO pode ser submetido à Rouanet. A planilha esportiva original (R$ 1,13 mi) não é aceitável (IN art. 18; sem segmento no Anexo IV). • A planilha SALIC anexa é uma PROPOSTA DE REFORMULAÇÃO DE OBJETO (formação cultural nas linguagens do futebol). Exige escrever um projeto novo (objetivos, justificativa cultural, projeto pedagógico com carga horária e conteúdo, ficha técnica de arte-educadores) antes de 31/10/2026. • Proponente 'a definir': escolher PJ com CNAE cultural compatível com Audiovisual e portfólio cultural (R$ 500 mil > R$ 200 mil), ou PF com carteira livre. Sem isso não há submissão. • Escolas, CRAS e prefeitura de Juatuba: anuência para salas e para as superfícies dos murais.
A25: P21 | B25: Caravana Cultura & Saúde | C25: Saúde | D25: Rafael Tose | E25: A confirmar | F25: 450000 | G25: 0 | H25: ='P21 Caravana Cultura & Saúde'!B20 -> 449994.24 | I25: =H25-F25 -> -5.76 | J25: ='P21 Caravana Cultura & Saúde'!B16 -> 351558 | K25: ='P21 Caravana Cultura & Saúde'!C17 -> 0.07 | L25: ='P21 Caravana Cultura & Saúde'!C18 -> 0.11 | M25: ='P21 Caravana Cultura & Saúde'!C19 -> 0.1 | N25: =IF(AND('P21 Caravana Cultura & Saúde'!E17="OK",'P21 Caravana Cultura & Saúde'!E18="OK",'P21 Caravana Cultura & Saúde'!E19="OK",'P21 Caravana Cultura & Saúde'!E22="OK"),"OK","EXCEDE") -> OK | O25: Mostra itinerante de cinema brasileiro – 36 blocos de exibição gratuitos em 6 municípios – Audiovisual / Difusão de acervo e conteúdo audiovisual em diversos meios e suportes | P25: Art. 18 | Q25: 9 | R25: 7 | S25: 5 | T25: 5 | U25: Ajustes importantes | V25: • Natureza jurídica do proponente e carteira: Rafael Tose aparece em P19 (kart, R$ 450 mil) e P21 (R$ 450 mil); como PF só cabe um projeto de R$ 450 mil (teto R$ 500 mil). Decidir qual vai à Rouanet ou usar PJ com CNAE audiovisual. • Portfólio cultural/audiovisual comprovável (obrigatório acima de R$ 200 mil); sem ele, trocar o proponente (ex.: produtora AV parceira) ou reduzir a ≤ R$ 200 mil se for 1º projeto. • Seleção dos 6 municípios e espaços (principais + alternativos cobertos) com anuência das prefeituras. • Lista indicativa de filmes com licenças, classificação e versões acessíveis (AD/LSE).
B26: TOTAL | F26: =SUM(F5:F25) -> 9550000 | G26: =SUM(G5:G25) -> 1810000 | H26: =SUM(H5:H25) -> 9549091 | I26: =SUM(I5:I25) -> -908.97

Sheet Carteira por proponente
A1: Limites de carteira por proponente (IN 29, arts. 10, 11 e 15)
A2: Soma só os projetos deste lote; projetos já ativos no SALIC também contam. 'A confirmar' é testado como pessoa física (pior caso). Sócios/dirigentes em comum unem carteiras (art. 15).
A4: Titular | B4: Tipo | C4: Projetos no lote | D4: Qtd. projetos | E4: Valor total orçado (R$) | F4: Limite de carteira (R$) | G4: Qtd. máx. | H4: Situação | I4: Observação
A5: A definir | B5: A confirmar | C5: P20 | D5: 1 | E5: =Resumo!H24 -> 499996.98 | F5: ='Parâmetros IN 29'!$B$8 -> 500000 | G5: 2 | H5: =IF(AND(E5<=F5,D5<=G5),"OK","EXCEDE")&IF(AND(E5<=F5,D5<=G5),""," (se PF)") -> OK | I5: Proponente não definido – projeto não pode ser cadastrado.
A6: Ado Viana | B6: PF | C6: P05, P16 | D6: 2 | E6: =Resumo!H9+Resumo!H20 -> 499886.13 | F6: ='Parâmetros IN 29'!$B$8 -> 500000 | G6: 2 | H6: =IF(AND(E6<=F6,D6<=G6),"OK","EXCEDE") -> OK | I6: Exatamente no teto PF (2 projetos, R$ 500 mil). A exceção de patrimônio (art. 14) não vale para PF. Nenhum outro projeto ativo pode existir.
A7: Amanda Lourenço | B7: A confirmar | C7: P17 | D7: 1 | E7: =Resumo!H21 -> 199986.9 | F7: ='Parâmetros IN 29'!$B$8 -> 500000 | G7: 2 | H7: =IF(AND(E7<=F7,D7<=G7),"OK","EXCEDE")&IF(AND(E7<=F7,D7<=G7),""," (se PF)") -> OK | I7: Se PF e 1º projeto: R$ 200 mil é exatamente o limite sem portfólio.
A8: Armind | B8: A confirmar | C8: P09 | D8: 1 | E8: =Resumo!H13 -> 699999.84 | F8: ='Parâmetros IN 29'!$B$8 -> 500000 | G8: 2 | H8: =IF(AND(E8<=F8,D8<=G8),"OK","EXCEDE")&IF(AND(E8<=F8,D8<=G8),""," (se PF)") -> EXCEDE (se PF) | I8: Se for PF, R$ 700 mil excede o teto por projeto. Confirmar natureza jurídica. P10 cita a Arminde como proponente nos documentos (Gustavo Ribeiro como representante): mesma carteira.
A9: Aver Mídia | B9: PJ | C9: P02, P15 | D9: 2 | E9: =Resumo!H6+Resumo!H19 -> 849671.75 | F9: ='Parâmetros IN 29'!$B$10 -> 15000000 | G9: 10 | H9: =IF(AND(E9<=F9,D9<=G9),"OK","EXCEDE") -> OK
A10: ESIP | B10: PJ | C10: P13, P14 | D10: 2 | E10: =Resumo!H17+Resumo!H18 -> 649991.51 | F10: ='Parâmetros IN 29'!$B$10 -> 15000000 | G10: 10 | H10: =IF(AND(E10<=F10,D10<=G10),"OK","EXCEDE") -> OK
A11: Educare | B11: PJ | C11: P01, P18 | D11: 2 | E11: =Resumo!H5+Resumo!H22 -> 749703.14 | F11: ='Parâmetros IN 29'!$B$10 -> 15000000 | G11: 10 | H11: =IF(AND(E11<=F11,D11<=G11),"OK","EXCEDE") -> OK
A12: Gustavo Ribeiro | B12: A confirmar | C12: P10 | D12: 1 | E12: =Resumo!H14 -> 499996.16 | F12: ='Parâmetros IN 29'!$B$8 -> 500000 | G12: 2 | H12: =IF(AND(E12<=F12,D12<=G12),"OK","EXCEDE")&IF(AND(E12<=F12,D12<=G12),""," (se PF)") -> OK | I12: Documentos indicam a Arminde como proponente; se Gustavo for dirigente da Armind, P09 + P10 ficam na mesma carteira (art. 15) e há risco de fracionamento/duplicidade.
A13: IHV | B13: PJ | C13: P03 | D13: 1 | E13: =Resumo!H7 -> 199953.87 | F13: ='Parâmetros IN 29'!$B$10 -> 15000000 | G13: 10 | H13: =IF(AND(E13<=F13,D13<=G13),"OK","EXCEDE") -> OK | I13: 1º projeto no SALIC: R$ 200 mil é o limite sem portfólio. Verificar se Ado Viana é dirigente (uniria carteira com PF).
A14: Mobox | B14: PJ | C14: P04, P11 | D14: 2 | E14: =Resumo!H8+Resumo!H15 -> 1699976.6 | F14: ='Parâmetros IN 29'!$B$10 -> 15000000 | G14: 10 | H14: =IF(AND(E14<=F14,D14<=G14),"OK","EXCEDE") -> OK | I14: Festa Junina como patrimônio cultural fica fora dos limites de valor e quantidade da PJ (art. 14, §ú).
A15: Morsa | B15: PJ | C15: P06 | D15: 1 | E15: =Resumo!H10 -> 749993.42 | F15: ='Parâmetros IN 29'!$B$10 -> 15000000 | G15: 10 | H15: =IF(AND(E15<=F15,D15<=G15),"OK","EXCEDE") -> OK
A16: PRO SP | B16: PJ | C16: P08 | D16: 1 | E16: =Resumo!H12 -> 599985.45 | F16: ='Parâmetros IN 29'!$B$10 -> 15000000 | G16: 10 | H16: =IF(AND(E16<=F16,D16<=G16),"OK","EXCEDE") -> OK
A17: Rafael Tose | B17: A confirmar | C17: P19, P21 | D17: 2 | E17: =Resumo!H23+Resumo!H25 -> 899993.96 | F17: ='Parâmetros IN 29'!$B$8 -> 500000 | G17: 2 | H17: =IF(AND(E17<=F17,D17<=G17),"OK","EXCEDE")&IF(AND(E17<=F17,D17<=G17),""," (se PF)") -> EXCEDE (se PF) | I17: P19 + P21 somam R$ 900 mil: viola se PF. P19 (kart) não é enquadrável; manter só P21.
A18: Túlio Gama | B18: PF | C18: P07, P12 | D18: 2 | E18: =Resumo!H11+Resumo!H16 -> 749955.32 | F18: ='Parâmetros IN 29'!$B$8 -> 500000 | G18: 2 | H18: =IF(AND(E18<=F18,D18<=G18),"OK","EXCEDE") -> EXCEDE | I18: P07 + P12 somam R$ 750 mil > R$ 500 mil. Só um vai à Rouanet (planilha do cliente já prevê o outro na LEIC). Recomendado: P07 na Rouanet, P12 na LEIC. Verificar vínculo com Morsa/Educare (art. 15).

Sheet Matriz de campos
A1: Campos do SALIC (A), checklist interno do cliente (B) e perguntas específicas (C) – status por projeto
A2: A12, A14 e A17 (cinza) não são campos próprios do formulário SALIC 2026 – mantidos como boa prática. Detalhes na aba 'Revisão detalhada'.
A3: Código | B3: Campo | C3: P01 | D3: P02 | E3: P03 | F3: P04 | G3: P05 | H3: P06 | I3: P07 | J3: P08 | K3: P09 | L3: P10 | M3: P11 | N3: P12 | O3: P13 | P3: P14 | Q3: P15 | R3: P16 | S3: P17 | T3: P18 | U3: P19 | V3: P20 | W3: P21
A4: A1 | B4: Identificação (nome, proponente, CNPJ/CNAE, área/segmento, Art. 18) | C4: PARCIAL | D4: PARCIAL | E4: PARCIAL | F4: PARCIAL | G4: PARCIAL | H4: PARCIAL | I4: PARCIAL | J4: PARCIAL | K4: PARCIAL | L4: PARCIAL | M4: PARCIAL | N4: PARCIAL | O4: PARCIAL | P4: PARCIAL | Q4: PARCIAL | R4: PARCIAL | S4: PARCIAL | T4: PARCIAL | U4: PARCIAL | V4: AUSENTE | W4: PARCIAL
A5: A2 | B5: Período de execução e prazo de captação | C5: PARCIAL | D5: PARCIAL | E5: PARCIAL | F5: PARCIAL | G5: PARCIAL | H5: PARCIAL | I5: PARCIAL | J5: PARCIAL | K5: PARCIAL | L5: PARCIAL | M5: PARCIAL | N5: PARCIAL | O5: PARCIAL | P5: PARCIAL | Q5: PARCIAL | R5: PARCIAL | S5: PARCIAL | T5: PARCIAL | U5: PARCIAL | V5: PARCIAL | W5: PARCIAL
A6: A3 | B6: Resumo | C6: OK | D6: OK | E6: OK | F6: OK | G6: OK | H6: OK | I6: OK | J6: OK | K6: OK | L6: OK | M6: OK | N6: OK | O6: PARCIAL | P6: OK | Q6: OK | R6: PARCIAL | S6: OK | T6: OK | U6: PARCIAL | V6: PARCIAL | W6: OK
A7: A4 | B7: Objetivos (geral e específicos mensuráveis) | C7: PARCIAL | D7: OK | E7: OK | F7: PARCIAL | G7: PARCIAL | H7: OK | I7: OK | J7: PARCIAL | K7: OK | L7: OK | M7: OK | N7: OK | O7: PARCIAL | P7: OK | Q7: OK | R7: OK | S7: OK | T7: OK | U7: PARCIAL | V7: PARCIAL | W7: OK
A8: A5 | B8: Justificativa (art. 1º/3º Lei 8.313, relevância, dados) | C8: PARCIAL | D8: PARCIAL | E8: PARCIAL | F8: PARCIAL | G8: PARCIAL | H8: PARCIAL | I8: PARCIAL | J8: PARCIAL | K8: PARCIAL | L8: PARCIAL | M8: PARCIAL | N8: PARCIAL | O8: PARCIAL | P8: PARCIAL | Q8: PARCIAL | R8: PARCIAL | S8: PARCIAL | T8: PARCIAL | U8: PARCIAL | V8: PARCIAL | W8: PARCIAL
A9: A6 | B9: Acessibilidade (arquitetônica, comunicacional, divulgação; Guia MDHC) | C9: PARCIAL | D9: PARCIAL | E9: PARCIAL | F9: PARCIAL | G9: PARCIAL | H9: PARCIAL | I9: PARCIAL | J9: PARCIAL | K9: PARCIAL | L9: PARCIAL | M9: PARCIAL | N9: PARCIAL | O9: PARCIAL | P9: PARCIAL | Q9: PARCIAL | R9: PARCIAL | S9: PARCIAL | T9: OK | U9: PARCIAL | V9: PARCIAL | W9: OK
A10: A7 | B10: Democratização de acesso (art. 41) | C10: OK | D10: OK | E10: OK | F10: OK | G10: PARCIAL | H10: OK | I10: OK | J10: PARCIAL | K10: OK | L10: OK | M10: OK | N10: OK | O10: OK | P10: OK | Q10: OK | R10: OK | S10: OK | T10: OK | U10: PARCIAL | V10: PARCIAL | W10: OK
A11: A8 | B11: Ampliação de acesso (art. 42) / contrapartida (art. 44) | C11: PARCIAL | D11: PARCIAL | E11: PARCIAL | F11: OK | G11: PARCIAL | H11: PARCIAL | I11: OK | J11: PARCIAL | K11: OK | L11: PARCIAL | M11: OK | N11: OK | O11: PARCIAL | P11: PARCIAL | Q11: OK | R11: PARCIAL | S11: PARCIAL | T11: PARCIAL | U11: PARCIAL | V11: PARCIAL | W11: PARCIAL
A12: A9 | B12: Etapas de trabalho | C12: OK | D12: OK | E12: OK | F12: OK | G12: OK | H12: OK | I12: OK | J12: OK | K12: OK | L12: OK | M12: OK | N12: OK | O12: PARCIAL | P12: OK | Q12: OK | R12: OK | S12: OK | T12: OK | U12: PARCIAL | V12: PARCIAL | W12: OK
A13: A10 | B13: Ficha técnica | C13: PARCIAL | D13: AUSENTE | E13: AUSENTE | F13: AUSENTE | G13: AUSENTE | H13: AUSENTE | I13: PARCIAL | J13: PARCIAL | K13: AUSENTE | L13: AUSENTE | M13: PARCIAL | N13: PARCIAL | O13: AUSENTE | P13: AUSENTE | Q13: AUSENTE | R13: AUSENTE | S13: AUSENTE | T13: AUSENTE | U13: PARCIAL | V13: PARCIAL | W13: AUSENTE
A14: A11 | B14: Sinopse/descrição do conteúdo artístico | C14: PARCIAL | D14: PARCIAL | E14: PARCIAL | F14: AUSENTE | G14: PARCIAL | H14: PARCIAL | I14: PARCIAL | J14: PARCIAL | K14: PARCIAL | L14: PARCIAL | M14: PARCIAL | N14: PARCIAL | O14: AUSENTE | P14: PARCIAL | Q14: PARCIAL | R14: PARCIAL | S14: PARCIAL | T14: PARCIAL | U14: AUSENTE | V14: AUSENTE | W14: PARCIAL
... A40: C5 | B40: Pergunta específica 5 (ver Revisão detalhada) | C40: OK | D40: PARCIAL | E40: PARCIAL | F40: PARCIAL | G40: PARCIAL | H40: PARCIAL | I40: OK | J40: OK | K40: PARCIAL | L40: AUSENTE | M40: OK | N40: PARCIAL | O40: PARCIAL | P40: PARCIAL | Q40: PARCIAL | R40: OK | S40: PARCIAL | T40: PARCIAL | U40: PARCIAL | V40: PARCIAL | W40: PARCIAL
B42: Total OK | C42: =COUNTIF(C4:C40,"OK") -> 13 | D42: =COUNTIF(D4:D40,"OK") -> 14 | E42: =COUNTIF(E4:E40,"OK") -> 15 | F42: =COUNTIF(F4:F40,"OK") -> 12 | G42: =COUNTIF(G4:G40,"OK") -> 7 | H42: =COUNTIF(H4:H40,"OK") -> 13 | I42: =COUNTIF(I4:I40,"OK") -> 13 | J42: =COUNTIF(J4:J40,"OK") -> 7 | ... W42: =COUNTIF(W4:W40,"OK") -> 16
B43: Total PARCIAL | C43: =COUNTIF(C4:C40,"PARCIAL") -> 21 | D43: =COUNTIF(D4:D40,"PARCIAL") -> 19 | E43: =COUNTIF(E4:E40,"PARCIAL") -> 18 | F43: =COUNTIF(F4:F40,"PARCIAL") -> 21 | G43: =COUNTIF(G4:G40,"PARCIAL") -> 21 | H43: =COUNTIF(H4:H40,"PARCIAL") -> 18 | I43: =COUNTIF(I4:I40,"PARCIAL") -> 21 | J43: =COUNTIF(J4:J40,"PARCIAL") -> 28 | ... W43: =COUNTIF(W4:W40,"PARCIAL") -> 13
B44: Total AUSENTE | C44: =COUNTIF(C4:C40,"AUSENTE") -> 3 | D44: =COUNTIF(D4:D40,"AUSENTE") -> 4 | E44: =COUNTIF(E4:E40,"AUSENTE") -> 4 | F44: =COUNTIF(F4:F40,"AUSENTE") -> 4 | G44: =COUNTIF(G4:G40,"AUSENTE") -> 9 | H44: =COUNTIF(H4:H40,"AUSENTE") -> 6 | I44: =COUNTIF(I4:I40,"AUSENTE") -> 3 | J44: =COUNTIF(J4:J40,"AUSENTE") -> 2 | ... W44: =COUNTIF(W4:W40,"AUSENTE") -> 8

Sheet Revisão detalhada
A1: Revisão campo a campo (use o filtro da coluna Projeto)
A3: Projeto | B3: Bloco | C3: Código | D3: Campo / pergunta | E3: Status | F3: O que o documento traz | G3: O que falta / ajuste
A4: P01 Escola de Ofícios do Espetáculo | B4: SALIC | C4: A1 | D4: Identificação (nome, proponente, CNPJ/CNAE, área/segmento, Art. 18) | E4: PARCIAL | F4: Nome e proponente Educare Formação e Desenvolvimento LTDA, CNPJ 44.799.592/0001-29; mecanismos Rouanet + LEIC. O texto alterna 'Educare', 'Educari' e 'Educação'. | G4: Declarar área Artes Cênicas / segmento Empreend Ações Educ-Cult/Capacitação/Treinamento e pedido de Art. 18; conferir no cartão CNPJ se há CNAE cultural compatível (ex.: 85.92-9/99 ensino de arte e cultura; 90.01-9/99) – razão social 'Formação e Desenvolvimento' sugere CNAE de treinamento (85.99), o que pode barrar a admissibilidade (art. 4º §3º); padronizar o nome 'Educare'.
A5: P01 Escola de Ofícios do Espetáculo | B5: SALIC | C5: A2 | D5: Período de execução e prazo de captação | E5: PARCIAL | F5: Ago–nov/2027 com 'preparação anterior e encerramento posterior' sem datas. | G5: Fixar datas (sugestão: 01/06/2027 a 31/12/2027) e prazo de captação; o cronograma precisa casar com a planilha (pré jun–jul, produção ago–nov, pós dez).
A6: P01 Escola de Ofícios do Espetáculo | B6: SALIC | C6: A3 | D6: Resumo | E6: OK | F6: Item 1 'Apresentação' e item 2 'Objeto' descrevem o projeto de forma clara. | G6: Condensar em resumo único para o campo do SALIC, citando 270 vagas, 9 turmas, 3 núcleos, 24h e mostra.
A7: P01 Escola de Ofícios do Espetáculo | B7: SALIC | C7: A4 | D7: Objetivos (geral e específicos mensuráveis) | E7: PARCIAL | F7: Objetivo geral e 8 específicos; vários com 'sempre que possível'/'aproximadamente'. | G7: Tornar mensuráveis: nº de visitas (9), taxa mínima de conclusão (ex.: 70%), público da mostra (número fechado), % de educadores dos territórios.
A8: P01 Escola de Ofícios do Espetáculo | B8: SALIC | C8: A5 | D8: Justificativa (art. 1º/3º Lei 8.313, relevância, dados) | E8: PARCIAL | F8: Justificativa qualitativa consistente (bastidores invisibilizados, descentralização, mostra). | G8: Incluir dados (ex.: oferta de formação técnica em artes cênicas em BH/RMBH, IVS dos territórios) e citar expressamente art. 1º (I, II) e art. 3º, I, 'c'/'d' da Lei 8.313/91 (formação e acesso).
A9: P01 Escola de Ofícios do Espetáculo | B9: SALIC | C9: A6 | D9: Acessibilidade (arquitetônica, comunicacional, divulgação; Guia MDHC) | E9: PARCIAL | F9: Item 12 lista diretrizes genéricas: Libras 'quando o perfil demandar', materiais 'sempre que necessário', atenção a autistas. | G9: Transformar em medidas fixas e orçadas: Libras em aulas inaugurais, visitas e mostra; audiodescrição na mostra; materiais ampliados/braille; consultor de acessibilidade; vídeo com Libras/AD; citar uso obrigatório do Guia MDHC (art. 40). Pendência MÉDIA 5 continua aberta.
A10: P01 Escola de Ofícios do Espetáculo | B10: SALIC | C10: A7 | D10: Democratização de acesso (art. 41) | E10: OK | F10: Item 13: 100% gratuito, inscrições públicas, prioridade socioeconômica/territorial e escola pública; mostra gratuita. | G10: Definir percentual de vagas reservadas (ex.: ≥50% estudantes de escola pública) e fluxo de seleção objetivo (pendência MÉDIA 6).
A11: P01 Escola de Ofícios do Espetáculo | B11: SALIC | C11: A8 | D11: Ampliação de acesso (art. 42) / contrapartida (art. 44) | E11: PARCIAL | F11: Visitas técnicas e mostra existem, mas nenhuma medida do art. 42 é declarada. Sem venda: contrapartida do art. 44 não se aplica. | G11: Declarar ao menos: art. 42, VI (ação para adolescentes/jovens e educadores) e III (vídeo-memória online com Libras e audiodescrição) – ambas já orçadas.
A12: P01 Escola de Ofícios do Espetáculo | B12: SALIC | C12: A9 | D12: Etapas de trabalho | E12: OK | F12: Item 18 – cronograma macro (pré-execução, ago, set, out, nov, pós). | G12: Detalhar entregas por mês e responsáveis; alinhar às etapas da planilha.
A13: P01 Escola de Ofícios do Espetáculo | B13: SALIC | C13: A10 | D13: Ficha técnica | E13: PARCIAL | F13: Coord. geral Túlio Gama; coord. pedagógica Jade Oliveira; coord. técnica e educadores 'a definir'. | G13: Nomear coordenador técnico e ao menos 1 educador por eixo; anexar currículos (Anexo II 3.1); confirmar vínculo de Túlio Gama com a Educare (art. 15 e 23).
A14: P01 Escola de Ofícios do Espetáculo | B14: SALIC | C14: A11 | D14: Sinopse/descrição do conteúdo artístico | E14: PARCIAL | F14: Ementas por eixo (item 8) e descrição da mostra (item 11). | G14: Definir o espetáculo/grupo parceiro da mostra (sinopse, duração, classificação, autorização do autor).
... A40: P01 Escola de Ofícios do Espetáculo | B40: Pergunta específica | C40: C5 | D40: Como será avaliada a aprendizagem? Haverá montagem prática, apresentação final, certificação ou aproximação com oportunidades de trabalho? | E40: OK | F40: Frequência mínima 60%, avaliação dos educadores e participação na mostra; certificado da Educare; sem promessa de inserção profissional. | G40: Instrumentos de avaliação (ficha do educador, questionário) – pendência MÉDIA 7.
A41: P01 Escola de Ofícios do Espetáculo | B41: Conformidade IN 29 | D41: Limite por projeto e carteira PJ (arts. 10–11) | E41: OK | F41: R$ 500 mil ≤ R$ 1,5 mi; carteira Educare = P01 R$ 500 mil + P18 R$ 250 mil = R$ 750 mil, 2 projetos.
A42: P01 Escola de Ofícios do Espetáculo | B42: Conformidade IN 29 | D42: CNAE cultural compatível (art. 4º §3º) | E42: ATENÇÃO | F42: Razão social 'Formação e Desenvolvimento' indica CNAE de treinamento; se não houver CNAE cultural (ex.: 85.92-9/99, 90.01-9/99) o SALIC bloqueia. Incluir CNAE secundário antes do cadastro, se necessário.
A43: P01 Escola de Ofícios do Espetáculo | B43: Conformidade IN 29 | D43: Portfólio (art. 4º §4º/§5º; Anexo II 1.1) | E43: ATENÇÃO | F43: Valor > R$ 200 mil: portfólio cultural obrigatório. Pendência ALTA 2 em aberto.
A44: P01 Escola de Ofícios do Espetáculo | B44: Conformidade IN 29 | D44: Mesma carteira (art. 15) e remuneração do proponente (art. 23) | E44: ATENÇÃO | F44: Túlio Gama (coord. geral) é proponente PF de P07/P12. Se for sócio/dirigente da Educare, as carteiras se unem e os pagamentos a ele contam no limite de 20% do proponente; confirmar quadro societário.
A45: P01 Escola de Ofícios do Espetáculo | B45: Conformidade IN 29 | D45: Fracionamento (art. 32, VII; Anexo I XXXIII) | E45: ATENÇÃO | F45: Objetos próximos no portfólio: P03 (oficinas de música/grafite/audiovisual para jovens de vilas de BH/Contagem – IHV) e P18 (Educare – idosos). Objetivos e públicos diferem e nenhum limite é ultrapassado; manter redações e territórios distintos e não usar o eixo audiovisual de forma idêntica ao P03.
A46: P01 Escola de Ofícios do Espetáculo | B46: Conformidade IN 29 | D46: Art. 18 da IN (projetos educativos/sociais: só custos artístico-culturais) | E46: ATENÇÃO | F46: Planilha contém apenas custos culturais; lanche e transporte coletivo estão vinculados às atividades. Não incluir bolsas, auxílios individuais ou promessas de emprego.
A47: P01 Escola de Ofícios do Espetáculo | B47: Conformidade IN 29 | D47: Custos vinculados e captação (arts. 19, 20, 22) | E47: OK | F47: Adm 8,5%, acessibilidade/divulgação 17,8%, captação 10% (R$ 36.670) do valor do projeto (R$ 366.700).
A48: P01 Escola de Ofícios do Espetáculo | B48: Conformidade IN 29 | D48: Limite de 20% por fornecedor (art. 24) | E48: OK | F48: Maior fornecedor potencial (locação de luz/som e ônibus) < R$ 60 mil (12%). Se Armind fornecer toda a luz, conferir o teto.
A49: P01 Escola de Ofícios do Espetáculo | B49: Conformidade IN 29 | D49: Cachês (art. 26) | E49: OK | F49: Direção R$ 10 mil (individual) e grupo R$ 8 mil – abaixo dos tetos.
A50: P01 Escola de Ofícios do Espetáculo | B50: Conformidade IN 29 | D50: Acessibilidade obrigatória e Guia MDHC (arts. 38–40) | E50: ATENÇÃO | F50: Texto genérico; a planilha prevê recursos concretos – atualizar o texto.
A51: P01 Escola de Ofícios do Espetáculo | B51: Conformidade IN 29 | D51: Democratização (art. 41) / ampliação (art. 42) / contrapartida (art. 44) | E51: ATENÇÃO | F51: 100% gratuito (OK); falta declarar a medida do art. 42 (sugestão VI + III); art. 44 não se aplica (sem venda).
A52: P01 Escola de Ofícios do Espetáculo | B52: Conformidade IN 29 | D52: Direito autoral do texto da mostra (Anexo II 3.3; art. 27) | E52: ATENÇÃO | F52: Grupo/espetáculo da mostra não definido – anexar autorização do autor ou usar texto em domínio público/criação coletiva.
... A54: P01 Escola de Ofícios do Espetáculo | B54: Conformidade IN 29 | D54: Prazo de apresentação (art. 5º – até 31/10) | E54: ATENÇÃO | F54: Faltam 17 dias (hoje 14/10/2026) e as pendências ALTA 1, 2, 4, 8 e 9 seguem abertas.
A55: P02 Mestres e Aprendizes | B55: SALIC | C55: A1 | D55: Identificação (nome, proponente, CNPJ/CNAE, área/segmento, Art. 18) | E55: PARCIAL | F55: Título, Aver Mídia Produções LTDA, CNPJ 46.152.875/0001-00; enquadramento preliminar Patrimônio/Salvaguarda, 'pretendido art. 18'. | G55: Confirmar CNAE compatível com Patrimônio Cultural (produtora audiovisual pode não ter CNAE correspondente – art. 4º §3º); fechar segmento definitivo (pendência ALTA 5).
A56: P02 Mestres e Aprendizes | B56: SALIC | C56: A2 | D56: Período de execução e prazo de captação | E56: PARCIAL | F56: 8 meses: jul/2027 a fev/2028, com correspondência mês a mês. | G56: Datas exatas e prazo de captação.
A57: P02 Mestres e Aprendizes | B57: SALIC | C57: A3 | D57: Resumo | E57: OK | F57: Item 3 'Resumo' completo; item 28 traz texto para o produto principal. | G57: —
A58: P02 Mestres e Aprendizes | B58: SALIC | C58: A4 | D58: Objetivos | E58: OK | F58: Objetivo geral e 10 específicos quantificados (4 mestres, 120 vagas, 24 encontros, 48h, 1 exposição). | G58: Incluir meta de conclusão (frequência mínima).
A59: P02 Mestres e Aprendizes | B59: SALIC | C59: A5 | D59: Justificativa | E59: PARCIAL | F59: Justificativa conceitual forte (transmissão pela convivência, remuneração e reconhecimento dos mestres, intergeracionalidade). | G59: Dados e histórico de cada saber/bem (depende dos mestres), citar art. 1º e art. 3º (II e IV) da Lei 8.313 e aderência à salvaguarda (Decreto 3.551/2000).
A60: P02 Mestres e Aprendizes | B60: SALIC | C60: A6 | D60: Acessibilidade | E60: PARCIAL | F60: Item 15: critérios físicos, linguagem clara, legendas, descrição de imagens; Libras/AD 'conforme necessidades'. | G60: Fixar recursos: Libras em acolhimento/integrados/abertura, AD e recursos táteis na exposição, consultor; citar Guia MDHC.
A61: P02 Mestres e Aprendizes | B61: SALIC | C61: A7 | D61: Democratização de acesso | E61: OK | F61: 100% gratuito, apoio presencial à inscrição, catálogo digital gratuito, critérios transparentes. | G61: Fixar proporção de vagas reservadas a escolas/comunidades (pendência MÉDIA 10).
A62: P02 Mestres e Aprendizes | B62: SALIC | C62: A8 | D62: Ampliação de acesso (art. 42) / contrapartida (art. 44) | E62: PARCIAL | F62: Medidas implícitas (exposição gratuita, catálogo digital, jovens a partir de 12 anos). Sem venda: art. 44 não se aplica. | G62: Declarar art. 42, I (doação de 10% do catálogo), III (vídeos com Libras/AD) e/ou VI (ação para adolescentes/jovens e educadores).
A63: P02 Mestres e Aprendizes | B63: SALIC | C63: A9 | D63: Etapas de trabalho | E63: OK | F63: Item 13: Etapas 1–4 com atividades; item 22 cronograma de 14 atividades. | G63: —
A64: P02 Mestres e Aprendizes | B64: SALIC | C64: A10 | D64: Ficha técnica | E64: AUSENTE | F64: Todas as funções 'nome a definir', inclusive os 4 mestres. | G64: Nomes e currículos de coordenação, curadoria e mestres; experiência junto às comunidades (Anexo II 8.1.6).
A65: P02 Mestres e Aprendizes | B65: SALIC | C65: A11 | D65: Descrição do conteúdo/bens culturais | E65: PARCIAL | F65: Saberes de referência (bordado, cerâmica, bonecos, viola) 'não definitivos'. | G65: Identificar cada bem/saber, seu território e detentores.
A66: P02 Mestres e Aprendizes | B66: SALIC | C66: A12 | D66: Impacto ambiental – NÃO é campo do SALIC 2026 (opcional em 'Outras informações') | E66: OK | F66: Item 12: dimensionar insumos, reutilização, descarte e armazenamento seguros. | G66: Detalhar destino de resíduos de cerâmica/tintas.
... A91: P02 Mestres e Aprendizes | B91: Pergunta específica | C91: C5 | D91: Haverá apresentação, exposição ou registro dos saberes? Como serão definidos remuneração, créditos, autorizações e conteúdos que podem ser divulgados? | E91: PARCIAL | F91: Exposição gratuita, catálogo, acervo e vídeos; mestres creditados como detentores; não divulgação de saberes restritos; autorizações específicas. | G91: Memória de cálculo da remuneração (adotada aqui: R$ 2.800/mês por mestre + cachês de concepção e abertura), termos e ficha de limites de registro (pendência 16).
A92: P02 Mestres e Aprendizes | B92: Conformidade IN 29 | D92: Limites de valor/carteira (arts. 10, 11, 14) | E92: OK | F92: R$ 400 mil; carteira Aver Mídia = P02 R$ 400 mil + P15 R$ 450 mil = R$ 850 mil, 2 projetos; patrimônio ainda fica fora dos limites (art. 14, II e §ú).
A93: P02 Mestres e Aprendizes | B93: Conformidade IN 29 | D93: CNAE cultural compatível (art. 4º §3º) | E93: ATENÇÃO | F93: Verificar se o CNPJ da Aver Mídia tem CNAE aceito pelo SALIC para Patrimônio Cultural (ou Artes Visuais, no Plano B).
A94: P02 Mestres e Aprendizes | B94: Conformidade IN 29 | D94: Portfólio (art. 4º §4º) | E94: ATENÇÃO | F94: Obrigatório (> R$ 200 mil); pendência ALTA 1.
A95: P02 Mestres e Aprendizes | B95: Conformidade IN 29 | D95: Documentos de Patrimônio Cultural (Anexo II 8.1) | E95: VIOLA | F95: No estado atual não há identificação dos bens, relatório de reconhecido valor nem anuência da comunidade detentora – proposta seria arquivada na admissibilidade/Iphan.
A96: P02 Mestres e Aprendizes | B96: Conformidade IN 29 | D96: Fracionamento (Anexo I XXXIII) | E96: ATENÇÃO | F96: Proximidade temática com P05 Sons do Congado (Ado Viana – salvaguarda de congado). Não incluir congado entre os saberes e manter objetivos distintos.
A97: P02 Mestres e Aprendizes | B97: Conformidade IN 29 | D97: Art. 18 da IN (custos permitidos) | E97: OK | F97: Manifestação de tradição/patrimônio imaterial – custos integrais admitidos.
A98: P02 Mestres e Aprendizes | B98: Conformidade IN 29 | D98: Custos vinculados e captação (arts. 19, 20, 22) | E98: OK | F98: Adm 7,8%, acessibilidade/divulgação 14,5%, captação 10% (R$ 30.219) sobre R$ 302.191.
A99: P02 Mestres e Aprendizes | B99: Conformidade IN 29 | D99: Cachês (art. 26) | E99: OK | F99: Mestres: R$ 2.800/mês e cachês de R$ 1.500 – muito abaixo de R$ 25 mil.
A100: P02 Mestres e Aprendizes | B100: Conformidade IN 29 | D100: Bens permanentes (art. 30) | E100: ATENÇÃO | F100: 10 violas (R$ 6 mil): justificar economicidade x locação e declarar destinação cultural.
A101: P02 Mestres e Aprendizes | B101: Conformidade IN 29 | D101: Limite de 20% por fornecedor (art. 24) | E101: OK | F101: Nenhum fornecedor acima de ~R$ 15 mil; mestres são pessoas distintas.
A102: P02 Mestres e Aprendizes | B102: Conformidade IN 29 | D102: Acessibilidade e Guia MDHC (arts. 38–40) | E102: ATENÇÃO | F102: Texto condicionado ('conforme necessidades'); planilha prevê recursos – alinhar texto.
A103: P02 Mestres e Aprendizes | B103: Conformidade IN 29 | D103: Ampliação de acesso (art. 42) / contrapartida (art. 44) | E103: ATENÇÃO | F103: Declarar medida(s) do art. 42; sem venda, art. 44 não se aplica.
... A105: P02 Mestres e Aprendizes | B105: Conformidade IN 29 | D105: Prazo (art. 5º – 31/10/2026) | E105: ATENÇÃO | F105: 17 dias para selecionar mestres e reunir dossiês – caminho crítico.
A106: P03 Cultura Viva nas Vilas | B106: SALIC | C106: A1 | D106: Identificação (nome, proponente, CNPJ/CNAE, área/segmento, Art. 18) | E106: PARCIAL | F106: Nome e proponente 'Instituto Horizonte Vivo (IHGV)'; sem CNPJ; Ado Viana como referência institucional com nome civil e função 'a confirmar'. | G106: CNPJ, estatuto, ata e representante; padronizar a sigla (IHV x IHGV); CNAE cultural compatível com Artes Visuais (ex.: 94.93-6/00 com objeto cultural, 85.92-9/99, 90.02-7/01); declarar área/segmento e Art. 18.
A107: P03 Cultura Viva nas Vilas | B107: SALIC | C107: A2 | D107: Período de execução e prazo de captação | E107: PARCIAL | F107: 4 a 6 meses, janela indicativa abr–set/2027; cronograma mensal. | G107: Fixar datas (sugestão 01/04 a 30/09/2027) e prazo de captação; as oficinas de jun–jul coincidem com férias escolares de julho – validar com escolas.
A108: P03 Cultura Viva nas Vilas | B108: SALIC | C108: A3 | D108: Resumo | E108: OK | F108: Seção 'Resumo' clara com metas. | G108: —
A109: P03 Cultura Viva nas Vilas | B109: SALIC | C109: A4 | D109: Objetivos | E109: OK | F109: Objetivo geral e 8 específicos quantificados (8 oficinas, 200 participantes, 6 artistas, 4 mostras). | G109: —
A110: P03 Cultura Viva nas Vilas | B110: SALIC | C110: A5 | D110: Justificativa | E110: PARCIAL | F110: Aderência à Política Cultura Viva de BH, descentralização, remuneração de artistas locais. | G110: Dados de cada território (IVS, equipamentos culturais, jovens) e citação do art. 1º e art. 3º da Lei 8.313; diagnóstico local (pergunta 1).
A111: P03 Cultura Viva nas Vilas | B111: SALIC | C111: A6 | D111: Acessibilidade | E111: PARCIAL | F111: Vistoria/checklist por espaço, formulário com necessidades, legendas nos vídeos, Libras nas mostras e AD conforme necessidade. | G111: Fixar AD nas mostras, consultor, Guia MDHC e acessibilidade nas oficinas (pendência 8 riscada, mas sem plano por espaço no texto).
A112: P03 Cultura Viva nas Vilas | B112: SALIC | C112: A7 | D112: Democratização de acesso | E112: OK | F112: Gratuito; 12 vagas por oficina via escolas e 13 abertas; cadastro único; lista de espera. | G112: —
A113: P03 Cultura Viva nas Vilas | B113: SALIC | C113: A8 | D113: Ampliação de acesso (art. 42) / contrapartida (art. 44) | E113: PARCIAL | F113: Não declarada; o projeto se encaixa no art. 42, VI (crianças, adolescentes, jovens e educadores). Sem venda: art. 44 n/a. | G113: Declarar art. 42, VI e, se houver vídeo com Libras/AD, inciso III.
A114: P03 Cultura Viva nas Vilas | B114: SALIC | C114: A9 | D114: Etapas de trabalho | E114: OK | F114: Cronograma preliminar com 5 etapas mensais. | G114: Datas por território.
A115: P03 Cultura Viva nas Vilas | B115: SALIC | C115: A10 | D115: Ficha técnica | E115: AUSENTE | F115: Somente Ado Viana como referência; curadoria, coordenação pedagógica e oficineiros a definir. | G115: Nomes e currículos (curadoria, coordenação, ≥6 oficineiros).
A116: P03 Cultura Viva nas Vilas | B116: SALIC | C116: A11 | D116: Descrição do conteúdo artístico | E116: PARCIAL | F116: Linguagens e distribuição por território definidas; resultados (painel, curtas, apresentação). | G116: Ementa de cada oficina.
A117: P03 Cultura Viva nas Vilas | B117: SALIC | C117: A12 | D117: Impacto ambiental – NÃO é campo do SALIC 2026 (opcional em 'Outras informações') | E117: AUSENTE | F117: Não há medidas ambientais. | G117: Tintas base água quando possível, coleta e descarte correto de latas de spray, reaproveitamento de painéis, digitalização.
... A142: P03 Cultura Viva nas Vilas | B142: Pergunta específica | C142: C5 | D142: O nome 'Cultura Viva' será apenas a identidade do projeto ou haverá articulação efetiva com Pontos de Cultura e iniciativas dessa política? | E142: PARCIAL | F142: O texto diz que é o nome do projeto, com intenção de articulação com Pontos de Cultura, sem afirmar certificação. | G142: Identificar Pontos de Cultura nos 4 territórios (Rede Cultura Viva) e obter cartas de parceria, ou deixar explícito que não há vínculo com a política (evita leitura de uso indevido do nome).
A143: P03 Cultura Viva nas Vilas | B143: Conformidade IN 29 | D143: 1º projeto ≤ R$ 200 mil – dispensa de portfólio (art. 4º §5º) | E143: ATENÇÃO | F143: Valor total fixado em exatamente R$ 200.000 (valor do projeto R$ 149.291). Confirmar que o IHV nunca apresentou projeto ao Pronac; qualquer acréscimo exige portfólio.
A144: P03 Cultura Viva nas Vilas | B144: Conformidade IN 29 | D144: Mesma carteira PF/PJ dirigente (art. 15, I) | E144: ATENÇÃO | F144: Ado Viana é proponente PF de P05 (R$ 300 mil) e P16 (R$ 200 mil) – carteira PF já no limite (2 projetos/R$ 500 mil). Se ele for sócio/dirigente do IHV, as carteiras se unem (prevalece o limite PJ, então não há estouro numérico), mas: o IHV deixa de ser 'proponente novo' na prática e a dispensa de portfólio pode ser questionada; a operação pode ser lida como contorno do teto PF; pagamentos a Ado contam no limite de remuneração do proponente (art. 23). Confirmar função estatutária e registrar de forma transparente.
A145: P03 Cultura Viva nas Vilas | B145: Conformidade IN 29 | D145: CNAE cultural (art. 4º §3º) | E145: ATENÇÃO | F145: Verificar CNAE do IHV compatível com Artes Visuais/educação cultural.
A146: P03 Cultura Viva nas Vilas | B146: Conformidade IN 29 | D146: Limite de projeto/carteira PJ (arts. 10–11) | E146: OK | F146: R$ 200 mil, 1 projeto.
A147: P03 Cultura Viva nas Vilas | B147: Conformidade IN 29 | D147: Fracionamento (Anexo I XXXIII) | E147: ATENÇÃO | F147: Proximidade com P01 (Educare – oficinas para jovens de periferias de BH/Contagem com eixo audiovisual). Linguagens, territórios e proponentes distintos; nenhum limite ultrapassado. Manter Eldorado/Contagem e o recorte de cultura urbana distintos do P01.
A148: P03 Cultura Viva nas Vilas | B148: Conformidade IN 29 | D148: Art. 18 da IN (projeto de caráter social) | E148: ATENÇÃO | F148: Só custos artístico-culturais; planilha atende. Evitar linguagem 'socioassistencial'.
A149: P03 Cultura Viva nas Vilas | B149: Conformidade IN 29 | D149: Risco Art. 26 (música popular cantada / Humanidades) | E149: ATENÇÃO | F149: Produto principal em Artes Visuais Educ-Cult; apresentações musicais apenas como parte das mostras.
A150: P03 Cultura Viva nas Vilas | B150: Conformidade IN 29 | D150: Custos vinculados e captação (arts. 19, 20, 22) | E150: OK | F150: Adm 6,7%, acessibilidade/divulgação 17,3%, captação 10% (R$ 14.929).
A151: P03 Cultura Viva nas Vilas | B151: Conformidade IN 29 | D151: Cachês (art. 26) e fornecedor 20% (art. 24) | E151: OK | F151: Cachês de R$ 1.500; maior fornecedor < R$ 15 mil (7,5%).
A152: P03 Cultura Viva nas Vilas | B152: Conformidade IN 29 | D152: Acessibilidade (arts. 38–40) | E152: ATENÇÃO | F152: Planilha prevê Libras, AD, apoio e consultor; texto ainda condicional.
A153: P03 Cultura Viva nas Vilas | B153: Conformidade IN 29 | D153: Democratização (art. 41) / ampliação (art. 42) / contrapartida (art. 44) | E153: ATENÇÃO | F153: Gratuito (OK); declarar art. 42, VI; art. 44 n/a.
A154: P03 Cultura Viva nas Vilas | B154: Conformidade IN 29 | D154: Participação de menores e autorizações de grafite | E154: ATENÇÃO | F154: Termos de responsáveis, uso de imagem e autorização formal para painéis (pendência ALTA 9 aberta).
A155: P03 Cultura Viva nas Vilas | B155: Conformidade IN 29 | D155: Prazo (31/10/2026) | E155: ATENÇÃO | F155: Pendências ALTA 1, 6 e 9 abertas; regularidade do IHV é pré-requisito do cadastro.
A156: P04 Cena Mineira em Movimento | B156: SALIC | C156: A1 | D156: Identificação (nome, proponente, CNPJ/CNAE, área/segmento, Art. 18) | E156: PARCIAL | F156: Título; proponente 'Mobox' sem razão social/CNPJ; área Artes Cênicas; produto 'Espetáculo de Artes Cênicas'. | G156: Razão social, CNPJ e representante (pendência ALTA 1); CNAE cultural (ex.: 90.01-9/99, 90.01-9/02); segmento exato do Anexo IV e pedido de Art. 18.
A157: P04 Cena Mineira em Movimento | B157: SALIC | C157: A2 | D157: Período de execução e prazo de captação | E157: PARCIAL | F157: Abr–nov/2027 com distribuição mensal por eixo. | G157: Datas exatas (sugestão 01/04 a 30/11/2027) e prazo de captação; julho concentra o eixo Histórico em período de férias escolares – rever matinês escolares.
A158: P04 Cena Mineira em Movimento | B158: SALIC | C158: A3 | D158: Resumo | E158: OK | F158: Item 1 completo. | G158: Trocar faixas '12 a 24' por números fechados.
A159: P04 Cena Mineira em Movimento | B159: SALIC | C159: A4 | D159: Objetivos | E159: PARCIAL | F159: Objetivo geral e 12 específicos; metas em faixas (12–24 sessões e oficinas). | G159: Fixar 24 apresentações e 24 oficinas (premissa da planilha) ou outro número decidido.
A160: P04 Cena Mineira em Movimento | B160: SALIC | C160: A5 | D160: Justificativa | E160: PARCIAL | F160: Concentração da oferta nas capitais; 'estudos recentes' sobre impacto da Rouanet sem fonte. | G160: Dados por município (existência de teatro, programação, IDH/população), fonte dos estudos citados, art. 1º e 3º da Lei 8.313.
A161: P04 Cena Mineira em Movimento | B161: SALIC | C161: A6 | D161: Acessibilidade | E161: PARCIAL | F161: Lista de requisitos físicos; Libras/AD 'definidos após a seleção'. | G161: Fixar: Libras em todas as sessões, AD em ao menos 1 sessão por cidade, apoio PcD, programas em braille, consultor e Guia MDHC (orçados).
A162: P04 Cena Mineira em Movimento | B162: SALIC | C162: A7 | D162: Democratização de acesso | E162: OK | F162: 100% gratuito, retirada antecipada, reserva para escolas e organizações. | G162: Percentual reservado a escolas públicas/organizações sociais.
A163: P04 Cena Mineira em Movimento | B163: SALIC | C163: A8 | D163: Ampliação de acesso (art. 42) / contrapartida (art. 44) | E163: OK | F163: Oficinas e conversas pós-espetáculo como ampliação (art. 42, V). Sem venda: art. 44 n/a. | G163: Reforçar com art. 42, III (6 sessões publicadas com Libras/AD) e VI (matinês escolares).
A164: P04 Cena Mineira em Movimento | B164: SALIC | C164: A9 | D164: Etapas de trabalho | E164: OK | F164: Item 23: cronograma abr–nov com eixos. | G164: Datas por município.
A165: P04 Cena Mineira em Movimento | B165: SALIC | C165: A10 | D165: Ficha técnica | E165: AUSENTE | F165: Item 20 lista só perfis. | G165: Nomes e currículos da coordenação, curadoria, coordenação técnica e acessibilidade (Anexo II 3.1).
A166: P04 Cena Mineira em Movimento | B166: SALIC | C166: A11 | D166: Sinopse/descrição das obras | E166: AUSENTE | F166: Espetáculos não selecionados. | G166: Pré-selecionar os 4 espetáculos (ou ao menos parte por convite) com sinopse, duração, classificação e ficha técnica antes do cadastro.
A167: P04 Cena Mineira em Movimento | B167: SALIC | C167: A12 | D167: Impacto ambiental – NÃO é campo do SALIC 2026 (opcional em 'Outras informações') | E167: PARCIAL | F167: Organização por eixos para reduzir deslocamentos. | G167: Medidas adicionais: material digital, compensação de emissões, LED, reaproveitamento de banners.
... A192: P04 Cena Mineira em Movimento | B192: Pergunta específica | C192: C5 | D192: Haverá oficinas, conversas com artistas ou outras atividades de formação de público? Qual será a quantidade e como se relacionarão com os espetáculos? | E192: PARCIAL | F192: 1 a 2 oficinas por cidade (~2h, 30–40 vagas) ministradas pelos artistas das companhias; conversas pós-espetáculo. | G192: Quantidade final (planilha usa 24 oficinas de 3h) e conteúdo programático.
A193: P04 Cena Mineira em Movimento | B193: Conformidade IN 29 | D193: Limite por projeto e carteira PJ (arts. 10–11) | E193: OK | F193: R$ 900 mil ≤ R$ 1,5 mi; carteira Mobox = P04 R$ 900 mil + P11 R$ 800 mil = R$ 1,7 mi, 2 projetos.
A194: P04 Cena Mineira em Movimento | B194: Conformidade IN 29 | D194: CNAE cultural (art. 4º §3º) e portfólio (§4º) | E194: ATENÇÃO | F194: Conferir CNAE de produção/artes cênicas e anexar portfólio da Mobox.
A195: P04 Cena Mineira em Movimento | B195: Conformidade IN 29 | D195: Fracionamento (Anexo I XXXIII) | E195: ATENÇÃO | F195: Outros projetos de circulação no interior de MG no portfólio: P07 Concertos nas Praças (música), P09 Auto de Natal Mineiro (Armind), P10 Natal nas Cidades Mineiras, P17 Corpo em Cena (dança?) e P11 Festa Junina (Mobox). Objetivos distintos e sem estouro de limites; evitar sobreposição de municípios/calendário com P09/P10/P17 e não selecionar espetáculos desses projetos.
A196: P04 Cena Mineira em Movimento | B196: Conformidade IN 29 | D196: Remuneração do proponente (art. 23) | E196: ATENÇÃO | F196: Se coordenação geral e produção executiva forem da própria Mobox: R$ 108 mil = 12% do valor – dentro dos 20%; somar outros pagamentos a coligadas.
A197: P04 Cena Mineira em Movimento | B197: Conformidade IN 29 | D197: Limite de 20% por fornecedor (art. 24) | E197: OK | F197: Maior fornecedor potencial (vans R$ 50 mil, ou luz+som R$ 42 mil) < 20% (R$ 180 mil).
A198: P04 Cena Mineira em Movimento | B198: Conformidade IN 29 | D198: Cachês (art. 26) | E198: OK | F198: R$ 6.000 por apresentação de grupo (teto R$ 50 mil).
A199: P04 Cena Mineira em Movimento | B199: Conformidade IN 29 | D199: Direitos autorais (art. 27; Anexo II 3.3) e ECAD (art. 29) | E199: ATENÇÃO | F199: Sem espetáculos definidos não há autorizações dos autores; prever na chamada a obrigação de apresentar anuência; ECAD orçado.
A200: P04 Cena Mineira em Movimento | B200: Conformidade IN 29 | D200: Custos vinculados e captação (arts. 19, 20, 22) | E200: OK | F200: Adm 9,0%, acessibilidade/divulgação 18,1%, captação 10% (R$ 65.643) sobre R$ 656.437.
...

Sheet Enquadramento e pendências
A1: Enquadramento Art. 18, pendências críticas e recomendações por projeto
A3: Projeto | B3: Produto principal e secundários | C3: Área / segmento (Anexo IV) | D3: Enquadr. | E3: Análise de enquadramento | F3: Pendências críticas | G3: Recomendações | H3: Versão mínima
A4: P01 Escola de Ofícios do Espetáculo | B4: Curso/Oficina – ciclo formativo de iniciação aos ofícios técnicos e criativos das artes cênicas (9 turmas x 24h, 270 vagas, 3 núcleos) Secundários: – Mostra final integrada – apresentação teatral com figurino, maquiagem, luz e vídeo realizados pelos participantes (1 sessão gratuita) (Artes Cênicas / Apresentação ou Performance de Teatro) | C4: Artes Cênicas / Empreend Ações Educ-Cult/Capacitação/Treinamento | D4: Art. 18 | E4: Produto principal = oficinas (R$ ~300 mil das etapas de projeto, muito acima da mostra, ~R$ 52 mil), logo o enquadramento segue Artes Cênicas > 'Empreend Ações Educ-Cult/Capacitação/Treinamento' = Art. 18 (Anexo IV). Riscos: (1) o eixo Audiovisual pode levar o técnico a sugerir área Audiovisual – também Art. 18 ('Ações de capacitação e treinamento de pessoal'), mas convém redigi-lo como 'audiovisual integrado à cena/registro do espetáculo' para manter um único segmento cênico; (2) a mostra NÃO deve ser um show de música popular cantada (Art. 26) – escolher grupo TEATRAL (a proposta admite 'teatral ou musical'); como secundário não muda o enquadramento, mas evita questionamento; (3) o caráter 'social/educativo' (público vulnerável) atrai o art. 18 da IN: somente custos artístico-culturais – não incluir bolsas-auxílio, vale-transporte individual, inclusão produtiva ou promessa de empregabilidade (a própria proposta já veda isso – manter); (4) não chamar de 'curso técnico/profissionalizante' (evita leitura de educação formal). Redação recomendada no SALIC: 'Ações educativo-culturais de iniciação aos ofícios do espetáculo cênico (figurino, caracterização, iluminação cênica e audiovisual para a cena), com mostra cênica de culminância'. | F4: • Documentação jurídica da Educare (cartão CNPJ com CNAE cultural compatível, contrato social, representante) – sem isso o SALIC não admite. • Portfólio de atuação cultural da Educare (obrigatório para projeto de R$ 500 mil). • Projeto pedagógico formal com currículo da coordenadora pedagógica e plano de execução com carga horária e conteúdo programático por turma (Anexo II 7.2/7.3), incluindo a matriz núcleo x formação. • Cartas de anuência dos 3 núcleos e do local da mostra; definição do grupo teatral parceiro com autorização autoral. • Adotar a planilha orçamentária e transformar a acessibilidade em medidas concretas (Libras, AD, consultor, Guia MDHC). | G4: • Cadastrar como Artes Cênicas > Empreend Ações Educ-Cult/Capacitação/Treinamento (Art. 18), produto principal 'Curso/Oficina', e a mostra como produto secundário 'Apresentação ou Performance de Teatro'. • Padronizar o nome do proponente (Educare) em todo o texto; remover 'Educari'/'Educação'. • Declarar matriz sugerida: Iluminação 3 turmas, Audiovisual 2, Figurino 2, Maquiagem 2 (premissa da planilha) – ajustar se a matriz já fechada for diferente. • Escolher grupo TEATRAL (não show musical) para a mostra, evitando leitura de música popular cantada. • Declarar art. 42, VI e III como medidas de ampliação e publicar o vídeo-memória com Libras e AD. • Confirmar se Túlio Gama tem vínculo societário com a Educare (art. 15/23) e registrar no SALIC. • Ajustar o cronograma: pré jun–jul/2027, oficinas ago–nov, pós dez/2027; captação aberta desde a portaria. | H4: R$ 100.000: Reduzir para 1 núcleo (central, ex.: CRJ) com 3 turmas (iluminação, figurino/maquiagem combinados e audiovisual) = 90 vagas, mantendo 24h por turma; eliminar coordenação técnica e assistente de produção (coordenação pedagógica acumula), reduzir coordenação geral para 4 meses em dedicação parcial; 3 visitas técnicas (1 ônibus por turma); mostra simplificada no próprio núcleo com grupo parceiro e luz/som pequeno porte; manter Libras na aula inaugural e na mostra, AD na mostra e vídeo com Libras; comunicação apenas digital + cartazes. Custos vinculados proporcionais (adm ~8%, acessibilidade/divulgação ~15%, captação 10%).
A5: P02 Mestres e Aprendizes | B5: Percursos continuados de transmissão de saberes tradicionais conduzidos por 4 mestres (4 turmas x 48h, 120 aprendizes) Secundários: – Exposição Mestres e Aprendizes (trabalhos, processos e registros), gratuita, com catálogo como item da exposição (Artes Visuais / Exposição Cultural / Artística) | C5: Patrimônio Cultural / Salvaguarda do patrimônio cultural imaterial | D5: Art. 18 | E5: Hipótese do próprio documento (Patrimônio Cultural > Salvaguarda do patrimônio cultural imaterial) é correta e garante Art. 18: o Anexo I (LXIX) define salvaguarda incluindo a 'transmissão – essencialmente por meio da educação formal e não formal', e o produto principal (mestres + percursos ≈ R$ 225 mil) supera a exposição (≈ R$ 43 mil). Vantagens: art. 14 II e §ú (patrimônio fora dos limites de valor e quantidade) e art. 18 da IN não restringe custos (é manifestação de tradição). Riscos: (1) o projeto passa por análise do Iphan e exige o pacote do Anexo II item 8 (identificação do bem, relatório de reconhecido valor cultural, anuência da comunidade detentora, ficha técnica com experiência junto às comunidades) – hoje NADA disso existe e os mestres não foram escolhidos; (2) saberes genéricos (ex.: 'bordado' sem vínculo comunitário) podem não ser aceitos como patrimônio – escolher mestres com referência territorial/comunitária comprovável (ex.: bordadeiras de comunidade tradicional, ceramistas do Jequitinhonha, mamulengueiros/bonequeiros, violeiros de folia), e evitar congado para não sobrepor ao P05; (3) o catálogo NÃO deve ser cadastrado como produto 'Outras publicações ou Periódicos' (Humanidades, Art. 26) – mantê-lo como item da exposição/salvaguarda; (4) vídeos de memória como itens, não como produto audiovisual autônomo. PLANO B (se até ~25/10 não houver mestres + anuências + dossiês): cadastrar como Artes Visuais > Empreend Ações Educ-Cult/Capacitação/Treinamento (Art. 18), que dispensa o pacote patrimonial (exige projeto pedagógico – Anexo II 7) – a viola, nesse caso, deve ser tratada como prática artesanal/musical regional sem virar produto de música popular cantada. | F5: • Selecionar e formalizar os 4 mestres (cartas de anuência) e, quando o saber for coletivo, a anuência da comunidade detentora (Anexo II 8.1.3). • Dossiê por saber com relatório de reconhecido valor cultural, identificação e relatório do bem (Anexo II 8.1.1, 8.1.2.1, 8.1.4, 8.1.5) – ou acionar o Plano B (Artes Visuais – Ações Educ-Cult). • Documentação PJ da Aver Mídia com CNAE compatível e portfólio cultural. • Espaços das 4 turmas e da exposição com anuência. • Ficha técnica nominal e plano pedagógico (24 encontros/48h) validado por mestre. | G5: • Cadastrar Patrimônio Cultural > Salvaguarda do patrimônio cultural imaterial (Art. 18) como produto principal; exposição como produto secundário Artes Visuais > Exposição; catálogo e vídeos como itens (não produtos). • Escolher mestres com vínculo territorial/comunitário documentável (registros, matérias, inventários, declarações) e evitar congado (P05). • Fechar a base em 4 mestres/120 vagas (o 5º mestre não cabe nos R$ 400 mil com a remuneração proposta). • Declarar art. 42, I (10% do catálogo doado), III (vídeos com Libras e AD) e VI. • Justificar coordenação em dedicação parcial (valores abaixo do piso de referência) e remuneração dos mestres por memória de cálculo por encontro. • Definir protocolo de saberes sensíveis em termo assinado antes de qualquer registro. | H5: R$ 80.000: 2 mestres/2 turmas (60 aprendizes) mantendo 24 encontros de 2h; coordenação única (geral + pedagógica) em dedicação parcial e sem produtor executivo; materiais só dos 2 saberes; sem ônibus de vivências; exposição simplificada (1 semana) no espaço parceiro sem projeto expográfico contratado; catálogo apenas digital; registro fotográfico + 1 vídeo síntese; Libras na abertura e AD/recursos táteis na exposição; divulgação digital. Custos vinculados proporcionais.
A6: P03 Cultura Viva nas Vilas | B6: Oficinas de formação artística em cultura urbana – música e musicalidade, grafite e audiovisual (8 oficinas x 24h, 200 participantes) Secundários: – 4 mostras territoriais gratuitas (painéis de grafite, exibição de curtas e apresentação dos trabalhos musicais) (Artes Visuais / Exposição Cultural / Artística) | C6: Artes Visuais / Empreend Ações Educ-Cult/Capacitação/Treinamento | D6: Art. 18 | E6: O produto principal são as oficinas (≈ R$ 113 mil nas etapas de projeto x ≈ R$ 19,5 mil das mostras). Como o SALIC exige uma única área para o produto, recomenda-se Artes Visuais > Empreend Ações Educ-Cult/Capacitação/Treinamento (Art. 18): o grafite e o audiovisual (criação de imagem) são 5 das 8 oficinas, e o conjunto se encaixa no conceito de 'projeto de cultura urbana' do Anexo I (LVII – hip-hop/grafite). Alternativa igualmente Art. 18: Música > Empreend Ações Educ-Cult/Capacitação/Treinamento. Riscos de Art. 26: (1) NÃO cadastrar nada em Humanidades ('Ações Educ-Cult em Humanidades em geral' é Art. 26) nem chamar de 'projeto social/socioeducativo'; (2) as apresentações musicais das mostras não podem virar o produto de maior custo nem ser descritas como 'show de música popular cantada' (rap/funk com vocal é música popular cantada) – mantê-las como resultado pedagógico dentro da mostra, com custo baixo; (3) art. 18 da IN: por ter caráter social, só custos artístico-culturais – planilha não tem bolsas, transporte individual ou assistência; lanche limitado e vinculado às oficinas. Redação: 'ações educativo-culturais de iniciação artística em linguagens da cultura urbana (grafite, audiovisual e musicalidade), com exposição/mostra territorial dos trabalhos'. | F6: • Regularidade cadastral do IHV (CNPJ ativo, estatuto, ata, representante, CNAE cultural) e padronização do nome/sigla (IHV x IHGV). • Confirmar a função de Ado Viana no IHV e o histórico do IHV no Pronac (dispensa de portfólio e art. 15) – risco de questionamento de carteira/fracionamento com P05 e P16. • Plano de execução com carga horária e conteúdo programático das 8 oficinas e ficha técnica nominal (curadoria + ≥6 oficineiros). • Cartas de anuência dos 4 espaços (incluindo solução para 12–14 anos no Eldorado) e autorizações para painéis de grafite. • Adotar a planilha (teto R$ 200 mil) e o plano concreto de acessibilidade. | G6: • Cadastrar Artes Visuais > Empreend Ações Educ-Cult/Capacitação/Treinamento (Art. 18) como produto principal e as mostras como Exposição Cultural/Artística. • Não ultrapassar R$ 200.000 de valor total enquanto o IHV não tiver portfólio. • Se Ado Viana for dirigente do IHV, avaliar indicar outro representante legal ou declarar a relação e justificar objetos distintos de P05/P16. • Declarar art. 42, VI (ação para adolescentes/jovens e educadores) e publicar o vídeo-síntese com legendas (e, se possível, Libras/AD). • Mapear Pontos de Cultura certificados nos 4 territórios e obter cartas; caso não haja, explicitar que 'Cultura Viva' é apenas o nome. • Incluir medidas ambientais (descarte de latas de spray, tintas base água). | H6: R$ 40.000: Atender 2 territórios com 1 oficina cada (ex.: grafite na Vila Marçola e audiovisual na Cabana) = 50 participantes, 24h cada; 2 mostras simplificadas no próprio espaço; coordenação geral acumulando produção e curadoria; sem artista convidado; materiais apenas das 2 linguagens; Libras e apoio PcD nas 2 mostras; divulgação digital e cartazes. Custos vinculados proporcionais.
A7: P04 Cena Mineira em Movimento | B7: Circulação de 4 espetáculos mineiros de teatro/dança – 24 apresentações gratuitas em 12 municípios Secundários: – 24 oficinas gratuitas de artes cênicas conduzidas pelas companhias (3h, 30–40 vagas) (Artes Cênicas / Empreend Ações Educ-Cult/Capacitação/Treinamento) | C7: Artes Cênicas / Apresentação ou Performance de Teatro | D7: Art. 18 | E7: Produto principal = apresentações (≈ R$ 594 mil nas etapas de projeto x ≈ R$ 25 mil das oficinas) → Artes Cênicas, Art. 18. O SALIC não tem segmento genérico 'Espetáculo de Artes Cênicas' (termo do documento): escolher 'Apresentação ou Performance de Teatro' (ou 'de Dança', conforme a maioria dos títulos selecionados); circo ('Performance de Circo, Clown e Ilusionismo') também é Art. 18. Riscos: (1) não selecionar show musical/música popular cantada como um dos 4 títulos; (2) evitar as palavras 'mostra/festival': se a CNIC classificar como Festival, vale o produto secundário de maior valor (art. 46 §ú) – aqui as oficinas, também Art. 18, mas o enquadramento fica dependente de outra rubrica; (3) teto de R$ 1,5 mi PJ não é atingido, então não é preciso itinerância em 2 regiões (art. 12, II). Redação sugerida: 'Circulação de quatro espetáculos de teatro e dança por 12 municípios de Minas Gerais, com 24 apresentações gratuitas e oficinas de formação'. | F7: • Dados jurídicos da Mobox (razão social, CNPJ, CNAE, representante) e portfólio. • Fechar 24 apresentações/24 oficinas e a matriz espetáculo x município (ou outro número), refletindo metas e planilha. • Pré-selecionar (por convite) os 4 espetáculos ou parte deles com sinopse, ficha técnica, currículos e autorização do autor do texto – sem isso o Anexo II 3.3 fica descoberto. • Anuências das 12 prefeituras/equipamentos com ficha técnica e lotação. • Plano de acessibilidade concreto e segmento exato do produto principal no SALIC. | G7: • Cadastrar produto principal 'Apresentação ou Performance de Teatro' (ou Dança) – Art. 18 – e oficinas como 'Empreend Ações Educ-Cult/Capacitação/Treinamento'. • Adotar o modelo de 2 sessões por cidade no mesmo dia (matinê escolar + noturna): dobra o público sem dobrar logística e cabe nos R$ 900 mil. • Ampliar as oficinas para 3h (duas horas é pouco para 30–40 participantes) e conduzi-las em dupla. • Limitar companhias a ~7 integrantes em viagem e cachê de referência por sessão (premissa R$ 6.000) na chamada pública. • Publicar 6 espetáculos registrados com Libras e AD (art. 42, III) e reservar matinês para escolas públicas (art. 42, VI). • Usar municípios-reserva apenas como substitutos, sem alterar o número de 12. | H7: R$ 180.000: Somente o Eixo Histórico (Ouro Preto, Mariana, Congonhas, Cons. Lafaiete – menor distância de BH): 2 espetáculos x 4 apresentações = 8 sessões (2 por cidade) e 4 oficinas; seleção por convite (sem chamada pública/pareceristas); equipe central de 3 pessoas; coordenação e produção acumuladas por 5 meses; registro fotográfico + 2 sessões filmadas; Libras em todas as sessões e AD em 1 por cidade; divulgação regional digital. Custos vinculados proporcionais.
A8: P05 Sons do Congado | B8: Álbum Sons do Congado como registro sonoro de salvaguarda: gravação de campo com 4 guardas (12 faixas), repertório e limites de registro definidos pelos mestres, devolução às comunidades e difusão gratuita. Secundários: – 6 oficinas/encontros de transmissão de saberes conduzidos por mestres para jovens das irmandades (Patrimônio Cultural / Salvaguarda do patrimônio cultural imaterial (alternativa: Ações de Educação Patrimonial)) – Apresentação final gratuita de devolutiva com 4 guardas (Música / Apresentação/Gravação de Música Regional) – Minidocumentário (~15 min) e acervo digital autorizado (Audiovisual / Prod. AV curta/média metragem/TV Educativa-Cultural) | C8: Patrimônio Cultural / Salvaguarda do patrimônio cultural imaterial | D8: Art. 18 | E8: Caminho recomendado para garantir o Art. 18: cadastrar o produto principal na área Patrimônio Cultural, segmento 'Salvaguarda do patrimônio cultural imaterial' (Anexo IV = Art. 18). A definição do Anexo I, LXIX (identificação, documentação, transmissão, promoção e valorização) descreve exatamente o objeto. O álbum precisa ser a ação de maior custo (art. 46 e Anexo I, LI): na planilha proposta ele soma R$ 115.243, contra R$ 36.720 da apresentação final, o maior secundário. Alternativa igualmente Art. 18: área Música, segmento 'Apresentação/Gravação de Música Regional'. Nesse caso a documentação é mais simples (currículos), mas o parecer musical pode ler os cantos como música popular cantada (Art. 26). Para evitar isso, a redação deve chamar o repertório de 'cantos tradicionais das guardas de Congado/Reinado', e nunca de 'canções' ou 'show'. No caminho Patrimônio, a análise é do Iphan e o Anexo II, item 8, exige: identificação do bem; registro/acautelamento OU relatório de reconhecido valor cultural (8.1.2.1); declaração de anuência da comunidade detentora de cada guarda (8.1.3); relatório do bem; justificativa de relevância; ficha técnica com experiência junto às comunidades (8.1.6); aderência à Portaria Iphan 299/2015 e benefícios diretos aos detentores (8.8.1-8.8.2); metodologia de pesquisa/documentação (8.8.3). Riscos: (i) vedação a proselitismo/culto religioso (art. 32, VI). O texto deve tratar o Congado como expressão cultural e forma de expressão, manter a regra de não registrar ritos reservados e não financiar celebração religiosa em si; (ii) a exceção de limites para patrimônio (art. 14 e p.u., IN 34/2026) só alcança os limites de pessoa jurídica (art. 10, III e art. 11, II). Para Ado Viana (PF) continuam valendo 2 projetos e R$ 500 mil de carteira; (iii) o art. 18 da IN (restrição de custos) não se aplica, porque o projeto é cultural e de patrimônio imaterial. Os resultados de documentação serão incorporados às bases do MinC/Iphan (art. 41, §9º), o que precisa constar do termo de consentimento. | F8: • Definir e cadastrar o proponente PF (CPF, endereço, portfólio de Ado Viana). Confirmar que a carteira P05 + P16 = R$ 500 mil não será ultrapassada. • Obter as declarações de anuência das guardas/comunidades detentoras e o relatório de reconhecido valor cultural (Anexo II, 8.1.2.1 e 8.1.3). Sem isso o Iphan não admite a proposta. • Fechar a lista nominal de guardas, mestres e municípios e as especificações técnicas (12 faixas, 6 oficinas de 4h, minidoc de 15 min, apresentação). • Ficha técnica com currículos, em especial do articulador comunitário/coordenador com experiência comprovada junto às comunidades (8.1.6) e da direção musical. • Converter as diretrizes em planilha, plano de distribuição e plano de acessibilidade orçados (base: planilha deste parecer). | G8: • No SALIC: área Patrimônio Cultural, segmento 'Salvaguarda do patrimônio cultural imaterial', produto principal 'Álbum Sons do Congado – registro sonoro de salvaguarda'. Plano B: Música/'Apresentação/Gravação de Música Regional'. • Redigir o objeto como salvaguarda (identificação, documentação, transmissão, valorização – Anexo I, LXIX), citando a Portaria Iphan 299/2015 e os benefícios diretos aos detentores (cachês, cópias, acervo). • Gravar preferencialmente no território de cada guarda (unidade móvel). Isso reduz a logística de grupos de 15-20 integrantes e respeita o contexto ritual. • Adotar protocolo de consentimento por guarda, com a lista de conteúdos restritos, e informar no termo a incorporação dos resultados às bases MinC/Iphan (art. 41, §9º). • Baixar a idade mínima das oficinas para 12 anos (com autorização dos responsáveis), coerente com a transmissão intergeracional. • Diferenciar o objeto de P02 Mestres e Aprendizes no texto e não repetir mestres/guardas entre os projetos, para afastar o fracionamento. • Declarar as medidas de ampliação de acesso (art. 42, III, V e VI) e registrar a inexistência de venda (sem art. 44). • Separar por linha as despesas incentivadas pela Rouanet e pela LEIC-MG (fonte complementar) para evitar duplicidade. | H8: R$ 60.000: Versão de R$ 60 mil: álbum com 2 guardas (6 faixas) gravado em campo (2 diárias); 2 oficinas com mestres; devolutiva comunitária na sede de uma guarda, sem som/luz locados e sem transporte por ônibus; minidocumentário substituído por registro fotográfico + 1 vídeo curto com legendas e Libras; CDs só para as guardas (100 un.); coordenação de 3 meses. Mantêm-se anuências, consultor/Libras mínimos, contador e captação de 10%. O objeto (registro de salvaguarda + transmissão) continua viável.
A9: P06 Mural Minas | B9: 6 murais de arte urbana (~180 m² no total) criados com as turmas e artistas-educadores, em exposição pública permanente e gratuita em BH, Contagem e Santa Luzia. Secundários: – Percurso formativo em artes urbanas: 3 turmas, 75 vagas, 48 encontros, visitas mediadas e certificação (Artes Visuais / Empreend Ações Educ-Cult/Capacitação/Treinamento) – Cerimônia de encerramento, registro fotográfico/audiovisual e minidocumentário (Artes Visuais / Exposição Cultural / Artística (atividade vinculada)) | C9: Artes Visuais / Exposição Cultural / Artística | D9: Art. 18 | E9: Os dois caminhos naturais são Art. 18: Artes Visuais, 'Exposição Cultural/Artística' (murais) e Artes Visuais, 'Empreend Ações Educ-Cult/Capacitação/Treinamento' (formação). O produto principal será o que tiver maior custo. Na planilha proposta os murais somam R$ 334.910 e a formação R$ 149.850. Riscos de cair no Art. 26 ou de sofrer glosa: (i) cadastrar a formação em Humanidades ('Ações Educ-Cult em Humanidades em geral' = Art. 26). Tudo deve ficar em Artes Visuais; (ii) redigir como projeto social de juventude. Pelo art. 18 da IN, só custos artístico-culturais seriam aprovados, e itens como lanche e auxílio-transporte precisam ser justificados como condição de acesso à atividade cultural; (iii) o termo 'pixo': pichação é crime ambiental (Lei 9.605/98, art. 65), e só o grafite autorizado é lícito (§2º). 'Pixo' deve aparecer apenas como objeto de estudo histórico-estético, com declaração expressa de que nenhuma intervenção ocorrerá sem autorização do responsável pela superfície. Exigências do Anexo II para exposição de artes visuais: projeto expográfico (4.3), que para murais pode ser adaptado como ficha técnica de cada superfície com fotos, medidas, croqui, preparação e plano de trabalho em altura; currículos e anuência de curadores/artistas (4.1, 4.4); relação de obras (4.5). Para as oficinas: beneficiários e forma de seleção (7.1) e plano de execução com carga horária e conteúdo programático (7.3). Proponente: Morsa é PJ (até R$ 1,5 mi por projeto; carteira de R$ 15 mi), então os R$ 750 mil cabem. O ponto crítico é o CNAE: o art. 4º, §3º exige CNAE cultural correspondente à área/segmento nos registros do CNPJ, e o CNAE principal informado é de edição de jornais. É preciso ter um CNAE secundário compatível (ex.: 9002-7/01 atividades de artistas plásticos; 8592-9/99 ensino de arte e cultura) antes do cadastro. Art. 15: Túlio Gama aparece nos documentos do Bloco Nerd como representante da Morsa. Se for sócio/dirigente, os projetos de Túlio como PF (P07 e eventualmente P12) e os da Morsa formam uma só carteira, com o limite da PJ. | F9: • CNAE da Morsa: incluir CNAE secundário cultural compatível com Artes Visuais/ensino de arte (o principal é edição de jornais), senão o SALIC inadmite. • Reescrever o documento (hoje no modelo LEIC) para o SALIC: área Artes Visuais, segmento Exposição Cultural/Artística, Art. 18; retirar a prática de 'pixo' do objeto. • Definir as 6 superfícies com anuência/termo de cessão e corrigir a área (180 m² x 80 m²). Decidir 6 ou 9 murais. • Equipe com currículos e plano pedagógico com carga horária e conteúdo programático (Anexo II, 4.1 e 7.3). • Justificar a economicidade do valor de R$ 750 mil frente ao escopo, ou ampliar o escopo. Esclarecer o vínculo de Túlio Gama com a Morsa (art. 15). | G9: • Cadastrar dois produtos em Artes Visuais: murais (principal, maior custo) e formação (secundário). Nunca usar Humanidades. • Substituir 'grafite, pixo e muralismo' por 'grafite e muralismo, com estudo histórico-crítico das escritas urbanas', declarando que as intervenções só ocorrem em superfícies autorizadas. • Apresentar uma 'ficha expográfica' por mural (foto, medidas, croqui, preparação, acesso, ART) para cumprir o Anexo II, 4.3. • Fixar a carga horária (sugestão: 16 encontros de 4h = 64h por turma) e a certificação com 75% de frequência. • Garantir que menores não operem em altura; prever seguro e autorizações dos responsáveis. • Dar mais peso artístico ao valor de R$ 750 mil (ex.: 9 murais ou ~300 m²) para reduzir o risco de corte por economicidade. A planilha atual segue o escopo documentado (6 murais/180 m²). • Tornar a acessibilidade fixa: AD + QR Code + placa em braille por mural e Libras nas visitas e no encerramento. | H9: R$ 150.000: Versão de R$ 150 mil: um único município (BH), 1 turma de 25 vagas com 16 encontros e 2 murais (~60 m²); coordenação geral acumulando a artística (5 meses), 1 artista-educador e 1 produtor; sem van, mapa digital e minidocumentário (só fotos e 1 vídeo curto acessível); cerimônia simples no próprio espaço. Mantêm-se AD/placas dos 2 murais, Libras sob demanda, seguro, contador e captação de 10%.
A10: P07 Concertos nas Praças do Interior (documentos: 'Concertos na Praça') | B10: Circuito de 8 concertos gratuitos de música instrumental/de concerto com formação de câmara (8 músicos + regente) e aberturas regionais instrumentais/corais. Secundários: – 8 ensaios abertos com mobilização de escolas públicas e bandas (Música / Empreend Ações Educ-Cult/Capacitação/Treinamento) – Registro audiovisual, cortes e aftermovie acessível (Audiovisual / Difusão de acervo e conteúdo AV em diversos meios/suportes) | C10: Música / Apresentação/Gravação de Música Instrumental (alternativa: Apresentação/Gravação de Música Erudita) | D10: Art. 18 | E10: O Art. 18 está bem encaminhado: Música, 'Apresentação/Gravação de Música Instrumental' (ou 'Erudita'), com os concertos como ação de maior custo (R$ 336.720 na planilha proposta). Risco de Art. 26: o conceito admite 'repertório popular em arranjos instrumentais ou orquestrais', o que é aceitável enquanto for instrumental. Se a formação ou as aberturas incluírem cantores de música popular como atração, o parecer pode reclassificar para 'Música Popular Cantada'. Corais se enquadram em 'Canto Coral' (Art. 18). As aberturas devem ser bandas de música, grupos instrumentais e corais, e a programação deve ser chamada de 'concertos', nunca 'shows'. Não usar a palavra 'festival' nem cadastrar o produto como Festival, para não ativar o art. 46, p.u. Proponente: a planilha e os DOIS documentos do projeto indicam Túlio Gama (PF). Só a pasta do Drive está nomeada 'PRO SP'. Ao mesmo tempo, a pasta de P08 está nomeada 'Tulio Gama', mas seus documentos são da ProSP. A conclusão mais provável é que as pastas foram trocadas, e P07 deve ser tratado como projeto de Túlio Gama (PF). Consequências para a carteira: PF tem teto de R$ 500 mil por projeto e R$ 500 mil de carteira (arts. 10, I e 11, I). P07 (R$ 500 mil) consome toda a carteira, então P12 Bloco Nerd (R$ 250 mil) deve ir para a LEIC, o que é coerente com a planilha ('só 1 dos 2 projetos do Túlio vai à Rouanet'). P08 não pode ser de Túlio. Ressalva do art. 15: os documentos de P12 apontam Túlio como representante da Morsa Produções Ltda. (proponente de P06). Se for sócio/dirigente, as carteiras se unificam com o limite da PJ, mas o teto por projeto de PF (R$ 500 mil) continua valendo para P07. | F10: • Confirmar Túlio Gama (PF) como proponente, corrigir a pasta 'PRO SP' e conferir a carteira: com P07 a R$ 500 mil, P12 vai para a LEIC e P08 fica com a ProSP. • Definir formação principal (nº de músicos), regente/diretor artístico e grupos regionais, com currículos (Anexo II, 5.1). • Escolher os municípios/praças e obter anuências municipais com a lista do que cada prefeitura cede (energia, segurança, banheiros, gradil). Sem isso, 8 concertos não cabem em R$ 500 mil. • Fechar a planilha com cotações (palco, som, ônibus, hospedagem) e a simulação do ECAD; dividir a estrutura entre fornecedores para respeitar o limite de 20%. • Portfólio e documentos de Túlio Gama; esclarecer o vínculo com a Morsa (art. 15). | G10: • Cadastrar como Música, 'Apresentação/Gravação de Música Instrumental' (ou Erudita, se o repertório for predominantemente de concerto), com produto 'Concertos'. • Agrupar os concertos em 4 finais de semana com 2 municípios vizinhos cada (ex.: Ouro Preto/Mariana; Congonhas/Lafaiete; Divinópolis/Itaúna; Curvelo/Diamantina) para reduzir logística. • Formalizar contrapartidas municipais e a parceria Armind como 'outras fontes', sem sobreposição com itens incentivados. • Usar repertório em domínio público/arranjos próprios para reduzir ECAD e partituras. • Corrigir o título (planilha 'Concertos nas Praças do Interior' x documentos 'Concertos na Praça') antes do cadastro. • Incluir medidas ambientais simples e as marcas do Pronac no plano de divulgação. | H10: R$ 100.000: Versão de R$ 100 mil: 2 concertos em 2 municípios vizinhos num único fim de semana (ex.: Ouro Preto e Mariana) com quinteto + regente, 2 ensaios abertos e 2 aberturas locais; palco/som/luz de pequeno porte só nesses 2 dias; registro fotográfico + 1 vídeo curto com legendas/Libras no lugar do aftermovie; coordenação de 3 meses. Mantêm-se Libras, rampa, ECAD, contador e captação de 10%.
A11: P08 Sabores de Minas – Circuito de Cultura Alimentar, Memória e Patrimônio de Minas Gerais | B11: Encontros de transmissão de saberes da cultura alimentar tradicional mineira com mestres e detentores (cozinhas de mestres, oficinas, 'Cozinha de Memórias' com escolas e rodas de conversa) em 4 etapas municipais, como ação de salvaguarda. Secundários: – Caderno Sabores de Minas – publicação de receitas, modos de fazer e memórias (digital acessível + 500 exemplares) (Humanidades / Livro/Obra Refer impres/eletrôni valor Art/Lit/Hum) – Registro audiovisual (4 episódios curtos) e acervo documental (Patrimônio Cultural / Salvaguarda do patrimônio cultural imaterial (documentação)) – Espaço de exposição de produtos tradicionais dos detentores (feira, sem taxa) (Patrimônio Cultural / Salvaguarda do patrimônio cultural imaterial (atividade vinculada; não usar 'Gastronomia de valor cultural')) | C11: Patrimônio Cultural / Salvaguarda do patrimônio cultural imaterial | D11: Risco | E11: Como está redigido ('festival gastronômico-cultural', 'feira gastronômica', 'circuitos gastronômicos'), o projeto cai em Humanidades, 'Gastronomia de valor cultural', que é Art. 26 no Anexo IV. Além disso, o art. 18 da IN determina que, em projetos gastronômicos que NÃO se caracterizem como manifestação de tradição, memória ou patrimônio imaterial, só se aprovam custos artístico-culturais. Isso glosaria estrutura de feira, ingredientes, cozinhas e logística. Caminho para o Art. 18: Patrimônio Cultural, 'Salvaguarda do patrimônio cultural imaterial' (Anexo I, LXIX: identificação, documentação, transmissão, promoção e valorização). O objeto deve ser redefinido como salvaguarda e transmissão dos SABERES E MODOS DE FAZER tradicionais da cozinha mineira (quitandas, doces de tacho, queijo artesanal, cozinhas quilombolas e de festas populares), com os mestres/detentores como protagonistas. O consumo e a gastronomia comercial ficam fora. Ancoragem: indicar bens registrados quando houver (ex.: Modo Artesanal de Fazer Queijo de Minas, registrado pelo Iphan, e registros do IEPHA/municipais a verificar). Para os demais saberes, apresentar relatório de reconhecido valor cultural/referência cultural das comunidades (Anexo II, 8.1.2.1). Também são exigidos: anuência dos detentores (8.1.3), relatório do bem (8.1.4), justificativa (8.1.5), ficha técnica com experiência junto às comunidades (8.1.6) e aderência à Portaria Iphan 299/2015 com benefícios diretos aos detentores (8.8). Estrutura: (i) não cadastrar como 'Festival' (art. 46, p.u.); (ii) o produto principal de maior custo deve ser a salvaguarda: na planilha proposta soma R$ 346.877, contra R$ 20.000 da feira; (iii) a feira fica como espaço de exposição dos detentores, sem taxa e sem compra de alimentos para venda ou degustação com recurso incentivado; ingredientes só como insumo pedagógico das oficinas; (iv) a publicação pode ser secundária em Humanidades/Livro (Art. 18). Alternativa Art. 18: Patrimônio, 'Ações de Educação Patrimonial', se o eixo escolar ('Cozinha de Memórias') for o principal, com aderência à Portaria Iphan 137/2016. Risco residual: CNIC/Iphan podem reclassificar como Gastronomia (Art. 26); cabe um único recurso em 10 dias (art. 45, §3º). Proponente: planilha e documentos indicam ProSP (PJ); só a pasta do Drive diz 'Túlio Gama' (provável troca com P07). Se fosse Túlio (PF), o valor teria de cair ao teto de R$ 500 mil (art. 11, I) e ainda assim não caberia, porque P07 já consome toda a carteira PF de Túlio. Por isso a planilha usa R$ 600 mil com ProSP como PJ. | F11: • Reestruturar o objeto de 'festival gastronômico' para salvaguarda de saberes e modos de fazer tradicionais (Patrimônio/Salvaguarda, Art. 18). Do contrário, o enquadramento é Art. 26 e há glosa de custos (IN, art. 18). • Confirmar o proponente ProSP (CNPJ, CNAE compatível, representante) e corrigir a pasta 'Túlio Gama'. Como PF de Túlio, o projeto é inviável (teto R$ 500 mil e carteira já usada por P07). • Reunir o Anexo II, item 8: identificação dos saberes/bens, registro ou relatório de reconhecido valor, anuências dos detentores/comunidades e ficha técnica com experiência junto às comunidades. • Regulamentar a feira sem taxa e sem receita para o projeto, ou declarar a receita e aplicar o art. 44. • Fechar a grade por etapa (decidir 1 ou 2 fins de semana; a planilha cobre 1), o 4º município, os espaços e as metas. | G11: • Novo objeto sugerido: 'Salvaguarda e transmissão dos saberes e modos de fazer da cultura alimentar tradicional mineira, por meio de encontros com mestres e detentores em 4 municípios, documentação e publicação'. • Retirar do texto as expressões 'festival gastronômico', 'expedição gastronômica', 'empreendedores da gastronomia' e 'oportunidades de comercialização' como objetivo; manter a comercialização só como efeito indireto e privado. • Ancorar em bens registrados (Modo Artesanal de Fazer Queijo de Minas – Iphan; registros IEPHA/municipais a conferir) e em relatórios de referência cultural para os demais saberes. • Usar a Portaria Iphan 299/2015 na justificativa e demonstrar benefícios diretos aos detentores: cachês, créditos, exemplares e acervo devolvido. • Manter o produto principal (salvaguarda) com o maior custo e a feira enxuta. Tendas de expositores podem vir de contrapartida municipal. • Se o foco escolar crescer, considerar 'Ações de Educação Patrimonial' (Art. 18), com aderência à Portaria Iphan 137/2016. • Verificar se a ProSP atende ao requisito de domicílio em MG exigido pela LEIC para a fonte complementar estadual. | H11: R$ 120.000: Versão de R$ 120 mil: 2 etapas em municípios contíguos (Ouro Preto e Mariana), 1 fim de semana cada (sáb-dom), com 8 atividades de mestres e 2 rodas; sem tendas de feira (expositores com estrutura própria ou cessão municipal); Caderno só em versão digital acessível; registro fotográfico + 1 vídeo curto acessível; coordenação e curadoria de 4 meses. Mantêm-se pesquisa/relatório de referência cultural, anuências, Libras, contador e captação de 10%.
A12: P09 Auto de Natal Mineiro | B12: Espetáculo teatral-musical Auto de Natal Mineiro – criação e circulação (10 apresentações gratuitas) Secundários: – Registro audiovisual integral acessível (Libras, AD, legendas) e clipes (Audiovisual / Difusão de acervo e conteúdo AV em diversos meios/suportes (Art. 18) – ou manter como ação do produto principal) | C12: Artes Cênicas / Teatro Musical (c/ dramaturgia, danças e canções) – alternativa equivalente: Apresentação ou Performance de Teatro | D12: Art. 18 | E12: O produto principal é o espetáculo. Na planilha proposta ele responde por cerca de 97% do valor do projeto (criação, elenco, núcleo musical, grupos locais, estrutura e circulação), e o registro audiovisual é o único secundário, de valor pequeno. Por isso o Art. 18 está garantido desde que o cadastro use Artes Cênicas. Recomendo o segmento 'Teatro Musical (c/ dramaturgia, danças e canções)', porque há dramaturgia original e números musicais ao vivo. 'Apresentação ou Performance de Teatro' também é Art. 18, e a escolha só precisa ser coerente com o texto. Não cadastrar em Música: 'canções natalinas' com corais e bandas poderiam ser lidas como Música Popular Cantada (Art. 26). Se a parte musical precisar de destaque, use 'Canto Coral' (Art. 18), nunca 'Popular Cantada'. Cuidados de redação: (1) manter e reforçar o parágrafo que afasta culto e proselitismo (IN art. 32, VI), tratando a obra como 'auto' da tradição popular, de fruição laica e aberta; (2) não apresentar a feira de artesanato e gastronomia como produto nem pôr custo dela na planilha (risco de glosa pela IN art. 18 e de leitura como Gastronomia, que é Art. 26); (3) não incluir a 'oficina de presépios' (pendência 16) como produto. Se for incluída, deve ser atividade paralela gratuita de ampliação de acesso (art. 42, V) e de baixo custo, para não diluir o produto principal; (4) a participação de corais e bandas é 'integração musical ao espetáculo', não 'shows'. | F12: • Resolver a sobreposição com o P10 (mesmo proponente Arminde e mesmo objeto 'Auto de Natal' em nov–dez/2027) antes de submeter. Sem isso há risco de indeferimento por fracionamento ou duplicidade e de custos de criação contados duas vezes. • Natureza jurídica e dossiê da Arminde (PF, MEI ou PJ; CNPJ e CNAE; portfólio obrigatório por ser > R$ 200 mil). Se for PF, o projeto tem de baixar para ≤ R$ 500 mil. • Ficha técnica com currículos, autor do texto com contrato ou anuência (Anexo II 3.1 e 3.3) e sinopse. • Fechar os 8 municípios e as praças com manifestação das prefeituras, mais o calendário real. • Plano de acessibilidade com AD presencial e medidas arquitetônicas por praça, alinhado ao Guia MDHC. | G12: • Cadastrar Artes Cênicas / Teatro Musical (ou Apresentação/Performance de Teatro) e pedir expressamente o Art. 18. Não usar a área Música. • Sobre o P10, escolher uma de três saídas: (a) fundir P09 e P10 num único projeto da Arminde de até R$ 1,2 mi (cabe no limite de PJ), com 15 apresentações (BH, RMBH e cidades históricas); (b) manter o P09 na Rouanet e levar o P10 só à LEIC-MG, em linha com o Banco Cemig, que exige LEIC; (c) se os dois forem à Rouanet, reposicionar o P10 em outro segmento (ex.: Música/Canto Coral – cantatas nas cidades históricas), com equipe e orçamento próprios e sem custos de criação do Auto. Nesse caso, declarar a relação entre os projetos nos dois cadastros. • Incluir na justificativa a aderência ao art. 1º e ao art. 3º da Lei 8.313 e dados socioculturais dos municípios. • A planilha só fecha em R$ 700 mil com estrutura de pequeno porte, gerador em 5 das 10 praças e elenco de 6 atores contratados como MEI. Confirmar essas premissas na vistoria ou reduzir para 8 apresentações. • Eliminar a oficina de presépios ou mantê-la como atividade paralela gratuita de custo baixo. Não colocar feiras na planilha. • Padronizar o nome do proponente (Armind ou Arminde) na planilha do cliente, na pasta e no SALIC. | H12: R$ 140.000: Mantém o objeto (criação + circulação gratuita) em formato enxuto: 3 apresentações (BH centro, Barreiro e 1 município) em equipamentos culturais públicos com palco, som e luz próprios, o que elimina palco, gerador e banheiros químicos. Elenco de 4 atores + 2 músicos, com 1 mês de ensaio. Cenografia simplificada (~R$ 8 mil). Grupos locais só em 3 praças. Sem vídeo integral: no lugar dele, Libras e AD presenciais nas 3 sessões e ensaio aberto (art. 42, V) como ampliação de acesso. Divulgação só digital. Custos vinculados proporcionais (adm ~8%, acessibilidade/divulgação ~16%, captação 10%).
A13: P10 Natal nas Cidades Mineiras | B13: Espetáculo Auto de Natal – 5 apresentações gratuitas em praças (criação/adaptação e circulação) Secundários: – Apresentações de canto coral/cantata natalina (5) (Música / Apresentação/Gravação de Canto Coral (Art. 18)) – Ambientação cênica temporária de iluminação LED (5) (Artes Cênicas / Apresentação ou Performance de Teatro – como ação vinculada ao espetáculo, não como produto autônomo de Artes Visuais) – Registro audiovisual – vídeo-síntese acessível (Audiovisual / Difusão de acervo e conteúdo AV em diversos meios/suportes (Art. 18)) | C13: Artes Cênicas / Apresentação ou Performance de Teatro | D13: Art. 18 | E13: O escopo SALIC acerta ao tratar o Auto de Natal como produto principal em Artes Cênicas / Apresentação ou Performance de Teatro (Art. 18) e ao evitar o cadastro como 'Festival/Festa/Feira'. Isso é importante: nesse cadastro valeria o secundário de maior valor (art. 46, parágrafo único), e a feira ou a estrutura poderiam definir o enquadramento. Na planilha proposta o Auto responde por cerca de 89% do valor do projeto e o coral (Canto Coral, também Art. 18) por cerca de 6%. RISCOS: (1) A feira de economia criativa com gastronomia não deve ser produto nem ter rubricas incentivadas. Há risco de glosa pela IN art. 18 (custos gastronômicos e comerciais) e de leitura como 'Gastronomia de valor cultural' (Art. 26). A estimativa preliminar de R$ 45 mil para 'tendas, feira e cenografia complementar' foi retirada da planilha, e a feira passa a ser ação associada com tendas dos expositores ou do município. Se o cliente quiser manter a feira no projeto, restringir a artesanato tradicional e enquadrar como Patrimônio/Artesanato tradicional (Art. 18), com valor inferior ao do Auto. (2) A iluminação de praças e fachadas deve ser descrita como luz cênica vinculada à apresentação, como o escopo já faz; decoração urbana é vedada como objeto (art. 33, V). (3) Os corais devem cantar repertório coral natalino (Canto Coral), não 'show' de música popular. (4) O tema natalino exige o mesmo cuidado do P09 quanto a proselitismo (art. 32, VI). PROBLEMA MAIOR: o enquadramento está correto, mas o projeto é quase o mesmo objeto do P09 (Auto de Natal Mineiro), com o mesmo proponente. Ver conformidade e recomendações. | F13: • Resolver a duplicidade com o P09: mesmo proponente (Arminde) e mesmo objeto (Auto de Natal gratuito em praças de MG em nov–dez/2027). Do jeito que está, o projeto não deve ser submetido à Rouanet em paralelo ao P09. • Definir o titular (Arminde PJ ou Gustavo Ribeiro PF) e reunir CNPJ, CNAE, contrato social e portfólio. A planilha e os documentos divergem. • Anuências das 5 prefeituras e autorizações de patrimônio nas cidades históricas, com praças definidas. • Ficha técnica e sinopse do Auto, com anuência do autor. • Firmar ao menos uma medida de ampliação de acesso (art. 42) e o público estimado por produto. | G13: • Opção preferencial: levar o P10 à LEIC-MG, para a qual já existe versão e que é coerente com o Banco Cemig, e deixar o P09 como projeto Rouanet. Assim se evita a sobreposição federal. O mecanismo 'R Art. 18 + E' não permite financiar as mesmas despesas duas vezes. • Alternativa: fundir P09 e P10 num único projeto Rouanet da Arminde (até R$ 1,2 mi, dentro do limite de PJ), com um só Auto e 15 apresentações (BH, RMBH e cidades históricas). Os custos de criação ficam uma vez só e a captação é única. • Se os dois forem mesmo à Rouanet, reposicionar o P10 como 'Cantatas de Natal nas Cidades Históricas', com produto principal em Música / Canto Coral (Art. 18). Território só nas cidades históricas (sem BH), sem Auto teatral, com equipe e cenografia próprias, e declaração de não sobreposição com o P09 nos dois cadastros. • Manter o cadastro como Artes Cênicas / Apresentação ou Performance de Teatro (não 'Festival/Festa/Feira'). Excluir a feira dos produtos e das rubricas incentivadas. • Corrigir a versão LEIC, que repete 'Enquadramento pretendido: Artigo 18... MinC'. • Rever a distribuição preliminar: os R$ 145 mil de estrutura do texto não cabem junto com os custos vinculados da Rouanet. A planilha proposta usa estrutura de pequeno porte (R$ 65 mil). | H13: R$ 100.000: 2 cidades sem pernoite (BH bairro + Sabará), Auto adaptado com 3 atores + 1 músico e cenografia mínima (~R$ 6 mil), 1 coral local por cidade, estrutura de pequeno porte só no dia, sem ambientação LED separada (a luz cênica cumpre esse papel), sem vídeo-síntese (só registro fotográfico), Libras e AD nas 2 sessões, e ação com escolas como ampliação de acesso. Sem feira. Custos vinculados proporcionais.
A14: P11 Festa Junina 2027 – Saberes e Tradições do Forró | B14: Festival/Festa: circuito Festa Junina – Saberes e Tradições do Forró (4 municípios, 8 dias). Pelo art. 46, parágrafo único, o enquadramento é dado pelo secundário de maior valor: as 16 apresentações das Matrizes Tradicionais do Forró Secundários: – 16 apresentações musicais das Matrizes Tradicionais do Forró (SECUNDÁRIO DE MAIOR VALOR: R$ 158,2 mil na planilha proposta) (Patrimônio Cultural / Salvaguarda do patrimônio cultural imaterial (Art. 18). Alternativa: Música / Apresentação de Música Regional (Art. 18). NUNCA Música Popular Cantada (Art. 26)) – 12 apresentações de quadrilhas juninas (mostra não competitiva) (Patrimônio Cultural / Salvaguarda do patrimônio cultural imaterial (Art. 18). Alternativa: Artes Cênicas / Apresentação ou Performance de Dança (Art. 18)) – 12 oficinas de saberes (ornamentação, dança de forró, culinária junina), 360 vagas (Patrimônio Cultural / Ações de Educação Patrimonial (Art. 18). Não usar 'Gastronomia de valor cultural' (Art. 26)) – Mapeamento cultural simplificado + 4 minidocumentários (Patrimônio Cultural / Salvaguarda do patrimônio cultural imaterial – pesquisa e documentação (Art. 18). Alternativa: Audiovisual / Difusão de acervo e conteúdo AV (Art. 18)) | C14: Patrimônio Cultural / Salvaguarda do patrimônio cultural imaterial (produto Festival, Bienal, Festa ou Feira) | D14: Art. 18 | E14: Por ser Festa, o art. 46, parágrafo único, manda enquadrar pelo PRODUTO SECUNDÁRIO DE MAIOR VALOR. Na planilha proposta ele são as 16 apresentações de forró (R$ 158,2 mil), seguidas das quadrilhas (R$ 74 mil), das oficinas (R$ 62 mil) e da documentação (R$ 45,2 mil). Todo o Art. 18 depende, portanto, do segmento em que as apresentações forem cadastradas. As alternativas: (A) RECOMENDADA – Patrimônio Cultural / Salvaguarda do PCI (Art. 18). É coerente com o objeto (bem registrado pelo Iphan em 2021, Plano de Salvaguarda de 2024, curadoria com detentores, remuneração e documentação) e ainda tira o projeto dos limites de valor e quantidade (art. 14, II e parágrafo único). Exige, porém, a instrução completa do Anexo II, item 8: registro do bem, relatório, anuência da comunidade detentora, aderência à Portaria Iphan 299/2015 e benefícios diretos aos detentores. Sem esses documentos o MinC pode reclassificar o produto. (B) Música / Apresentação de Música Regional (Art. 18). É defensável porque baião, xote, xaxado e arrasta-pé são gêneros regionais, mas trios de forró são majoritariamente cantados e o parecerista pode ler 'show de forró' como Música Popular Cantada (Art. 26). Nesse caso o projeto inteiro cairia no Art. 26. A previsão de 'sertanejo raiz' na programação complementar (§7.1) agrava esse risco e deve ser retirada. COMO REDIGIR: chamar as apresentações de 'Apresentações das Matrizes Tradicionais do Forró – bem registrado como Patrimônio Cultural do Brasil'; detalhar instrumentação tradicional (sanfona, zabumba, triângulo), repertório de domínio da tradição e presença de mestres; ligar cada apresentação à mediação patrimonial (mestre de cerimônias e painéis). Manter a culinária como oficina de transmissão de saberes (Educação Patrimonial), sem venda nem distribuição de alimentos, e deixar barracas e vendas fora da planilha. Pela IN art. 18, custos gastronômicos e comerciais só são aceitos em manifestações de tradição, e mesmo assim só os culturais. Manter a gestão geral (estrutura e equipe) no produto Festa, que não define o enquadramento, e garantir que nenhum secundário de segmento Art. 26 supere as apresentações. | F14: • Anuência da comunidade detentora das Matrizes Tradicionais do Forró (grupos e coletivos forrozeiros de MG), relatório do bem e comprovante do registro Iphan (Anexo II 8.1.1–8.1.5 e 8.8). Sem isso o enquadramento em Patrimônio não se sustenta. • Fixar no SALIC o segmento das apresentações (Salvaguarda do PCI, ou Música Regional) e retirar o 'sertanejo raiz', para que o secundário de maior valor garanta o Art. 18. • Confirmar municípios, espaços e datas com cartas das prefeituras, incluindo o apoio assumido na planilha: energia da rede, sanitários do local e policiamento. • Cadastro, CNAE e portfólio da Mobox. • Ficha técnica nominal (3 curadores com experiência junto aos detentores), proposta curatorial ou pré-grade e planos das 12 oficinas com carga horária. | G14: • Cadastrar o produto principal como Festival/Festa em Patrimônio Cultural / Salvaguarda do PCI e os secundários como na lista de produtos secundários (todos Art. 18). • Renomear as apresentações como 'Apresentações das Matrizes Tradicionais do Forró' e descrever a formação tradicional (sanfona, zabumba, triângulo) e a presença de mestres. • Trocar o MC por 'mediação cultural' e manter os painéis educativos. Isso reforça a natureza patrimonial dos shows. • Organização técnica para caber em R$ 800 mil: sábado com palco, som médio e luz (atração de referência + 2 trios) e domingo em arena no chão com som pequeno (3 quadrilhas + 1 trio). Sem essa solução e sem o apoio municipal, o escopo completo custaria cerca de R$ 900–950 mil; nesse caso, reduzir para 3 municípios. • Não cobrar taxa das barracas e não financiar barracas de venda. • Incluir no texto a aderência à Portaria Iphan 299/2015 (salvaguarda) e 137/2016 (educação patrimonial), e prever o envio do mapeamento ao MinC e ao Iphan (art. 41, §9º). • Registrar o vínculo do Hexagon e do Blip com 'Pixel' e do Minas Shopping com o Nerd Experience apenas como histórico de relacionamento, sem promessa de contrapartida comercial. | H14: R$ 160.000: 1 município (ex.: Sete Lagoas) com 1 fim de semana: 4 apresentações (1 referência + 3 trios), 3 quadrilhas e 3 oficinas (90 vagas), com 1 curador-detentor + pesquisador em regime parcial, mapeamento local e 1 minidocumentário. Estrutura de sábado e arena de domingo, Libras e AD, divulgação local. Mantém o enquadramento patrimonial: anuência dos detentores, secundário de maior valor nas apresentações e custos vinculados proporcionais.
... A24: P21 Caravana Cultura & Saúde | B24: Mostra itinerante de cinema brasileiro – 36 blocos de exibição gratuitos em 6 municípios Secundários: – 6 rodas de conversa mediadas (Audiovisual / Difusão de acervo e conteúdo AV (ação de formação de público vinculada)) – Catálogo digital acessível da mostra (Audiovisual / Difusão de acervo e conteúdo AV (não cadastrar como publicação de Humanidades)) | C24: Audiovisual / Difusão de acervo e conteúdo audiovisual em diversos meios e suportes | D24: Art. 18 | E24: Enquadramento Art. 18 correto e seguro: a exibição gratuita de obras brasileiras é "Difusão de acervo e conteúdo audiovisual", segmento do Anexo IV no Art. 18, e é de longe a ação de maior custo (~R$ 238 mil de R$ 334 mil). Respeitar art. 28 (direitos de exibição ≤ 20%: aqui 9,6%) e art. 31 IV (evento AV 1ª edição ≤ R$ 600 mil). O eixo "Saúde" é tema curatorial das rodas – deve permanecer assim: nenhuma despesa de saúde, nenhuma ação de testagem/vacinação/orientação clínica, convidados de saúde pagos como palestrantes de debate sobre o filme (≤ R$ 5 mil). Na redação, trocar "reflexão comunitária sobre assuntos de saúde" por "debate sobre temas sociais presentes nas obras (cuidado, convivência, envelhecimento, saúde coletiva)"; avaliar título com o cinema em primeiro plano (ex.: "Caravana de Cinema Brasileiro – Cultura & Saúde"), para não sugerir serviço de saúde itinerante. O ponto crítico não é o enquadramento, e sim o proponente: carteira de Rafael Tose (P19 + P21) e portfólio cultural. | F24: • Natureza jurídica do proponente e carteira: Rafael Tose aparece em P19 (kart, R$ 450 mil) e P21 (R$ 450 mil); como PF só cabe um projeto de R$ 450 mil (teto R$ 500 mil). Decidir qual vai à Rouanet ou usar PJ com CNAE audiovisual. • Portfólio cultural/audiovisual comprovável (obrigatório acima de R$ 200 mil); sem ele, trocar o proponente (ex.: produtora AV parceira) ou reduzir a ≤ R$ 200 mil se for 1º projeto. • Seleção dos 6 municípios e espaços (principais + alternativos cobertos) com anuência das prefeituras. • Lista indicativa de filmes com licenças, classificação e versões acessíveis (AD/LSE). • Ficha técnica nominal e confirmação de que não haverá serviços de saúde no projeto. | G24: • Se Rafael Tose for PF, priorizar P21 na Rouanet (Art. 18 seguro) e levar P19 (esporte, alto risco pela IN art. 18) para outro mecanismo/proponente. • Pedir às prefeituras contrapartidas formais (energia, banheiros, segurança, espaço coberto) para reduzir custos de estrutura. • Dividir estrutura técnica entre ≥ 2 fornecedores e cotar 3 orçamentos por item de maior valor. • Executar na estação seca e manter as 2 semanas de contingência. • Selecionar títulos com AD/LSE já existentes (obras com recursos públicos federais costumam tê-los). • Incluir P21 na aba Projetos da planilha do cliente com valor mínimo definido. | H24: R$ 90.000: Mínimo não consta da planilha do cliente; sugere-se R$ 90 mil (20%, padrão do portfólio): 2 municípios × 2 dias (12 blocos), 2 rodas de conversa, licenças de ~4 longas e 8 curtas, estrutura locada de um pacote compacto (tela inflável + som), sem gerador/hospedagem (municípios da RMBH com energia), equipe central reduzida (coordenação acumulando produção), Libras nas rodas e AD por receptores; catálogo digital simplificado.

Sheet Campos SALIC 2026
A1: Formulário de proposta no SALIC 2026 – campos e onde cada conteúdo entra
A2: Fonte: Manual do Proponente – apresentação de proposta e adequação (IN 2026), SEFIC/MinC, fev/2026: https://www.gov.br/cultura/pt-br/centrais-de-conteudo/marcas-e-logotipos/marcas-rouanet/ManualdoProponenteIN2026DEFINITIVO2.pdf
A4: Seção do SALIC | B4: Campo | C4: O que o manual pede | D4: Código na revisão
A5: Identificação | B5: Nome da proposta | C5: Curto; em data comemorativa citar evento e ano (ex.: 'Festa Junina 2027'). Sem 'título provisório'. | D5: A1
A6: Identificação | B6: Tipicidade / Tipologia | C6: Define produtos e teto (Normal R$1,5 mi; Arte Urbana; Cultura Afro-brasileira; Povos e Comunidades Tradicionais; Específicos R$6 mi; Especiais: festa/festival R$15 mi; Patrimônio sem teto). | D6: A1
A7: Identificação | B7: Data fixa (Sim/Não) | C7: Sim para Natal, Festa Junina, Carnaval – proposta com data fixa NÃO pode ser prorrogada. | D7: A2
A8: Identificação | B8: Agência do Banco do Brasil | C8: 5 dígitos; conferir se a agência existe. | D8: —
A9: Identificação | B9: Plano de execução imediata | C9: Normal (captar 10%), edital homologado, ou contrato de patrocínio ≥20% sem condicionantes (vai direto à adequação). | D9: —
A10: Identificação | B10: Período de realização (início/fim) e prorrogação automática | C10: Cobre captação + execução, até 36 meses. | D10: A2
A11: Identificação | B11: Resumo | C11: Máx. 5 linhas; todos os produtos; sem adjetivos, números, locais, datas ou artistas. Publicado no DOU. | D11: A3
A12: Identificação | B12: Objetivos (geral e específicos) | C12: Específicos = cada produto do Plano de Distribuição com quantidade (ex.: 'CURSO/OFICINA: 80 aulas de 50h/a'). Mal preenchido = proposta não analisada. | D12: A4
A13: Identificação | B13: Justificativa (8.000 caracteres) | C13: Transcrever os incisos do art. 1º e a alínea do art. 3º da Lei 8.313/91 aplicáveis, com fundamentação. | D13: A5
A14: Responsabilidade social | B14: Acessibilidade (8.000) | C14: Por produto: arquitetônica (dispensada se o espaço não é do proponente), comunicacional/conteúdo e divulgação acessível; Guia MDHC. | D14: A6
A15: Responsabilidade social | B15: Democratização de acesso (8.000) | C15: Distribuição/gratuidade e QUAL medida de ampliação do art. 42 (incisos I–X) será adotada. | D15: A7/A8
... A25: Anexar documentos | B25: PDFs do Anexo II | C25: Portfólio, identidade, CNPJ/estatuto/ata, currículos, projeto pedagógico, anuências, documentos de patrimônio. | D25: A20

Sheet Referência de preços
A1: Referências de preço (MG/Sudeste 2025-2026) usadas no alerta de preço das planilhas
A2: Fontes: atas e licitações de municípios de MG no PNCP, SindMusi-MG 2025, FEBRAPILS, Portaria SMC-SP 34/2023, tabela LPG Nova Friburgo, TRT5, Fiocruz. O SALIC compara cada item com a 'modal' do sistema; confira no SalicNet (aplicacoes.cultura.gov.br/comparar) antes de enviar.
A4: item | B4: unidade | C4: valor_minimo | D4: valor_tipico | E4: valor_maximo | F4: fonte | G4: observacao
A5: Coordenador geral / produtor executivo | B5: mês | C5: 3500 | D5: 5500 | E5: 8000 | F5: Tabela Referencial Nova Friburgo-RJ (LPG): https://s3.amazonaws.com/el.com.br/portal/uploads/6993/arquivos/C8332364EDB126E5116E3749DEA2C59B.pdf | G5: TIPO: edital público (RJ/Sudeste) + estimativa. Tabela: Coordenação geral R$ 3.500 (Nova Friburgo) a R$ 7.335 (média RJ). Produtor executivo R$ 3.333 a 4.000. Diária sugerida R$ 367-542. Ano da tabela não informado (ciclo LPG 2023-24). Corrigir para 2026. Sem dado de projeto Rouanet aprovado.
A6: Coordenador pedagógico | B6: mês | C6: 3000 | D6: 4500 | E6: 6500 | F6: Estimativa. Referência indireta: Nova Friburgo Coordenação de programação R$ 3.075-4.250 (mesma URL acima) | G6: TIPO: estimativa. Não achei tabela específica. Justificar com carga horária e projeto pedagógico.
A7: Diretor artístico | B7: mês | C7: 3000 | D7: 5000 | E7: 7000 | F7: Nova Friburgo (URL acima): Diretor artístico R$ 2.300-6.500 e Direção artística R$ 5.000-7.000. Itajubá-MG 2026 Diretor artístico R$ 1.415/diária 8h (estimado): https://pncp.gov.br/app/editais/21512443000131/2026/41 | G7: TIPO: edital público + licitação MG (valor estimado). Se for por apresentação usar unidade Cachê.
A8: Assistente de produção | B8: mês | C8: 2000 | D8: 3000 | E8: 4000 | F8: Nova Friburgo (URL acima): R$ 1.500-2.000 (diária R$ 175) | G8: TIPO: edital público + estimativa (ajustado para 2026 e MG). A tabela de Mogi Mirim-SP (R$ 150/h) foi vista só em resultado de busca e o PDF não baixou.
A9: Produtor local | B9: diária | C9: 200 | D9: 350 | E9: 550 | F9: Nova Friburgo (URL acima) produtor local diária R$ 196. Itajubá-MG 2026 produtor de backstage R$ 519/diária e coordenador técnico R$ 873/diária (estimados): https://pncp.gov.br/app/editais/21512443000131/2026/41 | G9: TIPO: edital público + licitação MG (estimado). Valores de licitação de agência de eventos tendem a ser altos.
A10: Oficineiro / arte-educador | B10: hora-aula | C10: 80 | D10: 130 | E10: 200 | F10: Portaria SMC-SP nº 34/2023 (cursos teóricos R$ 175/hora-aula): https://legislacao.prefeitura.sp.gov.br/portaria-secretaria-municipal-de-cultura-smc-34-de-12-de-maio-de-2023/consolidado . SindMusi-MG 2025 aula particular R$ 150/h: https://sindmusimg.org.br/content/files/2025/01/TABELA-SINDIMUSI-2025.pdf | G10: TIPO: tabela pública municipal SP (2023) + sindicato MG. Valor mínimo é estimativa para o interior de MG. No SALIC lançar como Serviço (qtde de horas na ocorrência) ou Mês.
A11: Mestre de cultura popular | B11: cachê por oficina ou apresentação | C11: 800 | D11: 1500 | E11: 3500 | F11: Estimativa. Referências: SMC-SP 34/2023 (1 integrante música R$ 3.500, cênicas R$ 4.500 por apresentação de 60 min). Teto IN 29/2026 art. 26 I = R$ 25.000 | G11: TIPO: estimativa. Mestres têm o mesmo teto de artista individual (R$ 25 mil).
A12: Cachê de artista individual (solo) | B12: cachê por apresentação | C12: 1250 | D12: 3500 | E12: 25000 | F12: SMC-SP 34/2023 (URL acima): música 1 integrante R$ 3.500, artes cênicas R$ 4.500, literatura R$ 3.000, contação de histórias R$ 1.250 (60 min). Teto: IN MinC 29/2026 art. 26 I https://www.gov.br/cultura/pt-br/acesso-a-informacao/legislacao-e-normativas/instrucao-normativa-minc-no-29-de-29-de-janeiro-de-2026 | G12: TIPO: tabela pública municipal SP (2023). O máximo é o TETO legal, não preço de mercado.
A13: Cachê de grupo artístico | B13: cachê por apresentação | C13: 5000 | D13: 7000 | E13: 50000 | F13: SMC-SP 34/2023: 2-3 integrantes R$ 5.000-5.500, 4-5 integrantes R$ 6.500-7.100, 6 ou mais R$ 7.400-8.000. Teto IN 29 art. 26 II = R$ 50.000 | G13: TIPO: tabela pública municipal SP (2023). O máximo é o TETO legal. Orquestras seguem regra própria (por músico).
A14: Músico (por apresentação) | B14: cachê | C14: 500 | D14: 800 | E14: 1500 | F14: SindMusi-MG Tabela 2025 (valores mínimos): acompanhamento de artista nacional R$ 800/show, bar 3h R$ 500, baile R$ 600, instrumentista de concerto R$ 600, artista estrangeiro R$ 1.500. Ensaio 3h R$ 250. https://sindmusimg.org.br/content/files/2025/01/TABELA-SINDIMUSI-2025.pdf | G14: TIPO: tabela de sindicato MG 2025. Teto IN 29 art. 26 III = R$ 5.000 por músico de orquestra. Diária de viagem do músico (SindMusi): R$ 200 até 300 km, R$ 300 acima.
A15: Regente / maestro | B15: cachê por espetáculo | C15: 3200 | D15: 4500 | E15: 25000 | F15: SindMusi-MG 2025: regente R$ 4.500/espetáculo, regente assistente R$ 3.200, ensaio 2h R$ 200 (URL acima). Teto IN 29 art. 26 III = R$ 25.000 | G15: TIPO: tabela de sindicato MG 2025. O máximo é o TETO legal.
A16: Palhaço / ator (intervenção artística) | B16: cachê por intervenção | C16: 600 | D16: 1200 | E16: 2500 | F16: Estimativa. Referências: Nova Friburgo ator/atriz diária R$ 558 (obra R$ 3.000-8.152). SMC-SP cênicas 1 integrante R$ 4.500/60 min | G16: TIPO: estimativa. Não achei tabela SATED-MG publicada. Para intervenção curta (até 30 min) usar proporção.
... A68: Ambulância de remoção para evento | B68: hora | C68: 126 | D68: 160 | E68: 190 | F68: Entre Rios de Minas-MG 2026: estimado R$ 186,63/h, homologado R$ 126/h https://pncp.gov.br/app/editais/20356747000194/2026/45 | G68: TIPO: licitação pública MG 2026 (homologado).

Sheet Parâmetros IN 29
A1: Parâmetros da IN MinC nº 29/2026 usados nas verificações
A3: Parâmetro | B3: Valor | C3: Fonte
A4: Custos de administração – máx. sobre o valor do projeto | B4: 0.15 | C4: IN 29/2026, art. 22
A5: Acessibilidade, comunicação e divulgação acessíveis – máx. sobre o valor do projeto | B5: 0.2 | C5: IN 29/2026, art. 20
A6: Remuneração para captação – máx. sobre o valor do projeto | B6: 0.1 | C6: IN 29/2026, art. 19
A7: Remuneração para captação – teto em R$ | B7: 150000 | C7: IN 29/2026, art. 19
A8: Pessoa física – valor máx. por projeto e carteira (até 2 projetos ativos) | B8: 500000 | C8: IN 29/2026, arts. 10, I e 11, I
A9: Pessoa jurídica – valor máx. por projeto (exceto patrimônio cultural, art. 14) | B9: 1500000 | C9: IN 29/2026, art. 11, II
A10: Pessoa jurídica – carteira (até 10 projetos ativos) | B10: 15000000 | C10: IN 29/2026, art. 10, III
A11: MEI – carteira (até 4 projetos ativos) | B11: 1500000 | C11: IN 29/2026, art. 10, II
A12: 1º projeto sem portfólio – valor máx. | B12: 200000 | C12: IN 29/2026, art. 4º, §5º
A13: Cachê artista individual / mestre(a) – por apresentação | B13: 25000 | C13: IN 29/2026, art. 26, I
A14: Cachê grupo/coletivo – por apresentação | B14: 50000 | C14: IN 29/2026, art. 26, II
A15: Orquestra – por músico (regente: R$ 25.000) | B15: 5000 | C15: IN 29/2026, art. 26, III
... A20: Custo por beneficiário (só com venda de ingresso/produto) | B20: 300 | C20: IN 29/2026, art. 16
A23: VALOR DO PROJETO = Pré-produção/Preparação + Produção/Execução + Pós-produção + Assessoria contábil e jurídica + Recolhimentos (IN 29, art. 17; Anexo I, LXXV). São as 5 abas de etapas do SALIC.
A24: CUSTOS VINCULADOS e CAPTAÇÃO não têm itens no SALIC: o proponente escolhe só o PERCENTUAL (Orçamento do projeto > Custos vinculados) e o sistema calcula sobre o valor do projeto. Os gastos são comprovados na prestação de contas (Manual do Proponente IN 2026, p. 43-49).
A25: VALOR TOTAL DO PROJETO = valor do projeto + custos vinculados + captação (Anexo I, LXXVII). É este valor que foi fechado no valor pré-planejado do cliente.
A26: Enquadramento Art. 18 x Art. 26: definido pela área/segmento do PRODUTO PRINCIPAL (maior custo); em festa/festival vale o produto secundário de maior valor (IN 29, art. 46; Anexo IV).
A27: Projetos sociais, educativos, esportivos e gastronômicos que não sejam patrimônio imaterial: só custos artístico-culturais são aprovados (IN 29, art. 18).
A28: Convenção de cores: azul = entrada editável; preto = fórmula; verde = vínculo com outra aba; amarelo = percentual a escolher no SALIC.

Sheet P01 Escola de Ofícios do Espetá
A1: P01 – Escola de Ofícios do Espetáculo | Planilha orçamentária no padrão SALIC (IN MinC 29/2026)
A2: Proponente (planilha / pasta Drive / tipo) | B2: Educare / Educare / PJ
A3: Produto principal (maior custo) e enquadramento | B3: Curso/Oficina – ciclo formativo de iniciação aos ofícios técnicos e criativos das artes cênicas (9 turmas x 24h, 270 vagas, 3 núcleos) – Artes Cênicas / Empreend Ações Educ-Cult/Capacitação/Treinamento → Art. 18
A4: Público estimado | B4: 270 beneficiários diretos (vagas formativas) + ~600 espectadores na mostra final (estimativa a validar com a lotação).
A5: Municípios | B5: Belo Horizonte (núcleos central e Venda Nova) e Contagem (núcleo metropolitano) – MG.
A6: Execução | B6: 7 meses (jun a dez/2027)
A7: Valor pré-planejado (planilha do cliente) | B7: 500000
A9: Resumo – o que vai ao SALIC
A10: Etapa / componente | B10: Valor (R$) | C10: % do valor do projeto | D10: Limite IN 29 | E10: Situação
A11: Pré-produção / Preparação | B11: =SUMIFS($I$26:$I$72,$B$26:$B$72,A11) -> 34000 | C11: =IF($B$16=0,0,B11/$B$16) -> 0.086404066
A12: Produção / Execução | B12: =SUMIFS($I$26:$I$72,$B$26:$B$72,A12) -> 310948 | C12: =IF($B$16=0,0,B12/$B$16) -> 0.79021093
A13: Pós-produção | B13: =SUMIFS($I$26:$I$72,$B$26:$B$72,A13) -> 23000 | C13: =IF($B$16=0,0,B13/$B$16) -> 0.058449809
A14: Assessoria contábil e jurídica | B14: =SUMIFS($I$26:$I$72,$B$26:$B$72,A14) -> 14500 | C14: =IF($B$16=0,0,B14/$B$16) -> 0.036848793
A15: Recolhimentos | B15: =SUMIFS($I$26:$I$72,$B$26:$B$72,A15) -> 11052 | C15: =IF($B$16=0,0,B15/$B$16) -> 0.028086404
A16: VALOR DO PROJETO (base de cálculo – soma das 5 etapas) | B16: =SUM(B11:B15) -> 393500
A17: Custos de administração (percentual escolhido no SALIC) | B17: =$B$16*C17 -> 31480 | C17: 0.08 | D17: ='Parâmetros IN 29'!$B$4 -> 0.15 | E17: =IF(AND(C17<=D17),"OK","EXCEDE") -> OK
A18: Custos de acessibilidade, comunicação e divulgação acessíveis (percentual no SALIC) | B18: =$B$16*C18 -> 35415 | C18: 0.09 | D18: ='Parâmetros IN 29'!$B$5 -> 0.2 | E18: =IF(AND(C18<=D18),"OK","EXCEDE") -> OK
A19: Remuneração para captação de recursos (percentual no SALIC; teto R$ 150 mil) | B19: =MIN($B$16*C19,'Parâmetros IN 29'!$B$7) -> 39350 | C19: 0.1 | D19: ='Parâmetros IN 29'!$B$6 -> 0.1 | E19: =IF(AND(C19<=D19,B19<='Parâmetros IN 29'!$B$7),"OK","EXCEDE") -> OK
A20: VALOR TOTAL DO PROJETO (valor solicitado) | B20: =B16+B17+B18+B19 -> 499745
A21: Diferença para o valor pré-planejado | B21: =B20-B7 -> -255
A22: Teto por projeto aplicável (PF R$ 500 mil / PJ R$ 1,5 mi) | B22: ='Parâmetros IN 29'!$B$9 -> 1500000 | C22: PJ | E22: =IF(B20<=B22,"OK","EXCEDE") -> OK
A23: Percentuais (células amarelas) são inteiros escolhidos para cobrir o detalhamento interno abaixo da planilha. Altere-os aqui e no SALIC.
A24: Planilha orçamentária analítica – itens a lançar no SALIC (Orçamento do projeto > Custos por produtos)
A25: Produto | B25: Etapa (aba do SALIC) | C25: Item | D25: Unidade SALIC | E25: Unidade de cálculo | F25: Quantidade | G25: Ocorrência | H25: Valor unitário (R$) | I25: Valor total (R$) | J25: Local (UF – município) | K25: Referência de mercado mín–típ–máx (R$) | L25: Alerta de preço | M25: Justificativa / memória de cálculo
A26: Oficinas – Escola de Ofícios do Espetáculo (principal) | B26: Pré-produção / Preparação | C26: Coordenação geral (Túlio Gama) | D26: Mês | E26: mês | F26: 1 | G26: 2 | H26: 7000 | I26: =F26*G26*H26 -> 14000 | J26: MG - Belo Horizonte | K26: 3.500 – 5.500 – 8.000 | L26: dentro da faixa | M26: Jun–jul/2027: formalização de núcleos, parcerias, contratações e plano de trabalho. Valor no piso da faixa de referência (7.000–12.000).
A27: Oficinas – Escola de Ofícios do Espetáculo (principal) | B27: Pré-produção / Preparação | C27: Coordenação pedagógica (Jade Oliveira) | D27: Mês | E27: mês | F27: 1 | G27: 1 | H27: 5500 | I27: =F27*G27*H27 -> 5500 | J27: MG - Belo Horizonte | K27: 3.000 – 4.500 – 6.500 | L27: dentro da faixa | M27: Jul/2027: desenho pedagógico final, curadoria de educadores, critérios de seleção e matriz núcleo x formação. Dedicação parcial.
A28: Oficinas – Escola de Ofícios do Espetáculo (principal) | B28: Pré-produção / Preparação | C28: Produtor(a) executivo(a) | D28: Mês | E28: mês | F28: 1 | G28: 1 | H28: 5500 | I28: =F28*G28*H28 -> 5500 | J28: MG - Belo Horizonte | K28: 3.500 – 5.500 – 8.000 | L28: dentro da faixa | M28: Jul/2027: contratos, logística dos núcleos, inscrições e mobilização.
A29: Oficinas – Escola de Ofícios do Espetáculo (principal) | B29: Pré-produção / Preparação | C29: Elaboração de planos de aula e conteúdo programático por eixo (figurino, maquiagem, iluminação, audiovisual) | D29: Serviço | E29: serviço | F29: 4 | G29: 1 | H29: 1500 | I29: =F29*G29*H29 -> 6000 | J29: MG - Belo Horizonte | K29: s/ ref. | M29: Exigência do Anexo II item 7.3 (carga horária e conteúdo programático). 1 plano por eixo, elaborado pelo educador responsável.
A30: Oficinas – Escola de Ofícios do Espetáculo (principal) | B30: Pré-produção / Preparação | C30: Vistorias técnicas e de acessibilidade nos núcleos (van com motorista) | D30: Unidade | E30: diária | F30: 1 | G30: 3 | H30: 1000 | I30: =F30*G30*H30 -> 3000 | J30: MG - Belo Horizonte e Contagem (3 núcleos) | K30: 750 – 1.000 – 1.500 | L30: dentro da faixa | M30: 3 diárias para vistoria dos 3 núcleos e do local da mostra (checklist de acessibilidade, estrutura e energia).
A31: Oficinas – Escola de Ofícios do Espetáculo (principal) | B31: Produção / Execução | C31: Coordenação geral (Túlio Gama) | D31: Mês | E31: mês | F31: 1 | G31: 4 | H31: 7000 | I31: =F31*G31*H31 -> 28000 | J31: MG - Belo Horizonte | K31: 3.500 – 5.500 – 8.000 | L31: dentro da faixa | M31: Ago–nov/2027: execução das 9 turmas, visitas e mostra.
A32: Oficinas – Escola de Ofícios do Espetáculo (principal) | B32: Produção / Execução | C32: Coordenação pedagógica (Jade Oliveira) | D32: Mês | E32: mês | F32: 1 | G32: 4 | H32: 5500 | I32: =F32*G32*H32 -> 22000 | J32: MG - Belo Horizonte | K32: 3.000 – 4.500 – 6.500 | L32: dentro da faixa | M32: Ago–nov/2027: acompanhamento de frequência, devolutivas, avaliação e certificação.
A33: Oficinas – Escola de Ofícios do Espetáculo (principal) | B33: Produção / Execução | C33: Produtor(a) executivo(a) | D33: Mês | E33: mês | F33: 1 | G33: 4 | H33: 5500 | I33: =F33*G33*H33 -> 22000 | J33: MG - Belo Horizonte | K33: 3.500 – 5.500 – 8.000 | L33: dentro da faixa | M33: Ago–nov/2027: gestão operacional dos 3 núcleos, fornecedores e mostra.
A34: Oficinas – Escola de Ofícios do Espetáculo (principal) | B34: Produção / Execução | C34: Coordenação técnica (iluminação, montagem e integração da mostra) | D34: Mês | E34: mês | F34: 1 | G34: 4 | H34: 5000 | I34: =F34*G34*H34 -> 20000 | J34: MG - Belo Horizonte | K34: s/ ref. | M34: Função prevista no item 14 da proposta; sem código no catálogo, valor abaixo de produtor executivo. Responde por segurança de equipamentos e operação supervisionada.
A35: Oficinas – Escola de Ofícios do Espetáculo (principal) | B35: Produção / Execução | C35: Assistente de produção (apoio aos núcleos) | D35: Mês | E35: mês | F35: 1 | G35: 4 | H35: 3500 | I35: =F35*G35*H35 -> 14000 | J35: MG - Belo Horizonte e Contagem (3 núcleos) | K35: 2.000 – 3.000 – 4.000 | L35: dentro da faixa | M35: 1 assistente para circular entre os 3 núcleos (materiais, listas de presença, lanches).
A36: Oficinas – Escola de Ofícios do Espetáculo (principal) | B36: Produção / Execução | C36: Educadores(as) dos eixos – oficinas, visita e mostra | D36: Unidade | E36: hora-aula | F36: 9 | G36: 24 | H36: 105 | I36: =F36*G36*H36 -> 22680 | J36: MG - Belo Horizonte e Contagem (3 núcleos) | K36: 80 – 130 – 200 | L36: dentro da faixa | M36: 9 turmas x 24h (16h de oficinas em 8 encontros de 2h + 4h de visita técnica + 4h de preparação/mostra) x R$130 (valor de referência). [Linha de equilíbrio: ajustada em R$ -5,199.21 para fechar o valor total com os percentuais de custos vinculados escolhidos no SALIC.]
A37: Oficinas – Escola de Ofícios do Espetáculo (principal) | B37: Produção / Execução | C37: Educadores(as) assistentes/monitores técnicos (turmas de iluminação e maquiagem) | D37: Unidade | E37: hora-aula | F37: 5 | G37: 16 | H37: 100 | I37: =F37*G37*H37 -> 8000 | J37: MG - Belo Horizonte e Contagem (3 núcleos) | K37: 80 – 130 – 200 | L37: dentro da faixa | M37: 5 turmas com manuseio de equipamentos elétricos e cosméticos (3 iluminação + 2 maquiagem) x 16h de oficina; segurança e atendimento a 30 participantes. Piso da faixa.
A38: Oficinas – Escola de Ofícios do Espetáculo (principal) | B38: Produção / Execução | C38: Mediador(a) cultural nas visitas técnicas | D38: Unidade | E38: hora-aula | F38: 9 | G38: 4 | H38: 130 | I38: =F38*G38*H38 -> 4680 | J38: MG - Belo Horizonte | K38: 80 – 130 – 200 | L38: dentro da faixa | M38: 1 visita/mediação por turma (Palácio das Artes, Sesc Palladium, escolas de teatro etc.), 4h cada.
A39: Oficinas – Escola de Ofícios do Espetáculo (principal) | B39: Produção / Execução | C39: Ônibus com motorista para visitas técnicas | D39: Unidade | E39: diária | F39: 9 | G39: 1 | H39: 2500 | I39: =F39*G39*H39 -> 22500 | J39: MG - Belo Horizonte e Contagem (3 núcleos) | K39: 1.500 – 2.200 – 3.500 | L39: dentro da faixa | M39: 1 ônibus por turma (30 participantes + equipe) do núcleo ao equipamento visitado; reduz barreira de deslocamento (art. 42, II). Piso da faixa.
A40: Oficinas – Escola de Ofícios do Espetáculo (principal) | B40: Produção / Execução | C40: Material de consumo das oficinas (tecidos e aviamentos, maquiagem descartável e higienização, gelatinas/filtros, mídias) | D40: Unidade | E40: kit/participante | F40: 270 | G40: 1 | H40: 60 | I40: =F40*G40*H40 -> 16200 | J40: MG - Belo Horizonte e Contagem (3 núcleos) | K40: s/ ref. | M40: 270 vagas x R$60; materiais consumidos nas práticas (60–70% da carga horária).
A41: Oficinas – Escola de Ofícios do Espetáculo (principal) | B41: Produção / Execução | C41: Locação de kit didático de iluminação cênica (refletores, mesa, cabos, dimmer) | D41: Unidade | E41: diária | F41: 1 | G41: 8 | H41: 1500 | I41: =F41*G41*H41 -> 12000 | J41: MG - Belo Horizonte e Contagem (3 núcleos) | K41: 1.500 – 3.000 – 6.000 | L41: dentro da faixa | M41: 3 turmas de iluminação; 8 diárias concentradas nos encontros práticos de montagem/operação (piso da faixa). Pode ser cotado com a Armind, respeitado o limite de 20% por fornecedor.
A42: Oficinas – Escola de Ofícios do Espetáculo (principal) | B42: Produção / Execução | C42: Locação de equipamentos audiovisuais para aulas (câmera, tripé, microfone, luz de vídeo) | D42: Unidade | E42: diária | F42: 1 | G42: 6 | H42: 600 | I42: =F42*G42*H42 -> 3600 | J42: MG - Belo Horizonte e Contagem (3 núcleos) | K42: s/ ref. | M42: 2 turmas de audiovisual; 3 encontros práticos cada; complementa celulares dos participantes (produção com dispositivos acessíveis).
A43: Oficinas – Escola de Ofícios do Espetáculo (principal) | B43: Produção / Execução | C43: Locação de máquinas de costura e manequins (turmas de figurino) | D43: Mês | E43: mês | F43: 2 | G43: 1 | H43: 1200 | I43: =F43*G43*H43 -> 2400 | J43: MG - Belo Horizonte e Contagem (3 núcleos) | K43: s/ ref. | M43: 2 turmas de figurino; 1 mês de prática de adaptação/reaproveitamento cada. Locação mais econômica que aquisição (art. 30).
A44: Oficinas – Escola de Ofícios do Espetáculo (principal) | B44: Produção / Execução | C44: Lanche para participantes | D44: Unidade | E44: unidade | F44: 270 | G44: 8 | H44: 8 | I44: =F44*G44*H44 -> 17280 | J44: MG - Belo Horizonte e Contagem (3 núcleos) | K44: s/ ref. | M44: 270 participantes x 8 encontros x R$8 (piso). Atividades de 2h a 4h com público jovem em vulnerabilidade; reduz evasão.
A45: Oficinas – Escola de Ofícios do Espetáculo (principal) | B45: Produção / Execução | C45: Certificados de conclusão | D45: Unidade | E45: unidade | F45: 270 | G45: 1 | H45: 8 | I45: =F45*G45*H45 -> 2160 | J45: MG - Belo Horizonte e Contagem (3 núcleos) | K45: s/ ref. | M45: Certificação com carga horária para concluintes (frequência mínima 60%).
A46: Oficinas – Escola de Ofícios do Espetáculo (principal) | B46: Produção / Execução | C46: Seguro de acidentes pessoais dos participantes | D46: Unidade | E46: apólice | F46: 1 | G46: 1 | H46: 3500 | I46: =F46*G46*H46 -> 3500 | J46: MG - Belo Horizonte e Contagem (3 núcleos) | K46: 800 – 2.000 – 5.000 | L46: dentro da faixa | M46: Participantes a partir de 14 anos em atividades práticas com equipamentos elétricos e visitas externas.
A47: Oficinas – Escola de Ofícios do Espetáculo (principal) | B47: Produção / Execução | C47: Registro fotográfico das oficinas e visitas | D47: Unidade | E47: diária | F47: 1 | G47: 5 | H47: 900 | I47: =F47*G47*H47 -> 4500 | J47: MG - Belo Horizonte e Contagem (3 núcleos) | K47: 500 – 800 – 1.500 | L47: dentro da faixa | M47: 5 diárias distribuídas entre núcleos e visitas; comprovação do objeto (meta 2 e 5).
A48: Oficinas – Escola de Ofícios do Espetáculo (principal) | B48: Produção / Execução | C48: Registro audiovisual das oficinas | D48: Unidade | E48: diária | F48: 1 | G48: 2 | H48: 1800 | I48: =F48*G48*H48 -> 3600 | J48: MG - Belo Horizonte e Contagem (3 núcleos) | K48: 900 – 1.400 – 2.500 | L48: dentro da faixa | M48: 2 diárias de captação para vídeo-memória e comprovação.
A49: Mostra final integrada (secundário) | B49: Produção / Execução | C49: Direção artística da mostra final integrada | D49: Cachê | E49: cachê | F49: 1 | G49: 1 | H49: 10000 | I49: =F49*G49*H49 -> 10000 | J49: MG - Belo Horizonte | K49: s/ ref. | M49: Concepção e direção da culminância que integra figurino, maquiagem, luz e audiovisual com o espetáculo parceiro; abaixo da faixa por ser montagem curta.
A50: Mostra final integrada (secundário) | B50: Produção / Execução | C50: Cachê de grupo teatral parceiro (apresentação na mostra – campo prático supervisionado) | D50: Cachê | E50: cachê | F50: 1 | G50: 1 | H50: 8000 | I50: =F50*G50*H50 -> 8000 | J50: MG - Belo Horizonte | K50: 5.000 – 7.000 – 50.000 | L50: dentro da faixa | M50: 1 apresentação teatral; grupo a confirmar com anuência e autorização do autor do texto (Anexo II 3.3). Valor de referência.
A51: Mostra final integrada (secundário) | B51: Produção / Execução | C51: Locação de iluminação cênica médio porte (mostra) | D51: Unidade | E51: diária | F51: 1 | G51: 2 | H51: 3500 | I51: =F51*G51*H51 -> 7000 | J51: MG - Belo Horizonte | K51: s/ ref. | M51: Montagem assistida pelos participantes + apresentação (2 diárias).
A52: Mostra final integrada (secundário) | B52: Produção / Execução | C52: Locação de sonorização pequeno porte (mostra) | D52: Unidade | E52: diária | F52: 1 | G52: 2 | H52: 2500 | I52: =F52*G52*H52 -> 5000 | J52: MG - Belo Horizonte | K52: 1.100 – 1.900 – 3.500 | L52: dentro da faixa | M52: Montagem/ensaio + apresentação.
A53: Mostra final integrada (secundário) | B53: Produção / Execução | C53: Técnico(a) de luz (supervisão da operação pelos participantes) | D53: Unidade | E53: diária | F53: 1 | G53: 2 | H53: 650 | I53: =F53*G53*H53 -> 1300 | J53: MG - Belo Horizonte | K53: 250 – 400 – 750 | L53: dentro da faixa | M53: 2 diárias.
A54: Mostra final integrada (secundário) | B54: Produção / Execução | C54: Técnico(a) de som | D54: Unidade | E54: diária | F54: 1 | G54: 2 | H54: 700 | I54: =F54*G54*H54 -> 1400 | J54: MG - Belo Horizonte | K54: 250 – 400 – 750 | L54: dentro da faixa | M54: 2 diárias.
A55: Mostra final integrada (secundário) | B55: Produção / Execução | C55: Montadores | D55: Unidade | E55: diária | F55: 3 | G55: 2 | H55: 300 | I55: =F55*G55*H55 -> 1800 | J55: MG - Belo Horizonte | K55: 200 – 300 – 400 | L55: dentro da faixa | M55: 3 montadores x 2 diárias (montagem e desmontagem).
A56: Mostra final integrada (secundário) | B56: Produção / Execução | C56: Ônibus para deslocamento dos participantes dos 3 núcleos à mostra | D56: Unidade | E56: diária | F56: 3 | G56: 1 | H56: 2500 | I56: =F56*G56*H56 -> 7500 | J56: MG - Belo Horizonte e Contagem (3 núcleos) | K56: 1.500 – 2.200 – 3.500 | L56: dentro da faixa | M56: 1 ônibus por núcleo no dia do ensaio geral/mostra.
A57: Mostra final integrada (secundário) | B57: Produção / Execução | C57: Brigadista | D57: Unidade | E57: diária | F57: 1 | G57: 2 | H57: 300 | I57: =F57*G57*H57 -> 600 | J57: MG - Belo Horizonte | K57: 180 – 300 – 470 | L57: dentro da faixa | M57: Exigência de segurança para evento aberto ao público.
A58: Mostra final integrada (secundário) | B58: Produção / Execução | C58: Registro fotográfico da mostra | D58: Unidade | E58: diária | F58: 1 | G58: 1 | H58: 900 | I58: =F58*G58*H58 -> 900 | J58: MG - Belo Horizonte | K58: 500 – 800 – 1.500 | L58: dentro da faixa | M58: Comprovação e memória.
A59: Mostra final integrada (secundário) | B59: Produção / Execução | C59: Registro audiovisual da mostra | D59: Unidade | E59: diária | F59: 1 | G59: 1 | H59: 1800 | I59: =F59*G59*H59 -> 1800 | J59: MG - Belo Horizonte | K59: 900 – 1.400 – 2.500 | L59: dentro da faixa | M59: Base do vídeo-memória a ser publicado com Libras e audiodescrição (art. 42, III).
A60: Mostra final integrada (secundário) | B60: Produção / Execução | C60: Materiais cênicos da mostra (figurinos adaptados, maquiagem, consumíveis de luz) – verba de ajuste | D60: Verba | E60: verba | F60: 1 | G60: 1 | H60: 4348 | I60: =F60*G60*H60 -> 4348 | J60: MG - Belo Horizonte | K60: s/ ref. | M60: Materiais aplicados pelos participantes na mostra; linha usada para arredondamento ao valor-alvo.
A61: Oficinas – Escola de Ofícios do Espetáculo (principal) | B61: Pós-produção | C61: Coordenação geral – encerramento | D61: Mês | E61: mês | F61: 1 | G61: 1 | H61: 7000 | I61: =F61*G61*H61 -> 7000 | J61: MG - Belo Horizonte | K61: 3.500 – 5.500 – 8.000 | L61: dentro da faixa | M61: Dez/2027: relatório de execução e indicadores.
A62: Oficinas – Escola de Ofícios do Espetáculo (principal) | B62: Pós-produção | C62: Coordenação pedagógica – relatório pedagógico e certificação | D62: Mês | E62: mês | F62: 1 | G62: 1 | H62: 5500 | I62: =F62*G62*H62 -> 5500 | J62: MG - Belo Horizonte | K62: 3.000 – 4.500 – 6.500 | L62: dentro da faixa | M62: Síntese pedagógica, avaliação e emissão de certificados.
A63: Oficinas – Escola de Ofícios do Espetáculo (principal) | B63: Pós-produção | C63: Produtor(a) executivo(a) – encerramento | D63: Mês | E63: mês | F63: 1 | G63: 1 | H63: 5500 | I63: =F63*G63*H63 -> 5500 | J63: MG - Belo Horizonte | K63: 3.500 – 5.500 – 8.000 | L63: dentro da faixa | M63: Organização documental e comprovações.
A64: Oficinas – Escola de Ofícios do Espetáculo (principal) | B64: Pós-produção | C64: Edição e finalização do vídeo-memória (com legendas) | D64: Serviço | E64: serviço | F64: 1 | G64: 1 | H64: 5000 | I64: =F64*G64*H64 -> 5000 | J64: MG - Belo Horizonte | K64: 1.500 – 3.000 – 5.000 | L64: dentro da faixa | M64: Vídeo de 8–12 min sobre o percurso e a mostra, publicado gratuitamente.
A65: Oficinas – Escola de Ofícios do Espetáculo (principal) | B65: Assessoria contábil e jurídica | C65: Contador(a) | D65: Mês | E65: mês | F65: 1 | G65: 7 | H65: 1500 | I65: =F65*G65*H65 -> 10500 | J65: MG - Belo Horizonte | K65: 800 – 1.500 – 3.000 | L65: dentro da faixa | M65: Jun–dez/2027; escrituração do projeto e prestação de contas.
A66: Oficinas – Escola de Ofícios do Espetáculo (principal) | B66: Assessoria contábil e jurídica | C66: Assessoria jurídica (contratos, termos de uso de imagem de menores, anuências) | D66: Mês | E66: mês | F66: 1 | G66: 2 | H66: 2000 | I66: =F66*G66*H66 -> 4000 | J66: MG - Belo Horizonte | K66: 1.500 – 3.000 – 5.000 | L66: dentro da faixa | M66: Atendimento a participantes de 14+ anos exige termos específicos.
A67: Oficinas – Escola de Ofícios do Espetáculo (principal) | B67: Produção / Execução | C67: Intérprete de Libras (aulas inaugurais, visitas, mostra e banco de horas sob demanda) | D67: Unidade | E67: hora | F67: 1 | G67: 50 | H67: 180 | I67: =F67*G67*H67 -> 9000 | J67: MG - Belo Horizonte e Contagem (3 núcleos) | K67: 144 – 192 – 240 | L67: dentro da faixa | M67: 9 aulas inaugurais x 2h + 4h mostra + 28h sob demanda de participantes surdos. [Acessibilidade de conteúdo lançada como item do produto, conforme exemplo do Manual do Proponente 2026, p. 47.]
A68: Oficinas – Escola de Ofícios do Espetáculo (principal) | B68: Produção / Execução | C68: Audiodescrição da mostra (roteiro + narração ao vivo) | D68: Serviço | E68: serviço | F68: 1 | G68: 1 | H68: 3000 | I68: =F68*G68*H68 -> 3000 | J68: MG - Belo Horizonte | K68: 2.300 – 4.500 – 9.000 | L68: dentro da faixa | M68: Acessibilidade comunicacional do evento aberto. [Acessibilidade de conteúdo lançada como item do produto, conforme exemplo do Manual do Proponente 2026, p. 47.]
A69: Oficinas – Escola de Ofícios do Espetáculo (principal) | B69: Produção / Execução | C69: Janela de Libras e audiodescrição no vídeo-memória | D69: Serviço | E69: serviço | F69: 1 | G69: 1 | H69: 3000 | I69: =F69*G69*H69 -> 3000 | J69: MG - Belo Horizonte | K69: 2.300 – 4.500 – 9.000 | L69: dentro da faixa | M69: Registro online acessível – medida de ampliação de acesso art. 42, III. [Acessibilidade de conteúdo lançada como item do produto, conforme exemplo do Manual do Proponente 2026, p. 47.]
A70: Oficinas – Escola de Ofícios do Espetáculo (principal) | B70: Produção / Execução | C70: Materiais pedagógicos em braille/ampliados | D70: Unidade | E70: unidade | F70: 80 | G70: 1 | H70: 25 | I70: =F70*G70*H70 -> 2000 | J70: MG - Belo Horizonte e Contagem (3 núcleos) | K70: s/ ref. | M70: Apostilas e programas acessíveis sob demanda. [Acessibilidade de conteúdo lançada como item do produto, conforme exemplo do Manual do Proponente 2026, p. 47.]
A71: Oficinas – Escola de Ofícios do Espetáculo (principal) | B71: Produção / Execução | C71: Gestão de redes sociais e conteúdo acessível (legendas, descrição de imagens) | D71: Mês | E71: mês | F71: 1 | G71: 4 | H71: 3800 | I71: =F71*G71*H71 -> 15200 | J71: MG - Belo Horizonte | K71: 1.200 – 2.500 – 4.000 | L71: dentro da faixa | M71: Campanha de inscrições e cobertura das oficinas e mostra. [Acessibilidade de conteúdo lançada como item do produto, conforme exemplo do Manual do Proponente 2026, p. 47.]
A72: Oficinas – Escola de Ofícios do Espetáculo (principal) | B72: Recolhimentos | C72: INSS patronal 20% sobre pagamentos a pessoas físicas (RPA) | D72: Verba | E72: verba | F72: 1 | G72: 1 | H72: 11052 | I72: =F72*G72*H72 -> 11052 | J72: MG - Belo Horizonte | K72: s/ ref. | M72: 20% x R$ 55.260 (base estimada de pagamentos a pessoas físicas: educadores R$28.080, monitores R$8.000, mediadores R$4.680, direção da mostra R$10.000, técnicos e montadores R$4.500). ISS não lançado: retido/embutido nas notas de prestadores PJ.
H73: TOTAL | I73: =SUM(I26:I72) -> 393500
A75: Detalhamento interno dos custos vinculados – NÃO lançar itens no SALIC (só o percentual); usar para planejar a execução e a prestação de contas
A76: Componente | B76: Custo vinculado | C76: Item | D76: Unidade SALIC | E76: Unidade de cálculo | F76: Quantidade | G76: Ocorrência | H76: Valor unitário (R$) | I76: Valor total (R$) | J76: Local | K76: Referência de mercado | L76: Alerta de preço | M76: Justificativa
A77: Administração do projeto (custos vinculados) | B77: Custos de administração | C77: Elaboração da proposta cultural (contrato prévio) | D77: Serviço | E77: serviço | F77: 1 | G77: 1 | H77: 12000 | I77: =F77*G77*H77 -> 12000 | J77: MG - Belo Horizonte | K77: 3.000 – 8.000 – 20.000 | L77: dentro da faixa | M77: 2,4% do valor total; pago só após aprovação (art. 22, VIII).
A78: Administração do projeto (custos vinculados) | B78: Custos de administração | C78: Elaboração de prestação de contas | D78: Serviço | E78: serviço | F78: 1 | G78: 1 | H78: 7000 | I78: =F78*G78*H78 -> 7000 | J78: MG - Belo Horizonte | K78: s/ ref. | M78: Art. 22, IX.
A79: Administração do projeto (custos vinculados) | B79: Custos de administração | C79: Assistente administrativo-financeiro | D79: Mês | E79: mês | F79: 1 | G79: 3 | H79: 3500 | I79: =F79*G79*H79 -> 10500 | J79: MG - Belo Horizonte | K79: s/ ref. | M79: Pagamentos, contratos e documentação nos meses de maior volume (ago–out).
A80: Administração do projeto (custos vinculados) | B80: Custos de administração | C80: Tarifas bancárias | D80: Mês | E80: mês | F80: 1 | G80: 8 | H80: 80 | I80: =F80*G80*H80 -> 640 | J80: MG - Belo Horizonte | K80: s/ ref. | M80: Contas captação/movimento.
A81: Administração do projeto (custos vinculados) | B81: Custos de administração | C81: Material de escritório/expediente | D81: Verba | E81: verba | F81: 1 | G81: 1 | H81: 1200 | I81: =F81*G81*H81 -> 1200 | J81: MG - Belo Horizonte | K81: s/ ref. | M81: Impressão de listas de presença, fichas de inscrição e termos.
A82: Administração do projeto (custos vinculados) | B82: Custos de acessibilidade, comunicação e divulgação | C82: Consultor(a) de acessibilidade (plano por núcleo, Guia MDHC, treinamento de educadores, adaptações sensoriais) | D82: Mês | E82: mês | F82: 1 | G82: 4 | H82: 3500 | I82: =F82*G82*H82 -> 14000 | J82: MG - Belo Horizonte | K82: s/ ref. | M82: Converte a diretriz do item 12 em protocolo; atenção a autistas e PcD.
A83: Administração do projeto (custos vinculados) | B83: Custos de acessibilidade, comunicação e divulgação | C83: Equipe de apoio a PcD na mostra | D83: Unidade | E83: diária | F83: 3 | G83: 1 | H83: 250 | I83: =F83*G83*H83 -> 750 | J83: MG - Belo Horizonte | K83: 200 – 260 – 380 | L83: dentro da faixa | M83: 3 monitores no dia da mostra.
A84: Administração do projeto (custos vinculados) | B84: Custos de acessibilidade, comunicação e divulgação | C84: Designer gráfico (identidade visual e peças, com aplicação das marcas obrigatórias) | D84: Serviço | E84: serviço | F84: 1 | G84: 1 | H84: 6000 | I84: =F84*G84*H84 -> 6000 | J84: MG - Belo Horizonte | K84: 2.500 – 4.000 – 7.000 | L84: dentro da faixa | M84: Identidade da Escola de Ofícios + peças de inscrição e da mostra; marcas Lei Rouanet/MinC/Governo Federal (art. 21).
A85: Administração do projeto (custos vinculados) | B85: Custos de acessibilidade, comunicação e divulgação | C85: Assessoria de imprensa | D85: Mês | E85: mês | F85: 1 | G85: 1 | H85: 4500 | I85: =F85*G85*H85 -> 4500 | J85: MG - Belo Horizonte | K85: 2.500 – 4.000 – 6.000 | L85: dentro da faixa | M85: Lançamento das inscrições e da mostra.
A86: Administração do projeto (custos vinculados) | B86: Custos de acessibilidade, comunicação e divulgação | C86: Impulsionamento/mídia digital segmentada por território | D86: Verba | E86: verba | F86: 1 | G86: 1 | H86: 4000 | I86: =F86*G86*H86 -> 4000 | J86: MG - Belo Horizonte | K86: 1.000 – 3.000 – 10.000 | L86: dentro da faixa | M86: Foco em jovens de periferias de BH/Contagem e escolas públicas.
A87: Administração do projeto (custos vinculados) | B87: Custos de acessibilidade, comunicação e divulgação | C87: Impressão de cartazes A3 | D87: Unidade | E87: unidade | F87: 400 | G87: 1 | H87: 2.5 | I87: =F87*G87*H87 -> 1000 | J87: MG - Belo Horizonte e Contagem (3 núcleos) | K87: s/ ref. | M87: Escolas, CRAS, centros culturais dos 3 territórios.
A88: Administração do projeto (custos vinculados) | B88: Custos de acessibilidade, comunicação e divulgação | C88: Impressão de folders/filipetas | D88: Unidade | E88: milheiro | F88: 4 | G88: 1 | H88: 450 | I88: =F88*G88*H88 -> 1800 | J88: MG - Belo Horizonte e Contagem (3 núcleos) | K88: s/ ref. | M88: 4.000 unidades para mobilização comunitária.
A89: Administração do projeto (custos vinculados) | B89: Custos de acessibilidade, comunicação e divulgação | C89: Banners/lonas de sinalização (núcleos e mostra) | D89: Unidade | E89: m² | F89: 16 | G89: 1 | H89: 65 | I89: =F89*G89*H89 -> 1040 | J89: MG - Belo Horizonte e Contagem (3 núcleos) | K89: 66 – 95 – 170 | L89: abaixo da referência – confirmar viabilidade | M89: 4 banners de 4 m².
A91: Custos de administração: detalhado x disponível pelo percentual | B91: =SUMIFS($I$77:$I$89,$B$77:$B$89,"Custos de administração") -> 31340 | C91: =B17 -> 31480 | D91: =C91-B91 -> 140 | E91: =IF(D91>=0,"OK","EXCEDE") -> OK
A92: Custos de acessibilidade, comunicação e divulgação: detalhado x disponível pelo percentual | B92: =SUMIFS($I$77:$I$89,$B$77:$B$89,"Custos de acessibilidade, comunicação e divulgação") -> 33090 | C92: =B18 -> 35415 | D92: =C92-B92 -> 2325 | E92: =IF(D92>=0,"OK","EXCEDE") -> OK
A93: Colunas: B = detalhado; C = valor que o percentual libera; D = saldo (reserva).
A95: Premissas do orçamento
A96: • 9 turmas x 30 vagas; 24h por turma (8 encontros de 2h + 4h visita técnica + 4h mostra) = 216 horas-aula de educador titular.
A97: • Matriz adotada: Iluminação 3 turmas, Audiovisual 2, Figurino 2, Maquiagem 2; monitores técnicos apenas em iluminação e maquiagem.
A98: • Espaços dos núcleos e da mostra cedidos por parceiros (sem locação de imóvel); equipamentos didáticos locados.
A99: • 1 visita técnica por turma com ônibus fretado; 3 ônibus no dia da mostra.
A100: • Equipe de coordenação contratada como PJ/MEI; educadores, monitores, mediadores, direção da mostra, técnicos e montadores como PF (base do INSS 20%).
A101: • Execução jun–dez/2027 (2 meses de pré, 4 de produção, 1 de pós); contador por 7 meses.
A102: • Valores unitários do catálogo precos_base.csv, majoritariamente no valor de referência ou no piso da faixa.
A103: • Ajuste de fechamento: R$ -5.199,21 aplicado em 'Educadores(as) dos eixos – oficinas. visita e mostra' para fechar o valor total com percentuais inteiros,
A105: Versão mínima (valor 'Mín.' da planilha do cliente) | B105: 100000
...

Sheet P02 Mestres e Aprendizes
A1: P02 – Mestres e Aprendizes | Planilha orçamentária no padrão SALIC (IN MinC 29/2026)
A2: Proponente (planilha / pasta Drive / tipo) | B2: Aver Mídia / Aver Mídia / PJ
A3: Produto principal (maior custo) e enquadramento | B3: Percursos continuados de transmissão de saberes tradicionais conduzidos por 4 mestres (4 turmas x 48h, 120 aprendizes) – Patrimônio Cultural / Salvaguarda do patrimônio cultural imaterial → Art. 18
A4: Público estimado | B4: 120 aprendizes (beneficiários diretos) + ~1.500 visitantes na exposição + alcance digital do catálogo/vídeos (contado à parte).
A5: Municípios | B5: Belo Horizonte e Região Metropolitana (municípios a definir conforme mestres) – MG.
A6: Execução | B6: 8 meses (jul/2027 a fev/2028)
A7: Valor pré-planejado (planilha do cliente) | B7: 400000
A9: Resumo – o que vai ao SALIC
A10: Etapa / componente | B10: Valor (R$) | C10: % do valor do projeto | D10: Limite IN 29 | E10: Situação
A11: Pré-produção / Preparação | B11: =SUMIFS($I$26:$I$65,$B$26:$B$65,A11) -> 30700 | C11: =IF($B$16=0,0,B11/$B$16) -> 0.099008304
A12: Produção / Execução | B12: =SUMIFS($I$26:$I$65,$B$26:$B$65,A12) -> 230555 | C12: =IF($B$16=0,0,B12/$B$16) -> 0.74354592
A13: Pós-produção | B13: =SUMIFS($I$26:$I$65,$B$26:$B$65,A13) -> 14500 | C13: =IF($B$16=0,0,B13/$B$16) -> 0.04676288
A14: Assessoria contábil e jurídica | B14: =SUMIFS($I$26:$I$65,$B$26:$B$65,A14) -> 13600 | C14: =IF($B$16=0,0,B14/$B$16) -> 0.043860356
A15: Recolhimentos | B15: =SUMIFS($I$26:$I$65,$B$26:$B$65,A15) -> 20720 | C15: =IF($B$16=0,0,B15/$B$16) -> 0.066822543
A16: VALOR DO PROJETO (base de cálculo – soma das 5 etapas) | B16: =SUM(B11:B15) -> 310075
A17: Custos de administração (percentual escolhido no SALIC) | B17: =$B$16*C17 -> 24806 | C17: 0.08 | D17: ='Parâmetros IN 29'!$B$4 -> 0.15 | E17: =IF(AND(C17<=D17),"OK","EXCEDE") -> OK
A18: Custos de acessibilidade, comunicação e divulgação acessíveis (percentual no SALIC) | B18: =$B$16*C18 -> 34108.25 | C18: 0.11 | D18: ='Parâmetros IN 29'!$B$5 -> 0.2 | E18: =IF(AND(C18<=D18),"OK","EXCEDE") -> OK
A19: Remuneração para captação de recursos (percentual no SALIC; teto R$ 150 mil) | B19: =MIN($B$16*C19,'Parâmetros IN 29'!$B$7) -> 31007.5 | C19: 0.1 | D19: ='Parâmetros IN 29'!$B$6 -> 0.1 | E19: =IF(AND(C19<=D19,B19<='Parâmetros IN 29'!$B$7),"OK","EXCEDE") -> OK
A20: VALOR TOTAL DO PROJETO (valor solicitado) | B20: =B16+B17+B18+B19 -> 399996.75
A21: Diferença para o valor pré-planejado | B21: =B20-B7 -> -3.25
A22: Teto por projeto aplicável (PF R$ 500 mil / PJ R$ 1,5 mi) | B22: ='Parâmetros IN 29'!$B$9 -> 1500000 | C22: PJ | E22: =IF(B20<=B22,"OK","EXCEDE") -> OK
A23: Percentuais (células amarelas) são inteiros escolhidos para cobrir o detalhamento interno abaixo da planilha. Altere-os aqui e no SALIC.
A24: Planilha orçamentária analítica – itens a lançar no SALIC (Orçamento do projeto > Custos por produtos)
A25: Produto | B25: Etapa (aba do SALIC) | C25: Item | D25: Unidade SALIC | E25: Unidade de cálculo | F25: Quantidade | G25: Ocorrência | H25: Valor unitário (R$) | I25: Valor total (R$) | J25: Local (UF – município) | K25: Referência de mercado mín–típ–máx (R$) | L25: Alerta de preço | M25: Justificativa / memória de cálculo
A26: Percursos de transmissão de saberes – salvaguarda do patrimônio imaterial (principal) | B26: Pré-produção / Preparação | C26: Coordenação geral (dedicação parcial) | D26: Mês | E26: mês | F26: 1 | G26: 1 | H26: 3500 | I26: =F26*G26*H26 -> 3500 | J26: MG - Belo Horizonte | K26: 3.500 – 5.500 – 8.000 | L26: dentro da faixa | M26: Jul/2027. Dedicação de ~50%: metade do piso da faixa (7.000) – projeto com 4 turmas semanais de 2h.
A27: Percursos de transmissão de saberes – salvaguarda do patrimônio imaterial (principal) | B27: Pré-produção / Preparação | C27: Coordenação pedagógica/curatorial (dedicação parcial) | D27: Mês | E27: mês | F27: 1 | G27: 1 | H27: 4000 | I27: =F27*G27*H27 -> 4000 | J27: MG - Belo Horizonte | K27: 3.000 – 4.500 – 6.500 | L27: dentro da faixa | M27: Jul/2027: curadoria, convite aos mestres, plano formativo e protocolo de saberes sensíveis. ~60% de dedicação.
A28: Percursos de transmissão de saberes – salvaguarda do patrimônio imaterial (principal) | B28: Pré-produção / Preparação | C28: Produtor(a) executivo(a) (dedicação parcial) | D28: Mês | E28: mês | F28: 1 | G28: 1 | H28: 4000 | I28: =F28*G28*H28 -> 4000 | J28: MG - Belo Horizonte | K28: 3.500 – 5.500 – 8.000 | L28: dentro da faixa | M28: Jul/2027: mapeamento e vistoria de espaços, cessões, compras.
A29: Percursos de transmissão de saberes – salvaguarda do patrimônio imaterial (principal) | B29: Pré-produção / Preparação | C29: Pesquisa curatorial e dossiê de reconhecido valor cultural por saber (Anexo II 8.1.1–8.1.5) | D29: Serviço | E29: serviço | F29: 4 | G29: 1 | H29: 1800 | I29: =F29*G29*H29 -> 7200 | J29: MG - Belo Horizonte e Região Metropolitana | K29: s/ ref. | M29: 1 dossiê por saber (histórico, referências, registros, relatório do bem e justificativa) – exigido para o enquadramento em Patrimônio Cultural sem acautelamento formal.
A30: Percursos de transmissão de saberes – salvaguarda do patrimônio imaterial (principal) | B30: Pré-produção / Preparação | C30: Articulação territorial (mobilização de escolas, comunidades e coletivos) | D30: Mês | E30: mês | F30: 1 | G30: 2 | H30: 3000 | I30: =F30*G30*H30 -> 6000 | J30: MG - Belo Horizonte e Região Metropolitana | K30: s/ ref. | M30: Jul–ago/2027: reserva de vagas e mobilização; sem código no catálogo, abaixo de assistente de produção.
A31: Percursos de transmissão de saberes – salvaguarda do patrimônio imaterial (principal) | B31: Pré-produção / Preparação | C31: Cachê dos mestres – participação na concepção do plano formativo e do protocolo de registro | D31: Cachê | E31: cachê | F31: 4 | G31: 1 | H31: 1500 | I31: =F31*G31*H31 -> 6000 | J31: MG - Belo Horizonte e Região Metropolitana | K31: 800 – 1.500 – 3.500 | L31: dentro da faixa | M31: 4 mestres; garante participação dos detentores na concepção (pergunta específica 2).
A32: Percursos de transmissão de saberes – salvaguarda do patrimônio imaterial (principal) | B32: Produção / Execução | C32: Coordenação geral (dedicação parcial) | D32: Mês | E32: mês | F32: 1 | G32: 6 | H32: 3500 | I32: =F32*G32*H32 -> 21000 | J32: MG - Belo Horizonte | K32: 3.500 – 5.500 – 8.000 | L32: dentro da faixa | M32: Ago/2027–jan/2028.
A33: Percursos de transmissão de saberes – salvaguarda do patrimônio imaterial (principal) | B33: Produção / Execução | C33: Coordenação pedagógica/curatorial (dedicação parcial) | D33: Mês | E33: mês | F33: 1 | G33: 6 | H33: 4000 | I33: =F33*G33*H33 -> 24000 | J33: MG - Belo Horizonte | K33: 3.000 – 4.500 – 6.500 | L33: dentro da faixa | M33: Acompanhamento dos 4 percursos, encontros integrados e avaliação.
A34: Percursos de transmissão de saberes – salvaguarda do patrimônio imaterial (principal) | B34: Produção / Execução | C34: Produtor(a) executivo(a) (dedicação parcial) | D34: Mês | E34: mês | F34: 1 | G34: 5 | H34: 4000 | I34: =F34*G34*H34 -> 20000 | J34: MG - Belo Horizonte | K34: 3.500 – 5.500 – 8.000 | L34: dentro da faixa | M34: Ago–dez/2027; em jan–fev a produção da exposição é coberta pela coordenação.
A35: Percursos de transmissão de saberes – salvaguarda do patrimônio imaterial (principal) | B35: Produção / Execução | C35: Mestres(as) – condução dos percursos de transmissão (24 encontros de 2h por turma) | D35: Mês | E35: mês | F35: 4 | G35: 6 | H35: 2716 | I35: =F35*G35*H35 -> 65184 | J35: MG - Belo Horizonte e Região Metropolitana | K35: s/ ref. | M35: 4 mestres x 6 meses x R$2.800 (≈R$700 por encontro de 2h com preparação e acompanhamento). Faixa 2.500–4.500. [Linha de equilíbrio: ajustada em R$ -2,013.48 para fechar o valor total com os percentuais de custos vinculados escolhidos no SALIC.]
A36: Percursos de transmissão de saberes – salvaguarda do patrimônio imaterial (principal) | B36: Produção / Execução | C36: Materiais e insumos por aprendiz (linhas, tecidos, argila, esmaltes, madeira, tintas, cordas) | D36: Unidade | E36: kit/participante | F36: 120 | G36: 1 | H36: 90 | I36: =F36*G36*H36 -> 10800 | J36: MG - Belo Horizonte e Região Metropolitana | K36: s/ ref. | M36: 120 aprendizes x 48h de prática continuada; kit acima da referência por ser percurso de 6 meses.
A37: Percursos de transmissão de saberes – salvaguarda do patrimônio imaterial (principal) | B37: Produção / Execução | C37: Serviço de queima de cerâmica (forno) | D37: Verba | E37: verba | F37: 1 | G37: 1 | H37: 2000 | I37: =F37*G37*H37 -> 2000 | J37: MG - Belo Horizonte e Região Metropolitana | K37: s/ ref. | M37: Percurso de cerâmica; queimas das peças da exposição.
A38: Percursos de transmissão de saberes – salvaguarda do patrimônio imaterial (principal) | B38: Produção / Execução | C38: Violas caipiras para o percurso de viola (aquisição justificada) | D38: Unidade | E38: unidade | F38: 10 | G38: 1 | H38: 600 | I38: =F38*G38*H38 -> 6000 | J38: MG - Belo Horizonte e Região Metropolitana | K38: s/ ref. | M38: 10 instrumentos de estudo; aquisição mais econômica que 6 meses de locação (art. 30); destinação final declarada a ponto de cultura/escola pública.
A39: Percursos de transmissão de saberes – salvaguarda do patrimônio imaterial (principal) | B39: Produção / Execução | C39: Ferramentas e EPIs (bastidores, estecas, formões, luvas, óculos) | D39: Verba | E39: verba | F39: 1 | G39: 1 | H39: 3000 | I39: =F39*G39*H39 -> 3000 | J39: MG - Belo Horizonte e Região Metropolitana | K39: s/ ref. | M39: Segurança e prática nas linguagens com ferramentas cortantes.
A40: Percursos de transmissão de saberes – salvaguarda do patrimônio imaterial (principal) | B40: Produção / Execução | C40: Lanche nos encontros integrados, vivências e acolhimento | D40: Unidade | E40: unidade | F40: 120 | G40: 6 | H40: 10 | I40: =F40*G40*H40 -> 7200 | J40: MG - Belo Horizonte e Região Metropolitana | K40: s/ ref. | M40: 120 aprendizes x 6 encontros de maior duração.
A41: Percursos de transmissão de saberes – salvaguarda do patrimônio imaterial (principal) | B41: Produção / Execução | C41: Ônibus para vivências comunitárias nos territórios dos mestres | D41: Unidade | E41: diária | F41: 2 | G41: 1 | H41: 2500 | I41: =F41*G41*H41 -> 5000 | J41: MG - Belo Horizonte e Região Metropolitana | K41: 1.500 – 2.200 – 3.500 | L41: dentro da faixa | M41: 2 vivências (turmas reunidas) – encontros integrados previstos na metodologia.
A42: Percursos de transmissão de saberes – salvaguarda do patrimônio imaterial (principal) | B42: Produção / Execução | C42: Van para transporte de materiais e mestres | D42: Unidade | E42: diária | F42: 3 | G42: 1 | H42: 1000 | I42: =F42*G42*H42 -> 3000 | J42: MG - Belo Horizonte e Região Metropolitana | K42: 750 – 1.000 – 1.500 | L42: dentro da faixa | M42: Distribuição de materiais/ferramentas aos 4 espaços e transporte dos mestres às vivências.
A43: Percursos de transmissão de saberes – salvaguarda do patrimônio imaterial (principal) | B43: Produção / Execução | C43: Registro fotográfico dos percursos (com protocolo de saberes sensíveis) | D43: Unidade | E43: diária | F43: 1 | G43: 8 | H43: 900 | I43: =F43*G43*H43 -> 7200 | J43: MG - Belo Horizonte e Região Metropolitana | K43: 500 – 800 – 1.500 | L43: dentro da faixa | M43: 2 diárias por turma; base do catálogo e do acervo.
A44: Percursos de transmissão de saberes – salvaguarda do patrimônio imaterial (principal) | B44: Produção / Execução | C44: Registro audiovisual (depoimentos e processos autorizados) | D44: Unidade | E44: diária | F44: 1 | G44: 2 | H44: 1800 | I44: =F44*G44*H44 -> 3600 | J44: MG - Belo Horizonte e Região Metropolitana | K44: 900 – 1.400 – 2.500 | L44: dentro da faixa | M44: Captação de depoimentos dos 4 mestres para vídeos de memória.
A45: Exposição Mestres e Aprendizes (secundário) | B45: Produção / Execução | C45: Projeto expográfico e curadoria da exposição | D45: Serviço | E45: serviço | F45: 1 | G45: 1 | H45: 8000 | I45: =F45*G45*H45 -> 8000 | J45: MG - Belo Horizonte | K45: s/ ref. | M45: Projeto expográfico com layout e especificações (Anexo II 4.3), elaborado com os mestres.
A46: Exposição Mestres e Aprendizes (secundário) | B46: Produção / Execução | C46: Mobiliário expositivo, suportes e montagem (verba de ajuste) | D46: Verba | E46: verba | F46: 1 | G46: 1 | H46: 4871 | I46: =F46*G46*H46 -> 4871 | J46: MG - Belo Horizonte | K46: s/ ref. | M46: Locação/confecção de bases, vitrines e suportes; linha usada para arredondamento ao valor-alvo.
A47: Exposição Mestres e Aprendizes (secundário) | B47: Produção / Execução | C47: Montadores | D47: Unidade | E47: diária | F47: 2 | G47: 3 | H47: 300 | I47: =F47*G47*H47 -> 1800 | J47: MG - Belo Horizonte | K47: 200 – 300 – 400 | L47: dentro da faixa | M47: Montagem e desmontagem.
A48: Exposição Mestres e Aprendizes (secundário) | B48: Produção / Execução | C48: Frete de peças e mobiliário | D48: Unidade | E48: diária | F48: 1 | G48: 1 | H48: 2200 | I48: =F48*G48*H48 -> 2200 | J48: MG - Belo Horizonte | K48: 1.200 – 1.500 – 2.500 | L48: dentro da faixa | M48: Transporte dos trabalhos dos 4 espaços ao local da exposição.
A49: Exposição Mestres e Aprendizes (secundário) | B49: Produção / Execução | C49: Impressão de painéis expográficos e legendas | D49: Unidade | E49: m² | F49: 20 | G49: 1 | H49: 65 | I49: =F49*G49*H49 -> 1300 | J49: MG - Belo Horizonte | K49: 66 – 95 – 170 | L49: abaixo da referência – confirmar viabilidade | M49: Textos de parede com fonte ampliada e contraste.
A50: Exposição Mestres e Aprendizes (secundário) | B50: Produção / Execução | C50: Mediadores culturais da exposição | D50: Unidade | E50: hora | F50: 2 | G50: 32 | H50: 100 | I50: =F50*G50*H50 -> 6400 | J50: MG - Belo Horizonte | K50: 80 – 130 – 200 | L50: dentro da faixa | M50: 2 mediadores x 8 dias x 4h.
A51: Exposição Mestres e Aprendizes (secundário) | B51: Produção / Execução | C51: Cachê dos mestres – demonstração/abertura da exposição | D51: Cachê | E51: cachê | F51: 4 | G51: 1 | H51: 1500 | I51: =F51*G51*H51 -> 6000 | J51: MG - Belo Horizonte | K51: 800 – 1.500 – 3.500 | L51: dentro da faixa | M51: Demonstração pública dos saberes na abertura (crédito e remuneração ao detentor).
A52: Exposição Mestres e Aprendizes (secundário) | B52: Produção / Execução | C52: Seguro das peças expostas | D52: Unidade | E52: apólice | F52: 1 | G52: 1 | H52: 1500 | I52: =F52*G52*H52 -> 1500 | J52: MG - Belo Horizonte | K52: 800 – 2.000 – 5.000 | L52: dentro da faixa | M52: Peças dos mestres e aprendizes.
A53: Exposição Mestres e Aprendizes (secundário) | B53: Produção / Execução | C53: Catálogo – textos, pesquisa e revisão | D53: Serviço | E53: serviço | F53: 1 | G53: 1 | H53: 3000 | I53: =F53*G53*H53 -> 3000 | J53: MG - Belo Horizonte | K53: s/ ref. | M53: Trajetórias, saberes e créditos aprovados pelos mestres.
A54: Exposição Mestres e Aprendizes (secundário) | B54: Produção / Execução | C54: Catálogo – design editorial e versão digital acessível | D54: Serviço | E54: serviço | F54: 1 | G54: 1 | H54: 4000 | I54: =F54*G54*H54 -> 4000 | J54: MG - Belo Horizonte | K54: 2.500 – 4.000 – 7.000 | L54: dentro da faixa | M54: PDF acessível (texto alternativo) + arquivo para impressão.
A55: Exposição Mestres e Aprendizes (secundário) | B55: Produção / Execução | C55: Catálogo – impressão (tiragem reduzida) | D55: Unidade | E55: exemplar | F55: 120 | G55: 1 | H55: 30 | I55: =F55*G55*H55 -> 3600 | J55: MG - Belo Horizonte | K55: s/ ref. | M55: 120 exemplares: mestres, aprendizes, parceiros, bibliotecas públicas e doação de 10% (art. 42, I).
A56: Percursos de transmissão de saberes – salvaguarda do patrimônio imaterial (principal) | B56: Pós-produção | C56: Coordenação geral – encerramento | D56: Mês | E56: mês | F56: 1 | G56: 1 | H56: 3500 | I56: =F56*G56*H56 -> 3500 | J56: MG - Belo Horizonte | K56: 3.500 – 5.500 – 8.000 | L56: dentro da faixa | M56: Fev/2028: relatório e indicadores.
A57: Percursos de transmissão de saberes – salvaguarda do patrimônio imaterial (principal) | B57: Pós-produção | C57: Coordenação pedagógica – avaliação final e relatório de memória | D57: Mês | E57: mês | F57: 1 | G57: 1 | H57: 4000 | I57: =F57*G57*H57 -> 4000 | J57: MG - Belo Horizonte | K57: 3.000 – 4.500 – 6.500 | L57: dentro da faixa | M57: Consolidação das avaliações e relatos dos mestres.
A58: Percursos de transmissão de saberes – salvaguarda do patrimônio imaterial (principal) | B58: Pós-produção | C58: Edição de vídeos de memória (4 vídeos curtos + 1 síntese, legendados) | D58: Serviço | E58: serviço | F58: 1 | G58: 1 | H58: 5000 | I58: =F58*G58*H58 -> 5000 | J58: MG - Belo Horizonte | K58: 1.500 – 3.000 – 5.000 | L58: dentro da faixa | M58: Conteúdo autorizado pelos mestres, publicado gratuitamente.
A59: Percursos de transmissão de saberes – salvaguarda do patrimônio imaterial (principal) | B59: Pós-produção | C59: Organização e catalogação do acervo digital | D59: Serviço | E59: serviço | F59: 1 | G59: 1 | H59: 2000 | I59: =F59*G59*H59 -> 2000 | J59: MG - Belo Horizonte | K59: s/ ref. | M59: Inventário, nomenclatura, backup e matriz de permissões (pendência 21).
A60: Percursos de transmissão de saberes – salvaguarda do patrimônio imaterial (principal) | B60: Assessoria contábil e jurídica | C60: Contador(a) | D60: Mês | E60: mês | F60: 1 | G60: 8 | H60: 1200 | I60: =F60*G60*H60 -> 9600 | J60: MG - Belo Horizonte | K60: 800 – 1.500 – 3.000 | L60: dentro da faixa | M60: Jul/2027–fev/2028.
A61: Percursos de transmissão de saberes – salvaguarda do patrimônio imaterial (principal) | B61: Assessoria contábil e jurídica | C61: Assessoria jurídica (contratos dos mestres, termos de imagem/voz, anuências de saberes coletivos) | D61: Mês | E61: mês | F61: 1 | G61: 2 | H61: 2000 | I61: =F61*G61*H61 -> 4000 | J61: MG - Belo Horizonte | K61: 1.500 – 3.000 – 5.000 | L61: dentro da faixa | M61: Protocolo de direitos e saberes sensíveis (pendência 16).
A62: Percursos de transmissão de saberes – salvaguarda do patrimônio imaterial (principal) | B62: Produção / Execução | C62: Intérprete de Libras (acolhimento, encontros integrados, abertura e visitas mediadas) | D62: Unidade | E62: hora | F62: 1 | G62: 30 | H62: 180 | I62: =F62*G62*H62 -> 5400 | J62: MG - Belo Horizonte e Região Metropolitana | K62: 144 – 192 – 240 | L62: dentro da faixa | M62: Banco de 30h. [Acessibilidade de conteúdo lançada como item do produto, conforme exemplo do Manual do Proponente 2026, p. 47.]
A63: Percursos de transmissão de saberes – salvaguarda do patrimônio imaterial (principal) | B63: Produção / Execução | C63: Audiodescrição da exposição (roteiro + audioguia) | D63: Serviço | E63: serviço | F63: 1 | G63: 1 | H63: 3000 | I63: =F63*G63*H63 -> 3000 | J63: MG - Belo Horizonte | K63: 2.300 – 4.500 – 9.000 | L63: dentro da faixa | M63: Acessibilidade comunicacional do produto secundário. [Acessibilidade de conteúdo lançada como item do produto, conforme exemplo do Manual do Proponente 2026, p. 47.]
A64: Percursos de transmissão de saberes – salvaguarda do patrimônio imaterial (principal) | B64: Produção / Execução | C64: Recursos táteis e textos em braille/ampliados na exposição | D64: Unidade | E64: unidade | F64: 60 | G64: 1 | H64: 25 | I64: =F64*G64*H64 -> 1500 | J64: MG - Belo Horizonte | K64: s/ ref. | M64: Legendas e etiquetas acessíveis. [Acessibilidade de conteúdo lançada como item do produto, conforme exemplo do Manual do Proponente 2026, p. 47.]
A65: Percursos de transmissão de saberes – salvaguarda do patrimônio imaterial (principal) | B65: Recolhimentos | C65: INSS patronal 20% sobre pagamentos a pessoas físicas (RPA) | D65: Verba | E65: verba | F65: 1 | G65: 1 | H65: 20720 | I65: =F65*G65*H65 -> 20720 | J65: MG - Belo Horizonte | K65: s/ ref. | M65: 20% x R$ 103.600 (base estimada de pagamentos a pessoas físicas: mestres R$79.200, dossiês R$7.200, articulação R$6.000, mediadores R$6.400, montadores R$1.800, textos do catálogo R$3.000). ISS não lançado: retido/embutido nas notas de prestadores PJ.
H66: TOTAL | I66: =SUM(I26:I65) -> 310075
A68: Detalhamento interno dos custos vinculados – NÃO lançar itens no SALIC (só o percentual); usar para planejar a execução e a prestação de contas
A69: Componente | B69: Custo vinculado | C69: Item | D69: Unidade SALIC | E69: Unidade de cálculo | F69: Quantidade | G69: Ocorrência | H69: Valor unitário (R$) | I69: Valor total (R$) | J69: Local | K69: Referência de mercado | L69: Alerta de preço | M69: Justificativa
A70: Administração do projeto (custos vinculados) | B70: Custos de administração | C70: Elaboração da proposta cultural (contrato prévio) | D70: Serviço | E70: serviço | F70: 1 | G70: 1 | H70: 10000 | I70: =F70*G70*H70 -> 10000 | J70: MG - Belo Horizonte | K70: 3.000 – 8.000 – 20.000 | L70: dentro da faixa | M70: 2,5% do valor total; pago após aprovação.
A71: Administração do projeto (custos vinculados) | B71: Custos de administração | C71: Elaboração de prestação de contas | D71: Serviço | E71: serviço | F71: 1 | G71: 1 | H71: 6000 | I71: =F71*G71*H71 -> 6000 | J71: MG - Belo Horizonte | K71: s/ ref. | M71: Art. 22, IX.
A72: Administração do projeto (custos vinculados) | B72: Custos de administração | C72: Assistente administrativo-financeiro | D72: Mês | E72: mês | F72: 1 | G72: 2 | H72: 3000 | I72: =F72*G72*H72 -> 6000 | J72: MG - Belo Horizonte | K72: s/ ref. | M72: Meses de contratação e de encerramento.
A73: Administração do projeto (custos vinculados) | B73: Custos de administração | C73: Tarifas bancárias | D73: Mês | E73: mês | F73: 1 | G73: 8 | H73: 80 | I73: =F73*G73*H73 -> 640 | J73: MG - Belo Horizonte | K73: s/ ref.
A74: Administração do projeto (custos vinculados) | B74: Custos de administração | C74: Material de escritório/expediente | D74: Verba | E74: verba | F74: 1 | G74: 1 | H74: 1000 | I74: =F74*G74*H74 -> 1000 | J74: MG - Belo Horizonte | K74: s/ ref. | M74: Listas de presença, termos e fichas.
A75: Administração do projeto (custos vinculados) | B75: Custos de acessibilidade, comunicação e divulgação | C75: Consultor(a) de acessibilidade (espaços, exposição, Guia MDHC) | D75: Mês | E75: mês | F75: 1 | G75: 2 | H75: 3500 | I75: =F75*G75*H75 -> 7000 | J75: MG - Belo Horizonte | K75: s/ ref. | M75: Planejamento (jul) e exposição (fev).
A76: Administração do projeto (custos vinculados) | B76: Custos de acessibilidade, comunicação e divulgação | C76: Equipe de apoio a PcD na exposição | D76: Unidade | E76: diária | F76: 1 | G76: 8 | H76: 250 | I76: =F76*G76*H76 -> 2000 | J76: MG - Belo Horizonte | K76: 200 – 260 – 380 | L76: dentro da faixa | M76: 8 dias de exposição.
A77: Administração do projeto (custos vinculados) | B77: Custos de acessibilidade, comunicação e divulgação | C77: Designer gráfico (identidade e peças, com marcas obrigatórias) | D77: Serviço | E77: serviço | F77: 1 | G77: 1 | H77: 5000 | I77: =F77*G77*H77 -> 5000 | J77: MG - Belo Horizonte | K77: 2.500 – 4.000 – 7.000 | L77: dentro da faixa | M77: Identidade que não use referências tradicionais como ornamento descontextualizado (item 19).
A78: Administração do projeto (custos vinculados) | B78: Custos de acessibilidade, comunicação e divulgação | C78: Gestão de redes sociais e conteúdo acessível | D78: Mês | E78: mês | F78: 1 | G78: 3 | H78: 3800 | I78: =F78*G78*H78 -> 11400 | J78: MG - Belo Horizonte | K78: 1.200 – 2.500 – 4.000 | L78: dentro da faixa | M78: Inscrições, trajetórias dos mestres e exposição.
A79: Administração do projeto (custos vinculados) | B79: Custos de acessibilidade, comunicação e divulgação | C79: Assessoria de imprensa | D79: Mês | E79: mês | F79: 1 | G79: 1 | H79: 4500 | I79: =F79*G79*H79 -> 4500 | J79: MG - Belo Horizonte | K79: 2.500 – 4.000 – 6.000 | L79: dentro da faixa | M79: Lançamento da exposição.
A80: Administração do projeto (custos vinculados) | B80: Custos de acessibilidade, comunicação e divulgação | C80: Impulsionamento/mídia digital | D80: Verba | E80: verba | F80: 1 | G80: 1 | H80: 2500 | I80: =F80*G80*H80 -> 2500 | J80: MG - Belo Horizonte | K80: 1.000 – 3.000 – 10.000 | L80: dentro da faixa | M80: Inscrições e exposição.
A81: Administração do projeto (custos vinculados) | B81: Custos de acessibilidade, comunicação e divulgação | C81: Impressão de cartazes A3 | D81: Unidade | E81: unidade | F81: 300 | G81: 1 | H81: 2.5 | I81: =F81*G81*H81 -> 750 | J81: MG - Belo Horizonte e Região Metropolitana | K81: s/ ref.
A82: Administração do projeto (custos vinculados) | B82: Custos de acessibilidade, comunicação e divulgação | C82: Impressão de folders/filipetas | D82: Unidade | E82: milheiro | F82: 2 | G82: 1 | H82: 450 | I82: =F82*G82*H82 -> 900 | J82: MG - Belo Horizonte e Região Metropolitana | K82: s/ ref.
A84: Custos de administração: detalhado x disponível pelo percentual | B84: =SUMIFS($I$70:$I$82,$B$70:$B$82,"Custos de administração") -> 23640 | C84: =B17 -> 24806 | D84: =C84-B84 -> 1166 | E84: =IF(D84>=0,"OK","EXCEDE") -> OK
A85: Custos de acessibilidade, comunicação e divulgação: detalhado x disponível pelo percentual | B85: =SUMIFS($I$70:$I$82,$B$70:$B$82,"Custos de acessibilidade, comunicação e divulgação") -> 34050 | C85: =B18 -> 34108.25 | D85: =C85-B85 -> 58.25 | E85: =IF(D85>=0,"OK","EXCEDE") -> OK
A86: Colunas: B = detalhado; C = valor que o percentual libera; D = saldo (reserva).
A88: Premissas do orçamento
A89: • 4 mestres, 4 turmas de até 30 aprendizes, 24 encontros de 2h (48h) por turma, 6 meses de formação (ago/2027–jan/2028).
A90: • Mestres remunerados por mês (R$ 2.800 ≈ R$ 700/encontro com preparação) + cachês de concepção e de demonstração na abertura.
A91: • Coordenação geral, pedagógica e produção em dedicação parcial (valores abaixo do piso do catálogo, justificados).
A92: • Espaços de formação e de exposição cedidos por parceiros; exposição de 8 dias com mediação.
A93: • Catálogo digital acessível + 120 exemplares impressos; 4 vídeos curtos + 1 síntese.
A94: • Mestres, pesquisadores, articulação, mediadores, montadores e redator como PF (base INSS 20%); demais PJ/MEI.
A95: • Ajuste de fechamento: R$ -2.013,48 aplicado em 'Mestres(as) – condução dos percursos de transmissão (24 encontros de 2h por turma)' para fechar o valor total com percentuais inteiros,
A97: Versão mínima (valor 'Mín.' da planilha do cliente) | B97: 80000
A98: 2 mestres/2 turmas (60 aprendizes) mantendo 24 encontros de 2h; coordenação única (geral + pedagógica) em dedicação parcial e sem produtor executivo; materiais só dos 2 saberes; sem ônibus de vivências; exposição simplificada (1 semana) no espaço parceiro sem projeto expográfico contratado; catálogo apenas digital; registro fotográfico + 1 vídeo síntese; Libras na abertura e AD/recursos táteis na exposição; divulgação digital. Custos vinculados proporcionais.

Sheet P03 Cultura Viva nas Vilas
A1: P03 – Cultura Viva nas Vilas | Planilha orçamentária no padrão SALIC (IN MinC 29/2026)
A2: Proponente (planilha / pasta Drive / tipo) | B2: IHV / IHV / PJ
A3: Produto principal (maior custo) e enquadramento | B3: Oficinas de formação artística em cultura urbana – música e musicalidade, grafite e audiovisual (8 oficinas x 24h, 200 participantes) – Artes Visuais / Empreend Ações Educ-Cult/Capacitação/Treinamento → Art. 18
A4: Público estimado | B4: 200 participantes distintos nas oficinas + 800 a 1.000 participações de público nas 4 mostras.
A5: Municípios | B5: Belo Horizonte (Serra/Vila Marçola, Lagoinha, Cabana do Pai Tomás) e Contagem (Eldorado) – MG.
A6: Execução | B6: 6 meses (abr a set/2027)
A7: Valor pré-planejado (planilha do cliente) | B7: 200000
A9: Resumo – o que vai ao SALIC
A10: Etapa / componente | B10: Valor (R$) | C10: % do valor do projeto | D10: Limite IN 29 | E10: Situação
A11: Pré-produção / Preparação | B11: =SUMIFS($I$26:$I$51,$B$26:$B$51,A11) -> 14000 | C11: =IF($B$16=0,0,B11/$B$16) -> 0.090320833
A12: Produção / Execução | B12: =SUMIFS($I$26:$I$51,$B$26:$B$51,A12) -> 117771 | C12: =IF($B$16=0,0,B12/$B$16) -> 0.7597982
A13: Pós-produção | B13: =SUMIFS($I$26:$I$51,$B$26:$B$51,A13) -> 6000 | C13: =IF($B$16=0,0,B13/$B$16) -> 0.038708928
A14: Assessoria contábil e jurídica | B14: =SUMIFS($I$26:$I$51,$B$26:$B$51,A14) -> 7200 | C14: =IF($B$16=0,0,B14/$B$16) -> 0.046450714
A15: Recolhimentos | B15: =SUMIFS($I$26:$I$51,$B$26:$B$51,A15) -> 10032 | C15: =IF($B$16=0,0,B15/$B$16) -> 0.064721328
A16: VALOR DO PROJETO (base de cálculo – soma das 5 etapas) | B16: =SUM(B11:B15) -> 155003
A17: Custos de administração (percentual escolhido no SALIC) | B17: =$B$16*C17 -> 10850.21 | C17: 0.07 | D17: ='Parâmetros IN 29'!$B$4 -> 0.15 | E17: =IF(AND(C17<=D17),"OK","EXCEDE") -> OK
A18: Custos de acessibilidade, comunicação e divulgação acessíveis (percentual no SALIC) | B18: =$B$16*C18 -> 18600.36 | C18: 0.12 | D18: ='Parâmetros IN 29'!$B$5 -> 0.2 | E18: =IF(AND(C18<=D18),"OK","EXCEDE") -> OK
A19: Remuneração para captação de recursos (percentual no SALIC; teto R$ 150 mil) | B19: =MIN($B$16*C19,'Parâmetros IN 29'!$B$7) -> 15500.3 | C19: 0.1 | D19: ='Parâmetros IN 29'!$B$6 -> 0.1 | E19: =IF(AND(C19<=D19,B19<='Parâmetros IN 29'!$B$7),"OK","EXCEDE") -> OK
A20: VALOR TOTAL DO PROJETO (valor solicitado) | B20: =B16+B17+B18+B19 -> 199953.87
A21: Diferença para o valor pré-planejado | B21: =B20-B7 -> -46.13
A22: Teto por projeto aplicável (PF R$ 500 mil / PJ R$ 1,5 mi) | B22: ='Parâmetros IN 29'!$B$9 -> 1500000 | C22: PJ | E22: =IF(B20<=B22,"OK","EXCEDE") -> OK
A23: Percentuais (células amarelas) são inteiros escolhidos para cobrir o detalhamento interno abaixo da planilha. Altere-os aqui e no SALIC.
A24: Planilha orçamentária analítica – itens a lançar no SALIC (Orçamento do projeto > Custos por produtos)
A25: Produto | B25: Etapa (aba do SALIC) | C25: Item | D25: Unidade SALIC | E25: Unidade de cálculo | F25: Quantidade | G25: Ocorrência | H25: Valor unitário (R$) | I25: Valor total (R$) | J25: Local (UF – município) | K25: Referência de mercado mín–típ–máx (R$) | L25: Alerta de preço | M25: Justificativa / memória de cálculo
A26: Oficinas de formação artística – música e musicalidade, grafite e audiovisual (principal) | B26: Pré-produção / Preparação | C26: Coordenação geral (dedicação parcial) | D26: Mês | E26: mês | F26: 1 | G26: 2 | H26: 3000 | I26: =F26*G26*H26 -> 6000 | J26: MG - Belo Horizonte | K26: 3.500 – 5.500 – 8.000 | L26: abaixo da referência – confirmar viabilidade | M26: Abr–mai/2027: anuências, vistorias, contratações, inscrições. Dedicação ~40% (abaixo do piso de 7.000 por ser projeto de R$ 200 mil).
A27: Oficinas de formação artística – música e musicalidade, grafite e audiovisual (principal) | B27: Pré-produção / Preparação | C27: Curadoria artística e coordenação pedagógica | D27: Mês | E27: mês | F27: 1 | G27: 2 | H27: 4000 | I27: =F27*G27*H27 -> 8000 | J27: MG - Belo Horizonte (Vila Marçola, Lagoinha, Cabana do Pai Tomás) e Contagem (Eldorado) | K27: 3.000 – 5.000 – 7.000 | L27: dentro da faixa | M27: Abr–mai/2027: mapeamento de artistas/Pontos de Cultura, seleção dos 6+ oficineiros, plano pedagógico (Anexo II 7.3). Funções unificadas; dedicação parcial.
A28: Oficinas de formação artística – música e musicalidade, grafite e audiovisual (principal) | B28: Produção / Execução | C28: Coordenação geral (dedicação parcial) | D28: Mês | E28: mês | F28: 1 | G28: 3 | H28: 3000 | I28: =F28*G28*H28 -> 9000 | J28: MG - Belo Horizonte | K28: 3.500 – 5.500 – 8.000 | L28: abaixo da referência – confirmar viabilidade | M28: Jun–ago/2027: oficinas e mostras.
A29: Oficinas de formação artística – música e musicalidade, grafite e audiovisual (principal) | B29: Produção / Execução | C29: Produtor(a) executivo(a) | D29: Mês | E29: mês | F29: 1 | G29: 3 | H29: 4500 | I29: =F29*G29*H29 -> 13500 | J29: MG - Belo Horizonte (Vila Marçola, Lagoinha, Cabana do Pai Tomás) e Contagem (Eldorado) | K29: 3.500 – 5.500 – 8.000 | L29: dentro da faixa | M29: Jun–ago/2027: logística dos 4 territórios, materiais e produção das 4 mostras. Dedicação parcial (abaixo do piso de 5.500).
A30: Oficinas de formação artística – música e musicalidade, grafite e audiovisual (principal) | B30: Produção / Execução | C30: Curadoria artística e coordenação pedagógica | D30: Mês | E30: mês | F30: 1 | G30: 2 | H30: 4000 | I30: =F30*G30*H30 -> 8000 | J30: MG - Belo Horizonte (Vila Marçola, Lagoinha, Cabana do Pai Tomás) e Contagem (Eldorado) | K30: 3.000 – 5.000 – 7.000 | L30: dentro da faixa | M30: Jun–jul/2027: acompanhamento pedagógico e curadoria das mostras.
A31: Oficinas de formação artística – música e musicalidade, grafite e audiovisual (principal) | B31: Produção / Execução | C31: Artistas-oficineiros(as) (música e musicalidade, grafite, audiovisual) | D31: Unidade | E31: hora-aula | F31: 8 | G31: 24 | H31: 116 | I31: =F31*G31*H31 -> 22272 | J31: MG - Belo Horizonte (Vila Marçola, Lagoinha, Cabana do Pai Tomás) e Contagem (Eldorado) | K31: 80 – 130 – 200 | L31: dentro da faixa | M31: 8 oficinas x 24h (8 encontros semanais de 3h) x R$130; ≥6 profissionais, prioridade para artistas dos territórios. [Linha de equilíbrio: ajustada em R$ -2,652.24 para fechar o valor total com os percentuais de custos vinculados escolhidos no SALIC.]
A32: Oficinas de formação artística – música e musicalidade, grafite e audiovisual (principal) | B32: Produção / Execução | C32: Materiais de grafite (tintas spray e base água, bicos, rolos, EPIs) | D32: Unidade | E32: kit/participante | F32: 75 | G32: 1 | H32: 100 | I32: =F32*G32*H32 -> 7500 | J32: MG - Belo Horizonte (Vila Marçola, Lagoinha, Cabana do Pai Tomás) e Contagem (Eldorado) | K32: s/ ref. | M32: 3 oficinas de grafite x 25 participantes.
A33: Oficinas de formação artística – música e musicalidade, grafite e audiovisual (principal) | B33: Produção / Execução | C33: Materiais de consumo – música e audiovisual (cabos, baquetas, cordas, cartões de memória) | D33: Unidade | E33: kit/participante | F33: 125 | G33: 1 | H33: 40 | I33: =F33*G33*H33 -> 5000 | J33: MG - Belo Horizonte (Vila Marçola, Lagoinha, Cabana do Pai Tomás) e Contagem (Eldorado) | K33: s/ ref. | M33: 3 oficinas de música + 2 de audiovisual x 25 participantes (piso da faixa).
A34: Oficinas de formação artística – música e musicalidade, grafite e audiovisual (principal) | B34: Produção / Execução | C34: Locação de equipamentos audiovisuais (câmeras, microfones, tripés, notebook de edição) | D34: Unidade | E34: diária | F34: 2 | G34: 6 | H34: 250 | I34: =F34*G34*H34 -> 3000 | J34: MG - Belo Horizonte (Vila Marçola, Lagoinha, Cabana do Pai Tomás) e Contagem (Eldorado) | K34: s/ ref. | M34: 2 oficinas de audiovisual x 6 encontros práticos; produção dos curtas exibidos nas mostras.
A35: Oficinas de formação artística – música e musicalidade, grafite e audiovisual (principal) | B35: Produção / Execução | C35: Locação de instrumentos e equipamento de som para oficinas de música | D35: Unidade | E35: kit/mês | F35: 3 | G35: 2 | H35: 500 | I35: =F35*G35*H35 -> 3000 | J35: MG - Belo Horizonte (Vila Marçola, Lagoinha, Cabana do Pai Tomás) e Contagem (Eldorado) | K35: s/ ref. | M35: 3 oficinas x 2 meses (percussão, teclado, caixa amplificada, controladora).
